Workbook
Name beta_observed: #REF!
Name beta_unlev_comps: #REF!
Name conversionfactor: '[10]E&P'!$D$6
Name convfactor: #REF!
Name costdebtfirm: #REF!
Name costequity: #REF!
Name days_per_year: #REF!
Name debt: #REF!
Name debt_weight: #REF!
Name market_equity: #REF!
Name relevered_beta: #REF!
Name risk_free_rate: #REF!
Name risk_premium: #REF!
Name stubyear: #REF!
Name totalcap: #REF!
Name wacc: #REF!

Sheet Transaction Summary
B2: Transaction Summary
B4: Sources & Uses
D5: CLOSE | H5: HOLD
D6: Total | E6: % of Total | F6: Per Unit | H6: Total | I6: % of Total | J6: Per Unit
B7: Uses
B8: Acquisition Costs | D8: =Model!E169 -> 5700000 | E8: =D8/D$14 -> 0.81015393 | F8: =D8/$J$25 -> 19000 | H8: =Model!F169 -> 5700000 | I8: =H8/H$14 -> 0.096904661 | J8: =H8/$J$25 -> 19000
B9: Soft Costs | D9: =Model!E170 -> 0 | E9: =D9/D$14 -> 0 | F9: =D9/$J$25 -> 0 | H9: =Model!F170 -> 5460000 | I9: =H9/H$14 -> 0.092824465 | J9: =H9/$J$25 -> 18200
B10: Hard Costs | D10: =Model!E171 -> 0 | E10: =D10/D$14 -> 0 | F10: =D10/$J$25 -> 0 | H10: =Model!F171 -> 44500000 | I10: =H10/H$14 -> 0.75653639 | J10: =H10/$J$25 -> 148333.33
B11: Other Development Costs | D11: =Model!E172 -> 0 | E11: =D11/D$14 -> 0 | F11: =D11/$J$25 -> 0 | H11: =Model!F172 -> 1750000 | I11: =H11/H$14 -> 0.029751431 | J11: =H11/$J$25 -> 5833.3333
B12: Financing Costs | D12: =Model!E173 -> 1335700 | E12: =D12/D$14 -> 0.18984607 | F12: =D12/$J$25 -> 4452.3333 | H12: =Model!F173 -> 1335700 | I12: =H12/H$14 -> 0.022707992 | J12: =H12/$J$25 -> 4452.3333
B13: Capital Reserves | D13: =Model!E174 -> 0 | E13: =D13/D$14 -> 0 | F13: =D13/$J$25 -> 0 | H13: =Model!F174 -> 75000 | I13: =H13/H$14 -> 0.0012750613 | J13: =H13/$J$25 -> 250
B14: Total Uses | D14: =SUM(D8:D13) -> 7035700 | E14: =SUM(E8:E13) -> 1 | F14: =SUM(F8:F13) -> 23452.333 | H14: =SUM(H8:H13) -> 58820700 | I14: =SUM(I8:I13) -> 1 | J14: =SUM(J8:J13) -> 196069
B16: Sources
B17: Equity | D17: =Model!E178 -> 6100000 | E17: =D17/D$20 -> 0.86700684 | F17: =D17/$J$25 -> 20333.333 | H17: =Model!F178 -> 18749450 | I17: =H17/H$20 -> 0.31875598 | J17: =H17/$J$25 -> 62498.167
B18: Debt | D18: =Model!E179 -> 0 | E18: =D18/D$20 -> 0 | F18: =D18/$J$25 -> 0 | H18: =Model!F179 -> 40000000 | I18: =H18/H$20 -> 0.68003271 | J18: =H18/$J$25 -> 133333.33
B19: Operating Cashflow | D19: =Model!E180 -> 935700 | E19: =D19/D$20 -> 0.13299316 | F19: =D19/$J$25 -> 3119 | H19: =Model!F180 -> 71250 | I19: =H19/H$20 -> 0.0012113083 | J19: =H19/$J$25 -> 237.5
B20: Total Sources | D20: =SUM(D17:D19) -> 7035700 | E20: =SUM(E17:E19) -> 1 | F20: =SUM(F17:F19) -> 23452.333 | H20: =SUM(H17:H19) -> 58820700 | I20: =SUM(I17:I19) -> 1 | J20: =SUM(J17:J19) -> 196069
B22: Returns Summary | H22: Deal Summary
C23: Peak Equity | D23: IRR | E23: Profit | F23: Multiple | H23: Location | J23: ='Inputs & Drivers'!E7 -> Boston, MA
B24: Unlevered Project | C24: {=TRANSPOSE(Model!C100:C103)} -> 57090929 | D24: 0.16394511 | E24: 19459558 | F24: 1.340852 | H24: Vintage | J24: ='Inputs & Drivers'!E9 -> 2015
B25: Levered Project | C25: {=TRANSPOSE(Model!C162:C165)} -> 18749450 | D25: 0.27464951 | E25: 15915270 | F25: 1.8488393 | H25: Total Units | J25: ='Inputs & Drivers'!E8 -> 300
B26: LP | C26: {=TRANSPOSE(Model!C263:C266)} -> 16874505 | D26: 0.22744136 | E26: 11449567 | F26: 1.6785127 | H26: Hold Period | J26: ='Inputs & Drivers'!E13 -> 36
B27: GP | C27: {=TRANSPOSE(Model!C277:C280)} -> 1874945 | D27: 0.60943713 | E27: 4465703 | F27: 3.3817781 | H27: Rentable SF | J27: ='Inputs & Drivers'!F34*'Inputs & Drivers'!C34 -> 289000
B28: GP Project | C28: {=TRANSPOSE(Model!C270:C273)} -> 1874945 | D28: 0.22744136 | E28: 1272174.1 | F28: 1.6785127 | H28: Avg Unit Size | J28: ='Inputs & Drivers'!F34 -> 963.33333
B29: GP Promote | C29: n/a | D29: n/a | E29: =E27-E28 -> 3193528.9 | F29: n/a | H29: Occupancy | J29: ='Inputs & Drivers'!E49 -> 0.93
B31: NOI Summary | H31: Debt Summary
C32: NOI | D32: Growth | E32: NOI YoC | F32: Delta to Exit Cap | H32: Loan Proceeds | J32: ='Inputs & Drivers'!J16 -> 40000000
B33: 1 | C33: {=TRANSPOSE(Model!EM80:ER80)} -> 0 | E33: =C33/$H$20 -> 0 | F33: =E33-$D$42 -> -0.055 | H33: Leverage (Close / Life) | J33: =TEXT(D18/D20,"0%")&" / "&TEXT(H18/H20,"0%") -> 0% / 68%
B34: 2 | C34: 728720.74 | D34: =IFERROR(C34/C33-1,0) -> 0 | E34: =C34/$H$20 -> 0.012388848 | F34: =E34-$D$42 -> -0.042611152 | H34: Rate | J34: ='Inputs & Drivers'!J19 -> 0.051562
B35: 3 | C35: 3639516.9 | D35: =IFERROR(C35/C34-1,0) -> 3.9943919 | E35: =C35/$H$20 -> 0.061874764 | F35: =E35-$D$42 -> 0.0068747641 | H35: Fees | J35: ='Inputs & Drivers'!J24 -> 0.01
B36: 4 | C36: 4032017.8 | D36: =IFERROR(C36/C35-1,0) -> 0.10784421 | E36: =C36/$H$20 -> 0.068547599 | F36: =E36-$D$42 -> 0.013547599 | H36: IO Period | J36: ='Inputs & Drivers'!J21 -> 36
B37: 5 | C37: 4155645.8 | D37: =IFERROR(C37/C36-1,0) -> 0.030661583 | E37: =C37/$H$20 -> 0.070649377 | F37: =E37-$D$42 -> 0.015649377 | H37: Maturity | J37: ='Inputs & Drivers'!J15 -> 45291
B38: 6 | C38: 4283054.1 | D38: =IFERROR(C38/C37-1,0) -> 0.030659086 | E38: =C38/$H$20 -> 0.072815422 | F38: =E38-$D$42 -> 0.017815422
H39: Joint Venture Summary
B40: Exit Summary | H40: GP Equity | J40: ='Inputs & Drivers'!H5 -> 0.1
C41: Fwd NOI | D41: Exit Cap | E41: Total $ | F41: Per Unit | H41: Pref | J41: ='Inputs & Drivers'!I7 -> 0.1
B42: Sale Proceeds | C42: =SUMIF(Model!$H$6:$EJ$6,'Inputs & Drivers'!$E$14,Model!$H$81:$EJ$81) -> 4032017.8 | D42: ='Inputs & Drivers'!E16 -> 0.055 | E42: =C42/D42 -> 73309414 | F42: =E42/$J$25 -> 244364.71 | H42: Hurdle #2 | J42: =TEXT('Inputs & Drivers'!H8,"0.0%")&" after a "&TEXT('Inputs & Drivers'!I7,"0.0%") -> 20.0% after a 10.0%
B43: Less: Sale Costs | E43: =-'Inputs & Drivers'!E15*E42 -> -733094.14 | H43: Hurdle #3 | J43: =TEXT('Inputs & Drivers'!H9,"0.0%")&" after a "&TEXT('Inputs & Drivers'!I8,"0.0%") -> 30.0% after a 15.0%
B44: Net Sale Proceeds | E44: =SUM(E42:E43) -> 72576320 | H44: Hurdle #4 | J44: =TEXT('Inputs & Drivers'!H10,"0.0%")&" after a "&TEXT('Inputs & Drivers'!I9,"0.0%") -> 40.0% after a 20.0%
B45: Less: Outstanding Debt | D45: Value | E45: =SUMIF(Model!$H$6:$EJ$6,'Inputs & Drivers'!$E$14,Model!H154:EJ154) -> -40000000
B46: Less: Equity | D46: Allocation | E46: =-C25 -> -18749450 | H46: Unit Mix
B47: Terminal Value Profit | D47: =E47/$E$49 -> 0.86878011 | E47: =SUM(E44:E46) -> 13826870 | H47: Type | I47: Count | J47: %
B48: Interim Cash Flow | D48: =E48/$E$49 -> 0.13121989 | E48: =E25-E47 -> 2088399.9 | H48: Studio | I48: ='Inputs & Drivers'!C30 -> 15 | J48: =I48/$I$52 -> 0.05
B49: Total Profit | D49: =SUM(D47:D48) -> 1 | E49: =SUM(E47:E48) -> 15915270 | H49: 1 BR, 1 BA | I49: ='Inputs & Drivers'!C31 -> 155 | J49: =I49/$I$52 -> 0.51666667
H50: 2 BR, 2 BA | I50: ='Inputs & Drivers'!C32 -> 130 | J50: =I50/$I$52 -> 0.43333333
B51: Deal Timetable | H51: 3 BR, 2 BA | I51: ='Inputs & Drivers'!C33 -> 0 | J51: =I51/$I$52 -> 0
C52: Start | E52: End | H52: Total | I52: =SUM(I48:I51) -> 300 | J52: =SUM(J48:J51) -> 1
B53: Acquisition | C53: ='Inputs & Drivers'!G38 -> 44196 | D53: ='Inputs & Drivers'!F38 -> 0 | E53: ='Inputs & Drivers'!I38 -> 44196 | F53: ='Inputs & Drivers'!J38 -> 0
B54: Soft Costs | C54: ='Inputs & Drivers'!G39 -> 44286 | D54: ='Inputs & Drivers'!F39 -> 3 | E54: ='Inputs & Drivers'!I39 -> 44865 | F54: ='Inputs & Drivers'!J39 -> 22 | H54: Lease-up Assumptions
B55: Hard Costs | C55: ='Inputs & Drivers'!G40 -> 44408 | D55: ='Inputs & Drivers'!F40 -> 7 | E55: ='Inputs & Drivers'!I40 -> 44865 | F55: ='Inputs & Drivers'!J40 -> 22 | H55: Units Leased / Month | J55: ='Inputs & Drivers'!C37 -> 30
B56: Lease-up | C56: ='Inputs & Drivers'!G41 -> 44681 | D56: ='Inputs & Drivers'!F41 -> 16 | E56: ='Inputs & Drivers'!I41 -> 44957 | F56: ='Inputs & Drivers'!J41 -> 25 | H56: Concessions | J56: ='Inputs & Drivers'!C38 -> 1
B57: Stabilization | C57: ='Inputs & Drivers'!G42 -> 44681 | D57: ='Inputs & Drivers'!F42 -> 16 | E57: ='Inputs & Drivers'!I42 -> 45138 | F57: ='Inputs & Drivers'!J42 -> 31 | H57: Concession Burnoff | J57: ='Inputs & Drivers'!C39 -> 6
B58: Exit | C58: ='Inputs & Drivers'!G43 -> 45291 | D58: ='Inputs & Drivers'!F43 -> 36 | E58: ='Inputs & Drivers'!I43 -> 45291 | F58: ='Inputs & Drivers'!J43 -> 36 | H58: Pre-Construction Leasing | J58: ='Inputs & Drivers'!C40 -> 6
B60: Revenue & Expense Summary
D61: Untrended | E61: =F57+1 -> 32
D62: Stabilized | E62: Stabilized | F62: Year 1 | G62: Year 2 | H62: Year 3 | I62: Year 4 | J62: Year 5
B63: Net Potential Rent | D63: ='Inputs & Drivers'!E53 -> 5328000 | E63: =SUMIF(Model!$H$5:$EJ$5,'Transaction Summary'!$E$61,Model!$H49:$EJ49)*12 -> 5545209.1 | F63: =Model!EM49 -> 0 | G63: =Model!EN49 -> 1624347.5 | H63: =Model!EO49 -> 5479275.1 | I63: =Model!EP49 -> 5692723.1 | J63: =Model!EQ49 -> 5865872.8
B64: Concessions | D64: ='Inputs & Drivers'!E54 -> -444000 | E64: =SUMIF(Model!$H$5:$EJ$5,'Transaction Summary'!$E$61,Model!$H50:$EJ50)*12 -> 0 | F64: =Model!EM50 -> 0 | G64: =Model!EN50 -> -135362.29 | H64: =Model!EO50 -> -263099.16 | I64: =Model!EP50 -> 0 | J64: =Model!EQ50 -> 0
B65: Net Effective Rent | D65: =SUM(D63:D64) -> 4884000 | E65: =SUM(E63:E64) -> 5545209.1 | F65: =SUM(F63:F64) -> 0 | G65: =SUM(G63:G64) -> 1488985.2 | H65: =SUM(H63:H64) -> 5216176 | I65: =SUM(I63:I64) -> 5692723.1 | J65: =SUM(J63:J64) -> 5865872.8
B66: Vacancy Loss | D66: ='Inputs & Drivers'!E56 -> -341880 | E66: =SUMIF(Model!$H$5:$EJ$5,'Transaction Summary'!$E$61,Model!$H52:$EJ52)*12 -> -388164.64 | F66: =Model!EM52 -> 0 | G66: =Model!EN52 -> -134008.67 | H66: =Model!EO52 -> -365132.32 | I66: =Model!EP52 -> -398490.62 | J66: =Model!EQ52 -> -410611.09
B67: Uncollectible Rent | D67: ='Inputs & Drivers'!E57 -> -24420 | E67: =SUMIF(Model!$H$5:$EJ$5,'Transaction Summary'!$E$61,Model!$H53:$EJ54)*12 -> -27726.045 | F67: =SUM(Model!EM53:EM54) -> 0 | G67: =SUM(Model!EN53:EN54) -> -18612.315 | H67: =SUM(Model!EO53:EO54) -> -65202.2 | I67: =SUM(Model!EP53:EP54) -> -71159.039 | J67: =SUM(Model!EQ53:EQ54) -> -73323.409
B68: Other Revenue | D68: ='Inputs & Drivers'!E58 -> -36630 | E68: =SUMIF(Model!$H$5:$EJ$5,'Transaction Summary'!$E$61,Model!$H64:$EJ64)*12 -> 576897.47 | F68: =Model!EM64 -> 0 | G68: =Model!EN64 -> 170117.48 | H68: =Model!EO64 -> 570715.97 | I68: =Model!EP64 -> 587083.18 | J68: =Model!EQ64 -> 598933.07
B69: Total Income | D69: =SUM(D65:D68) -> 4481070 | E69: =SUM(E65:E68) -> 5706215.9 | F69: =SUM(F65:F68) -> 0 | G69: =SUM(G65:G68) -> 1506481.7 | H69: =SUM(H65:H68) -> 5356557.4 | I69: =SUM(I65:I68) -> 5810156.6 | J69: =SUM(J65:J68) -> 5980871.3
B70: Operating Expenses | D70: =-'Inputs & Drivers'!J58 -> -1661932.1 | E70: =SUMIF([11]Model!$H$5:$EJ$5,'[11]Transaction Summary'!$E$61,Model!$H78:$EJ78)*12 -> -1737918.5 | F70: =Model!EM78 -> 0 | G70: =Model!EN78 -> -777760.99 | H70: =Model!EO78 -> -1717040.5 | I70: =Model!EP78 -> -1778138.9 | J70: =Model!EQ78 -> -1825225.5
B71: NOI | D71: =SUM(D69:D70) -> 2819137.9 | E71: =SUM(E69:E70) -> 3968297.4 | F71: =SUM(F69:F70) -> 0 | G71: =SUM(G69:G70) -> 728720.74 | H71: =SUM(H69:H70) -> 3639516.9 | I71: =SUM(I69:I70) -> 4032017.8 | J71: =SUM(J69:J70) -> 4155645.8
B72: Development Cost | F72: =SUM(Model!EM90:EM93) -> -20292500 | G72: =SUM(Model!EN90:EN93) -> -31417500 | H72: =SUM(Model!EO90:EO93) -> 0 | I72: =SUM(Model!EP90:EP93) -> 0 | J72: =SUM(Model!EQ90:EQ93) -> 0
B73: Capital Reserves | F73: =Model!EM86 -> 0 | G73: =Model!EN86 -> -30000 | H73: =Model!EO86 -> -45000 | I73: =Model!EP86 -> 0 | J73: =Model!EQ86 -> 0
B74: Unlevered Cash Flow | F74: =SUM(F71:F73)*(Model!EM98<>0) -> -20292500 | G74: =SUM(G71:G73)*(Model!EN98<>0) -> -30718779 | H74: =SUM(H71:H73)*(Model!EO98<>0) -> 3594516.9 | I74: =SUM(I71:I73)*(Model!EP98<>0) -> 0 | J74: =SUM(J71:J73)*(Model!EQ98<>0) -> 0
B75: Debt Service | F75: =Model!EM148+Model!EM153 -> -24061.131 | G75: =Model!EN148+Model!EN153 -> -1202402.8 | H75: =Model!EO148+Model!EO153 -> -1917823.8 | I75: =Model!EP148+Model!EP153 -> 0 | J75: =Model!EQ148+Model!EQ153 -> 0
B76: Loan Funding / Payoff (net of fees) | F76: =Model!EM152+Model!EM154+Model!EM150 -> 7670861.1 | G76: =Model!EN152+Model!EN154+Model!EN150 -> 32329139 | H76: =Model!EO152+Model!EO154+Model!EO150 -> -40000000 | I76: =Model!EP152+Model!EP154+Model!EP150 -> 0 | J76: =Model!EQ152+Model!EQ154+Model!EQ150 -> 0
B77: Levered Cash Flow | F77: =SUM(F74:F76) -> -12645700 | G77: =SUM(G74:G76) -> 407956.78 | H77: =SUM(H74:H76) -> -38323307 | I77: =SUM(I74:I76) -> 0 | J77: =SUM(J74:J76) -> 0
B78: Effective Rent | D78: ='Inputs & Drivers'!E51 -> 1356.6667 | E78: =SUMIF(Model!$H$5:$EJ$5,'Transaction Summary'!$E$61,Model!$H56:$EJ56) -> 1540.3359 | F78: =Model!EM56 -> 1356.6667 | G78: =Model!EN56 -> 1384.0501 | H78: =Model!EO56 -> 1555.7971 | I78: =Model!EP56 -> 1603.1181 | J78: =Model!EQ56 -> 1651.8785
B79: Effective Rent Growth | G79: =G78/F78-1 -> 0.020184356 | H79: =H78/G78-1 -> 0.12409013 | I79: =I78/H78-1 -> 0.030415957 | J79: =J78/I78-1 -> 0.030415957
B80: Occupancy | D80: ='Inputs & Drivers'!E49 -> 0.93 | E80: =SUMIF(Model!$H$5:$EJ$5,'Transaction Summary'!$E$61,Model!$H58:$EJ58) -> 0.93 | F80: =Model!EM58 -> 0 | G80: =Model!EN58 -> 0.91 | H80: =Model!EO58 -> 0.93 | I80: =Model!EP58 -> 0.93 | J80: =Model!EQ58 -> 0.93
B81: Yield-on-Cost | D81: =D71/$H$14 -> 0.04792765 | E81: =E71/$H$14 -> 0.0674643 | F81: =Model!EM83 -> 0 | G81: =Model!EN83 -> 0.012398334 | H81: =Model!EO83 -> 0.061874764 | I81: =Model!EP83 -> 0.068547599 | J81: =Model!EQ83 -> 0.070649377
B82: NOI Margin | D82: =IFERROR(D71/D69,0) -> 0.62912159 | E82: =IFERROR(E71/E69,0) -> 0.69543415 | F82: =IFERROR(F71/F69,0) -> 0 | G82: =IFERROR(G71/G69,0) -> 0.48372358 | H82: =IFERROR(H71/H69,0) -> 0.67945075 | I82: =IFERROR(I71/I69,0) -> 0.69396025 | J82: =IFERROR(J71/J69,0) -> 0.69482281
B83: DSCR | F83: =Model!EM156 -> 0 | G83: =Model!EN156 -> 0.60605375 | H83: =Model!EO156 -> 1.8977327 | I83: =Model!EP156 -> n/a | J83: =Model!EQ156 -> n/a

Sheet Inputs & Drivers
B2: Inputs
B4: Property Overview | G4: Joint Venture Assumptions | L4: Checks | P4: LIBOR Index | S4: Amortization Table | AA4: Sensitivity Tables
B5: Name | E5: Multifamily Property | G5: GP Equity | H5: 0.1 | L5: S&U - Hold | N5: =Model!F183 -> Ok
B6: Type | E6: Development | H6: Promote | I6: Pref | J6: Splits | L6: S&U - Close | N6: =Model!E183 -> Ok | P6: Date | Q6: LIBOR | S6: PMT | T6: =PMT($J$23/12,$J$22*12,-$J$16) -> 214728.65 | AA6: Exit Cap | AB6: Annual Rent Growth - Steady State
B7: Location | E7: Boston, MA | G7: Hurdle #1 | H7: n/a | I7: 0.1 | J7: =H5 -> 0.1 | L7: S&U - Monthly | N7: =IF(SUM(Model!H183:EJ183)=0,"Ok","Check") -> Ok | P7: 44196 | Q7: 0.016562 | AA7: =IF(ISERROR(CONCATENATE(TEXT($N$21,"0.0%"),", ",TEXT($N$22/1000000,"$0.0"),"M, ",TEXT($N$23,"0.0x"))),0,CONCATENATE(TEXT($N$21,"0.0%"),", ",TEXT($N$22/1000000,"$0.0"),"M, ",TEXT($N$23,"0.0x"))) -> 27.5%, $15.9M, 1.8x | AB7: =AC7-0.25% -> 0.025 | AC7: =AD7-0.25% -> 0.0275 | AD7: 0.03 | AE7: =AD7+0.25% -> 0.0325 | AF7: =AE7+0.25% -> 0.035
B8: Units | E8: =C34 -> 300 | G8: Hurdle #2 | H8: 0.2 | I8: 0.15 | J8: =$H$5+(H8*(1-$H$5)) -> 0.28 | L8: S&U - Summary | N8: =IF(ROUND('Transaction Summary'!D14+'Transaction Summary'!H14-'Transaction Summary'!D20-'Transaction Summary'!H20,0)=0,"Ok","Check") -> Ok | P8: 44227 | Q8: 0.0162663 | S8: Date | T8: Period | U8: Payment | V8: Beg. Balance | W8: Principal | X8: Interest | Y8: End Balance | AA8: =AA9-0.25% -> 0.045
B9: Year Built | E9: 2015 | G9: Hurdle #3 | H9: 0.3 | I9: 0.2 | J9: =$H$5+(H9*(1-$H$5)) -> 0.37 | L9: Summary NOI | N9: =IF(SUM('Transaction Summary'!F71:J71)=SUM(Model!EM80:EQ80),"Ok","Check") -> Ok | P9: 44255 | Q9: 0.015964 | S9: =J13 -> 44196 | T9: 0 | Y9: =J16 -> 40000000 | AA9: =AA10-0.25% -> 0.0475
G10: Hurdle #4 | H10: 0.4 | I10: 5 | J10: =$H$5+(H10*(1-$H$5)) -> 0.46 | L10: Debt Paydown | N10: =IF(SUM(Model!H152:EJ152,Model!H153:EJ154)=0,"Ok","Check") -> Ok | P10: 44286 | Q10: 0.0156102 | S10: =EOMONTH(S9,1) -> 44227 | T10: =T9+1 -> 1 | U10: =IF(T10<=$J$21,$X10,$T$6) -> 177602.44 | V10: =Y9 -> 40000000 | W10: =U10-X10 -> 0 | X10: =$J$19/$I$13*($S10-$S9)*V10 -> 177602.44 | Y10: =V10-W10 -> 40000000 | AA10: =AA11-0.25% -> 0.05
B11: Investment Overview | L11: Deal Profit | N11: =IF(ROUND(Model!C164-Model!C265-Model!C279,-1)=0,"Ok","Check") -> Ok | P11: 44316 | Q11: 0.0152492 | S11: =EOMONTH(S10,1) -> 44255 | T11: =T10+1 -> 2 | U11: =IF(T11<=$J$21,$X11,$T$6) -> 160415.11 | V11: =Y10 -> 40000000 | W11: =U11-X11 -> 0 | X11: =$J$19/$I$13*($S11-$S10)*V11 -> 160415.11 | Y11: =V11-W11 -> 40000000 | AA11: =AA12-0.25% -> 0.0525
B12: Acquisition Date | E12: 44196 | G12: Financing Assumptions | L12: Remaining CF | N12: =IF(SUM(Model!H258:EJ258)=0,"Ok","Check") -> Ok | P12: 44347 | Q12: 0.0149364 | S12: =EOMONTH(S11,1) -> 44286 | T12: =T11+1 -> 3 | U12: =IF(T12<=$J$21,$X12,$T$6) -> 177602.44 | V12: =Y11 -> 40000000 | W12: =U12-X12 -> 0 | X12: =$J$19/$I$13*($S12-$S11)*V12 -> 177602.44 | Y12: =V12-W12 -> 40000000 | AA12: 0.055
B13: Hold Period | E13: 36 | G13: Start Date | H13: Floating | I13: 360 | J13: =E12 -> 44196 | L13: IRR | N13: =IF(AND(Model!C261=Model!C268,Model!C261<=Model!C275),"Ok","Check") -> Ok | P13: 44377 | Q13: 0.0145569 | S13: =EOMONTH(S12,1) -> 44316 | T13: =T12+1 -> 4 | U13: =IF(T13<=$J$21,$X13,$T$6) -> 171873.33 | V13: =Y12 -> 40000000 | W13: =U13-X13 -> 0 | X13: =$J$19/$I$13*($S13-$S12)*V13 -> 171873.33 | Y13: =V13-W13 -> 40000000 | AA13: =AA12+0.25% -> 0.0575
B14: Exit Date | E14: =EOMONTH(E12,E13) -> 45291 | G14: Term | J14: =E13 -> 36 | L14: YoC | N14: =IF(ROUND(Model!ER83,-1)=ROUND('Transaction Summary'!E38,-1),"Ok","Check") -> Ok | P14: 44408 | Q14: 0.0141933 | S14: =EOMONTH(S13,1) -> 44347 | T14: =T13+1 -> 5 | U14: =IF(T14<=$J$21,$X14,$T$6) -> 177602.44 | V14: =Y13 -> 40000000 | W14: =U14-X14 -> 0 | X14: =$J$19/$I$13*($S14-$S13)*V14 -> 177602.44 | Y14: =V14-W14 -> 40000000 | AA14: =AA13+0.25% -> 0.06
B15: Exit Closing Costs | E15: 0.01 | G15: Maturity Date | J15: =EOMONTH(J13,J14) -> 45291 | L15: Total Profit | N15: =IF(AND(ROUND('Transaction Summary'!E49,0)=ROUND(Model!F159,0),ROUND(Model!F159,0)=ROUND(Model!C164,0)),"Ok","Check") -> Ok | P15: 44439 | Q15: 0.0138616 | S15: =EOMONTH(S14,1) -> 44377 | T15: =T14+1 -> 6 | U15: =IF(T15<=$J$21,$X15,$T$6) -> 171873.33 | V15: =Y14 -> 40000000 | W15: =U15-X15 -> 0 | X15: =$J$19/$I$13*($S15-$S14)*V15 -> 171873.33 | Y15: =V15-W15 -> 40000000 | AA15: =AA14+0.25% -> 0.0625
B16: Exit Cap Rate | E16: 0.055 | G16: Loan Amount | J16: 40000000 | L16: Debt Draw | N16: =IF(J16='Transaction Summary'!H18,"Ok","Check") -> Ok | P16: 44469 | Q16: 0.0135342 | S16: =EOMONTH(S15,1) -> 44408 | T16: =T15+1 -> 7 | U16: =IF(T16<=$J$21,$X16,$T$6) -> 177602.44 | V16: =Y15 -> 40000000 | W16: =U16-X16 -> 0 | X16: =$J$19/$I$13*($S16-$S15)*V16 -> 177602.44 | Y16: =V16-W16 -> 40000000 | AA16: =AA15+0.25% -> 0.065
B17: Sale Price | D17: =E17/$E$8 -> 244364.71 | E17: =SUM(Model!H94:EJ94) -> 73309414 | G17: Loan-to-Cost | J17: =J16/E18 -> 0.6809009 | L17: Dev. Budget | N17: =IF(-SUM(Model!F90:F93,Model!F131,Model!F139,Model!F150)='Development Budget'!E34,"Ok","Check") -> Ok | P17: 44500 | Q17: 0.0132701 | S17: =EOMONTH(S16,1) -> 44439 | T17: =T16+1 -> 8 | U17: =IF(T17<=$J$21,$X17,$T$6) -> 177602.44 | V17: =Y16 -> 40000000 | W17: =U17-X17 -> 0 | X17: =$J$19/$I$13*($S17-$S16)*V17 -> 177602.44 | Y17: =V17-W17 -> 40000000
B18: Total Cost | D18: =E18/$E$8 -> 195819 | E18: ='Development Budget'!E34 -> 58745700 | G18: Interest Rate Spread | I18: L+ | J18: 350 | L18: Reserves | N18: =IF(AND(ROUND(Model!F127+Model!F131,0)=0,ROUND(Model!F135+Model!F139,0)=0),"Ok","Check") -> Ok | P18: 44530 | Q18: 0.0130594 | S18: =EOMONTH(S17,1) -> 44469 | T18: =T17+1 -> 9 | U18: =IF(T18<=$J$21,$X18,$T$6) -> 171873.33 | V18: =Y17 -> 40000000 | W18: =U18-X18 -> 0 | X18: =$J$19/$I$13*($S18-$S17)*V18 -> 171873.33 | Y18: =V18-W18 -> 40000000 | AA18: Exit Cap | AB18: Hold Period
B19: Untrended YoC | E19: =(E63-J60)/E18 -> 0.056721392 | G19: All-in Rate | J19: =Q7+J18/10000 -> 0.051562 | P19: 44561 | Q19: 0.0128912 | S19: =EOMONTH(S18,1) -> 44500 | T19: =T18+1 -> 10 | U19: =IF(T19<=$J$21,$X19,$T$6) -> 177602.44 | V19: =Y18 -> 40000000 | W19: =U19-X19 -> 0 | X19: =$J$19/$I$13*($S19-$S18)*V19 -> 177602.44 | Y19: =V19-W19 -> 40000000 | AA19: =IF(ISERROR(CONCATENATE(TEXT($N$21,"0.0%"),", ",TEXT($N$22/1000000,"$0.0"),"M, ",TEXT($N$23,"0.0x"))),0,CONCATENATE(TEXT($N$21,"0.0%"),", ",TEXT($N$22/1000000,"$0.0"),"M, ",TEXT($N$23,"0.0x"))) -> 27.5%, $15.9M, 1.8x | AB19: =AC19-12 -> 36 | AC19: =AD19-12 -> 48 | AD19: 60 | AE19: =AD19+12 -> 72 | AF19: =AE19+12 -> 84
B20: Stabilized YoC | E20: =SUMIF(Model!$H$5:$EJ$5,'Inputs & Drivers'!$J$42+1,Model!$H$83:$EJ$83) -> 0.06677428 | G20: Fixed Rate | J20: 0.05 | L20: Project Returns | P20: 44592 | Q20: 0.0127664 | S20: =EOMONTH(S19,1) -> 44530 | T20: =T19+1 -> 11 | U20: =IF(T20<=$J$21,$X20,$T$6) -> 171873.33 | V20: =Y19 -> 40000000 | W20: =U20-X20 -> 0 | X20: =$J$19/$I$13*($S20-$S19)*V20 -> 171873.33 | Y20: =V20-W20 -> 40000000 | AA20: =AA21-0.25% -> 0.045
G21: Interest Only Period | J21: 36 | L21: IRR | N21: =Model!C163 -> 0.27464951 | P21: 44620 | Q21: 0.0126461 | S21: =EOMONTH(S20,1) -> 44561 | T21: =T20+1 -> 12 | U21: =IF(T21<=$J$21,$X21,$T$6) -> 177602.44 | V21: =Y20 -> 40000000 | W21: =U21-X21 -> 0 | X21: =$J$19/$I$13*($S21-$S20)*V21 -> 177602.44 | Y21: =V21-W21 -> 40000000 | AA21: =AA22-0.25% -> 0.0475
G22: Amortization Period | J22: 30 | L22: Profit | N22: =Model!C164 -> 15915270 | P22: 44651 | Q22: 0.0125157 | S22: =EOMONTH(S21,1) -> 44592 | T22: =T21+1 -> 13 | U22: =IF(T22<=$J$21,$X22,$T$6) -> 177602.44 | V22: =Y21 -> 40000000 | W22: =U22-X22 -> 0 | X22: =$J$19/$I$13*($S22-$S21)*V22 -> 177602.44 | Y22: =V22-W22 -> 40000000 | AA22: =AA23-0.25% -> 0.05
G23: Amortization Rate | J23: 0.05 | L23: Multiple | N23: =Model!C165 -> 1.8488393 | P23: 44681 | Q23: 0.0123878 | S23: =EOMONTH(S22,1) -> 44620 | T23: =T22+1 -> 14 | U23: =IF(T23<=$J$21,$X23,$T$6) -> 160415.11 | V23: =Y22 -> 40000000 | W23: =U23-X23 -> 0 | X23: =$J$19/$I$13*($S23-$S22)*V23 -> 160415.11 | Y23: =V23-W23 -> 40000000 | AA23: =AA24-0.25% -> 0.0525
G24: Origination Fee | J24: 0.01 | P24: 44712 | Q24: 0.0122618 | S24: =EOMONTH(S23,1) -> 44651 | T24: =T23+1 -> 15 | U24: =IF(T24<=$J$21,$X24,$T$6) -> 177602.44 | V24: =Y23 -> 40000000 | W24: =U24-X24 -> 0 | X24: =$J$19/$I$13*($S24-$S23)*V24 -> 177602.44 | Y24: =V24-W24 -> 40000000 | AA24: 0.055
G25: Interest Reserve | J25: =Model!F127 -> 907885.1 | L25: LP Returns | P25: 44742 | Q25: 0.0121419 | S25: =EOMONTH(S24,1) -> 44681 | T25: =T24+1 -> 16 | U25: =IF(T25<=$J$21,$X25,$T$6) -> 171873.33 | V25: =Y24 -> 40000000 | W25: =U25-X25 -> 0 | X25: =$J$19/$I$13*($S25-$S24)*V25 -> 171873.33 | Y25: =V25-W25 -> 40000000 | AA25: =AA24+0.25% -> 0.0575
G26: Operating Reserve | J26: =Model!F135 -> 27814.901 | L26: IRR | N26: =Model!C264 -> 0.22744136 | P26: 44773 | Q26: 0.0120598 | S26: =EOMONTH(S25,1) -> 44712 | T26: =T25+1 -> 17 | U26: =IF(T26<=$J$21,$X26,$T$6) -> 177602.44 | V26: =Y25 -> 40000000 | W26: =U26-X26 -> 0 | X26: =$J$19/$I$13*($S26-$S25)*V26 -> 177602.44 | Y26: =V26-W26 -> 40000000 | AA26: =AA25+0.25% -> 0.06
L27: Profit | N27: =Model!C265 -> 11449567 | P27: 44804 | Q27: 0.0119824 | S27: =EOMONTH(S26,1) -> 44742 | T27: =T26+1 -> 18 | U27: =IF(T27<=$J$21,$X27,$T$6) -> 171873.33 | V27: =Y26 -> 40000000 | W27: =U27-X27 -> 0 | X27: =$J$19/$I$13*($S27-$S26)*V27 -> 171873.33 | Y27: =V27-W27 -> 40000000 | AA27: =AA26+0.25% -> 0.0625
B28: Unit Mix | L28: Multiple | N28: =Model!C266 -> 1.6785127 | P28: 44834 | Q28: 0.0119528 | S28: =EOMONTH(S27,1) -> 44773 | T28: =T27+1 -> 19 | U28: =IF(T28<=$J$21,$X28,$T$6) -> 177602.44 | V28: =Y27 -> 40000000 | W28: =U28-X28 -> 0 | X28: =$J$19/$I$13*($S28-$S27)*V28 -> 177602.44 | Y28: =V28-W28 -> 40000000 | AA28: =AA27+0.25% -> 0.065
B29: Type | C29: Count | D29: % of Total | F29: Unit Size | G29: Total SF | I29: Potential Rent | J29: Rent PSF | P29: 44865 | Q29: 0.0119603 | S29: =EOMONTH(S28,1) -> 44804 | T29: =T28+1 -> 20 | U29: =IF(T29<=$J$21,$X29,$T$6) -> 177602.44 | V29: =Y28 -> 40000000 | W29: =U29-X29 -> 0 | X29: =$J$19/$I$13*($S29-$S28)*V29 -> 177602.44 | Y29: =V29-W29 -> 40000000
B30: Studio | C30: 15 | D30: =C30/$C$34 -> 0.05 | F30: 600 | G30: =F30*C30 -> 9000 | I30: 1000 | J30: =IFERROR(I30/F30,"0") -> 1.6666667 | L30: GP Returns after Promote | P30: 44895 | Q30: 0.0119794 | S30: =EOMONTH(S29,1) -> 44834 | T30: =T29+1 -> 21 | U30: =IF(T30<=$J$21,$X30,$T$6) -> 171873.33 | V30: =Y29 -> 40000000 | W30: =U30-X30 -> 0 | X30: =$J$19/$I$13*($S30-$S29)*V30 -> 171873.33 | Y30: =V30-W30 -> 40000000 | AA30: Exit Cap | AB30: Renovation Premium
B31: 1 BR, 1 BA | C31: 155 | D31: =C31/$C$34 -> 0.51666667 | F31: 800 | G31: =F31*C31 -> 124000 | I31: 1300 | J31: =IFERROR(I31/F31,"0") -> 1.625 | L31: IRR | N31: =Model!C278 -> 0.60943713 | P31: 44926 | Q31: 0.0120267 | S31: =EOMONTH(S30,1) -> 44865 | T31: =T30+1 -> 22 | U31: =IF(T31<=$J$21,$X31,$T$6) -> 177602.44 | V31: =Y30 -> 40000000 | W31: =U31-X31 -> 0 | X31: =$J$19/$I$13*($S31-$S30)*V31 -> 177602.44 | Y31: =V31-W31 -> 40000000 | AA31: =IF(ISERROR(CONCATENATE(TEXT($N$21,"0.0%"),", ",TEXT($N$22/1000000,"$0.0"),"M, ",TEXT($N$23,"0.0x"))),0,CONCATENATE(TEXT($N$21,"0.0%"),", ",TEXT($N$22/1000000,"$0.0"),"M, ",TEXT($N$23,"0.0x"))) -> 27.5%, $15.9M, 1.8x | AB31: =AC31-25 -> 75 | AC31: =AD31-25 -> 100 | AD31: 125 | AE31: =AD31+25 -> 150 | AF31: =AE31+25 -> 175
B32: 2 BR, 2 BA | C32: 130 | D32: =C32/$C$34 -> 0.43333333 | F32: 1200 | G32: =F32*C32 -> 156000 | I32: 1750 | J32: =IFERROR(I32/F32,"0") -> 1.4583333 | L32: Profit | N32: =Model!C279 -> 4465703 | P32: 44957 | Q32: 0.012084 | S32: =EOMONTH(S31,1) -> 44895 | T32: =T31+1 -> 23 | U32: =IF(T32<=$J$21,$X32,$T$6) -> 171873.33 | V32: =Y31 -> 40000000 | W32: =U32-X32 -> 0 | X32: =$J$19/$I$13*($S32-$S31)*V32 -> 171873.33 | Y32: =V32-W32 -> 40000000 | AA32: =AA33-0.25% -> 0.045
B33: 3 BR, 2 BA | C33: 0 | D33: =C33/$C$34 -> 0 | F33: 0 | G33: =F33*C33 -> 0 | I33: 0 | J33: =IFERROR(I33/F33,0) -> 0 | L33: Multiple | N33: =Model!C280 -> 3.3817781 | P33: 44985 | Q33: 0.0121249 | S33: =EOMONTH(S32,1) -> 44926 | T33: =T32+1 -> 24 | U33: =IF(T33<=$J$21,$X33,$T$6) -> 177602.44 | V33: =Y32 -> 40000000 | W33: =U33-X33 -> 0 | X33: =$J$19/$I$13*($S33-$S32)*V33 -> 177602.44 | Y33: =V33-W33 -> 40000000 | AA33: =AA34-0.25% -> 0.0475
B34: Total | C34: =SUM(C30:C33) -> 300 | D34: =SUM(D30:D33) -> 1 | F34: =SUMPRODUCT(F30:F33,$C$30:$C$33)/$C$34 -> 963.33333 | G34: =SUM(G30:G33) -> 289000 | I34: =SUMPRODUCT(I30:I33,$C$30:$C$33)/$C$34 -> 1480 | J34: =SUMPRODUCT(J30:J33,$C$30:$C$33)/$C$34 -> 1.5548611 | P34: 45016 | Q34: 0.012174 | S34: =EOMONTH(S33,1) -> 44957 | T34: =T33+1 -> 25 | U34: =IF(T34<=$J$21,$X34,$T$6) -> 177602.44 | V34: =Y33 -> 40000000 | W34: =U34-X34 -> 0 | X34: =$J$19/$I$13*($S34-$S33)*V34 -> 177602.44 | Y34: =V34-W34 -> 40000000 | AA34: =AA35-0.25% -> 0.05
P35: 45046 | Q35: 0.0122224 | S35: =EOMONTH(S34,1) -> 44985 | T35: =T34+1 -> 26 | U35: =IF(T35<=$J$21,$X35,$T$6) -> 160415.11 | V35: =Y34 -> 40000000 | W35: =U35-X35 -> 0 | X35: =$J$19/$I$13*($S35-$S34)*V35 -> 160415.11 | Y35: =V35-W35 -> 40000000 | AA35: =AA36-0.25% -> 0.0525
B36: Lease-up Assumptions | E36: Timetable | P36: 45077 | Q36: 0.0122549 | S36: =EOMONTH(S35,1) -> 45016 | T36: =T35+1 -> 27 | U36: =IF(T36<=$J$21,$X36,$T$6) -> 177602.44 | V36: =Y35 -> 40000000 | W36: =U36-X36 -> 0 | X36: =$J$19/$I$13*($S36-$S35)*V36 -> 177602.44 | Y36: =V36-W36 -> 40000000 | AA36: 0.055
B37: Units Leased / Month | C37: 30 | F37: Month | G37: Start | H37: Duration | I37: End | J37: Month | P37: 45107 | Q37: 0.0122909 | S37: =EOMONTH(S36,1) -> 45046 | T37: =T36+1 -> 28 | U37: =IF(T37<=$J$21,$X37,$T$6) -> 171873.33 | V37: =Y36 -> 40000000 | W37: =U37-X37 -> 0 | X37: =$J$19/$I$13*($S37-$S36)*V37 -> 171873.33 | Y37: =V37-W37 -> 40000000 | AA37: =AA36+0.25% -> 0.0575
B38: Concessions | C38: 1 | E38: Acquisition | F38: 0 | G38: =E12 -> 44196 | H38: 1 | I38: =EOMONTH(G38,H38-1) -> 44196 | J38: =F38+H38-1 -> 0 | P38: 45138 | Q38: 0.0123245 | S38: =EOMONTH(S37,1) -> 45077 | T38: =T37+1 -> 29 | U38: =IF(T38<=$J$21,$X38,$T$6) -> 177602.44 | V38: =Y37 -> 40000000 | W38: =U38-X38 -> 0 | X38: =$J$19/$I$13*($S38-$S37)*V38 -> 177602.44 | Y38: =V38-W38 -> 40000000 | AA38: =AA37+0.25% -> 0.06
B39: Concession Burnoff | C39: 6 | E39: Soft Costs | F39: 3 | G39: =EOMONTH($G$38,F39) -> 44286 | H39: 20 | I39: =EOMONTH(G39,H39-1) -> 44865 | J39: =F39+H39-1 -> 22 | P39: 45169 | Q39: 0.0123451 | S39: =EOMONTH(S38,1) -> 45107 | T39: =T38+1 -> 30 | U39: =IF(T39<=$J$21,$X39,$T$6) -> 171873.33 | V39: =Y38 -> 40000000 | W39: =U39-X39 -> 0 | X39: =$J$19/$I$13*($S39-$S38)*V39 -> 171873.33 | Y39: =V39-W39 -> 40000000 | AA39: =AA38+0.25% -> 0.0625
B40: Pre-Construction Leasing | C40: 6 | E40: Hard Costs | F40: 7 | G40: =EOMONTH($G$38,F40) -> 44408 | H40: 16 | I40: =EOMONTH(G40,H40-1) -> 44865 | J40: =F40+H40-1 -> 22 | P40: 45199 | Q40: 0.0123718 | S40: =EOMONTH(S39,1) -> 45138 | T40: =T39+1 -> 31 | U40: =IF(T40<=$J$21,$X40,$T$6) -> 177602.44 | V40: =Y39 -> 40000000 | W40: =U40-X40 -> 0 | X40: =$J$19/$I$13*($S40-$S39)*V40 -> 177602.44 | Y40: =V40-W40 -> 40000000 | AA40: =AA39+0.25% -> 0.065
E41: Lease-up | F41: =J40-C40 -> 16 | G41: =EOMONTH($G$38,F41) -> 44681 | H41: =ROUNDUP(E8/C37,0) -> 10 | I41: =EOMONTH(G41,H41-1) -> 44957 | J41: =F41+H41-1 -> 25 | P41: 45230 | Q41: 0.0124011 | S41: =EOMONTH(S40,1) -> 45169 | T41: =T40+1 -> 32 | U41: =IF(T41<=$J$21,$X41,$T$6) -> 177602.44 | V41: =Y40 -> 40000000 | W41: =U41-X41 -> 0 | X41: =$J$19/$I$13*($S41-$S40)*V41 -> 177602.44 | Y41: =V41-W41 -> 40000000
E42: Stabilization | F42: =F41 -> 16 | G42: =G41 -> 44681 | H42: =J42-F42+1 -> 16 | I42: =EOMONTH(I41,C39) -> 45138 | J42: =J41+C39 -> 31 | P42: 45260 | Q42: 0.0124186 | S42: =EOMONTH(S41,1) -> 45199 | T42: =T41+1 -> 33 | U42: =IF(T42<=$J$21,$X42,$T$6) -> 171873.33 | V42: =Y41 -> 40000000 | W42: =U42-X42 -> 0 | X42: =$J$19/$I$13*($S42-$S41)*V42 -> 171873.33 | Y42: =V42-W42 -> 40000000
E43: Exit | F43: =E13 -> 36 | G43: =E14 -> 45291 | H43: 1 | I43: =EOMONTH(G43,H43-1) -> 45291 | J43: =F43+H43-1 -> 36 | P43: 45291 | Q43: 0.0124424 | S43: =EOMONTH(S42,1) -> 45230 | T43: =T42+1 -> 34 | U43: =IF(T43<=$J$21,$X43,$T$6) -> 177602.44 | V43: =Y42 -> 40000000 | W43: =U43-X43 -> 0 | X43: =$J$19/$I$13*($S43-$S42)*V43 -> 177602.44 | Y43: =V43-W43 -> 40000000
P44: 45322 | Q44: 0.0124766 | S44: =EOMONTH(S43,1) -> 45260 | T44: =T43+1 -> 35 | U44: =IF(T44<=$J$21,$X44,$T$6) -> 171873.33 | V44: =Y43 -> 40000000 | W44: =U44-X44 -> 0 | X44: =$J$19/$I$13*($S44-$S43)*V44 -> 171873.33 | Y44: =V44-W44 -> 40000000
B45: Drivers | P45: 45351 | Q45: 0.0124993 | S45: =EOMONTH(S44,1) -> 45291 | T45: =T44+1 -> 36 | U45: =IF(T45<=$J$21,$X45,$T$6) -> 177602.44 | V45: =Y44 -> 40000000 | W45: =U45-X45 -> 0 | X45: =$J$19/$I$13*($S45-$S44)*V45 -> 177602.44 | Y45: =V45-W45 -> 40000000
P46: 45382 | Q46: 0.0125341 | S46: =EOMONTH(S45,1) -> 45322 | T46: =T45+1 -> 37 | U46: =IF(T46<=$J$21,$X46,$T$6) -> 214728.65 | V46: =Y45 -> 40000000 | W46: =U46-X46 -> 37126.205 | X46: =$J$19/$I$13*($S46-$S45)*V46 -> 177602.44 | Y46: =V46-W46 -> 39962874
B47: Untrended Stabilized Income | G47: Untrended Stabilized Operating Expenses | P47: 45412 | Q47: 0.0125729 | S47: =EOMONTH(S46,1) -> 45351 | T47: =T46+1 -> 38 | U47: =IF(T47<=$J$21,$X47,$T$6) -> 214728.65 | V47: =Y46 -> 39962874 | W47: =U47-X47 -> 48738.635 | X47: =$J$19/$I$13*($S47-$S46)*V47 -> 165990.01 | Y47: =V47-W47 -> 39914135
D48: Assumption | E48: Total | H48: % | I48: Per Unit | J48: Total | P48: 45443 | Q48: 0.0126043 | S48: =EOMONTH(S47,1) -> 45382 | T48: =T47+1 -> 39 | U48: =IF(T48<=$J$21,$X48,$T$6) -> 214728.65 | V48: =Y47 -> 39914135 | W48: =U48-X48 -> 37507.45 | X48: =$J$19/$I$13*($S48-$S47)*V48 -> 177221.2 | Y48: =V48-W48 -> 39876628
B49: Stabilized Occupancy | E49: =D71 -> 0.93 | G49: Repairs & Maintenance | I49: 600 | J49: =I49*$E$8 -> 180000 | P49: 45473 | Q49: 0.0126472 | S49: =EOMONTH(S48,1) -> 45412 | T49: =T48+1 -> 40 | U49: =IF(T49<=$J$21,$X49,$T$6) -> 214728.65 | V49: =Y48 -> 39876628 | W49: =U49-X49 -> 43385.426 | X49: =$J$19/$I$13*($S49-$S48)*V49 -> 171343.22 | Y49: =V49-W49 -> 39833242
B50: Potential Rent / Month | E50: =I34 -> 1480 | G50: Turnover | I50: 250 | J50: =I50*$E$8 -> 75000 | P50: 45504 | Q50: 0.0126952 | S50: =EOMONTH(S49,1) -> 45443 | T50: =T49+1 -> 41 | U50: =IF(T50<=$J$21,$X50,$T$6) -> 214728.65 | V50: =Y49 -> 39833242 | W50: =U50-X50 -> 37866.619 | X50: =$J$19/$I$13*($S50-$S49)*V50 -> 176862.03 | Y50: =V50-W50 -> 39795376
B51: Effective Rent / Month | E51: =E55/E8/12 -> 1356.6667 | G51: Marketing | I51: 150 | J51: =I51*$E$8 -> 45000 | P51: 45535 | Q51: 0.0127308 | S51: =EOMONTH(S50,1) -> 45473 | T51: =T50+1 -> 42 | U51: =IF(T51<=$J$21,$X51,$T$6) -> 214728.65 | V51: =Y50 -> 39795376 | W51: =U51-X51 -> 43734.553 | X51: =$J$19/$I$13*($S51-$S50)*V51 -> 170994.1 | Y51: =V51-W51 -> 39751641
G52: General & Administrative | I52: 375 | J52: =I52*$E$8 -> 112500 | P52: 45565 | Q52: 0.0127724 | S52: =EOMONTH(S51,1) -> 45504 | T52: =T51+1 -> 43 | U52: =IF(T52<=$J$21,$X52,$T$6) -> 214728.65 | V52: =Y51 -> 39751641 | W52: =U52-X52 -> 38228.933 | X52: =$J$19/$I$13*($S52-$S51)*V52 -> 176499.72 | Y52: =V52-W52 -> 39713412
B53: Net Potential Rent | E53: =E50*E8*12 -> 5328000 | G53: Payroll | I53: 1100 | J53: =I53*$E$8 -> 330000 | P53: 45596 | Q53: 0.0128259 | S53: =EOMONTH(S52,1) -> 45535 | T53: =T52+1 -> 44 | U53: =IF(T53<=$J$21,$X53,$T$6) -> 214728.65 | V53: =Y52 -> 39713412 | W53: =U53-X53 -> 38398.672 | X53: =$J$19/$I$13*($S53-$S52)*V53 -> 176329.98 | Y53: =V53-W53 -> 39675014
B54: Concessions | E54: =-(E8*C38*E50) -> -444000 | G54: Management Fees | H54: 0.03 | I54: =J54/$E$8 -> 448.107 | J54: =H54*E59 -> 134432.1 | P54: 45626 | Q54: 0.0128633 | S54: =EOMONTH(S53,1) -> 45565 | T54: =T53+1 -> 45 | U54: =IF(T54<=$J$21,$X54,$T$6) -> 214728.65 | V54: =Y53 -> 39675014 | W54: =U54-X54 -> 44251.729 | X54: =$J$19/$I$13*($S54-$S53)*V54 -> 170476.92 | Y54: =V54-W54 -> 39630762
B55: Net Effective Rent | E55: =SUM(E53:E54) -> 4884000 | G55: Utilities | I55: 175 | J55: =I55*$E$8 -> 52500 | P55: 45657 | Q55: 0.0129034 | S55: =EOMONTH(S54,1) -> 45596 | T55: =T54+1 -> 46 | U55: =IF(T55<=$J$21,$X55,$T$6) -> 214728.65 | V55: =Y54 -> 39630762 | W55: =U55-X55 -> 38765.645 | X55: =$J$19/$I$13*($S55-$S54)*V55 -> 175963 | Y55: =V55-W55 -> 39591996
B56: Vacancy Loss | E56: =-(1-$E$49)*E55 -> -341880 | G56: Real Estate Taxes | I56: =J56/$E$8 -> 2166.6667 | J56: 650000 | P56: 45688 | Q56: 0.0129587 | S56: =EOMONTH(S55,1) -> 45626 | T56: =T55+1 -> 47 | U56: =IF(T56<=$J$21,$X56,$T$6) -> 214728.65 | V56: =Y55 -> 39591996 | W56: =U56-X56 -> 44608.44 | X56: =$J$19/$I$13*($S56-$S55)*V56 -> 170120.21 | Y56: =V56-W56 -> 39547388
B57: Non-Revenue Units | D57: 0.005 | E57: =-D57*$E$55 -> -24420 | G57: Property Insurance | I57: 275 | J57: =I57*$E$8 -> 82500 | P57: 45716 | Q57: 0.0130048 | S57: =EOMONTH(S56,1) -> 45657 | T57: =T56+1 -> 48 | U57: =IF(T57<=$J$21,$X57,$T$6) -> 214728.65 | V57: =Y56 -> 39547388 | W57: =U57-X57 -> 39135.831 | X57: =$J$19/$I$13*($S57-$S56)*V57 -> 175592.82 | Y57: =V57-W57 -> 39508252
B58: Bad Debt | D58: 0.0075 | E58: =-D58*$E$55 -> -36630 | G58: Subtotal | I58: =SUM(I49:I57) -> 5539.7737 | J58: =SUM(J49:J57) -> 1661932.1 | P58: 45747 | Q58: 0.0130543 | S58: =EOMONTH(S57,1) -> 45688 | T58: =T57+1 -> 49 | U58: =IF(T58<=$J$21,$X58,$T$6) -> 214728.65 | V58: =Y57 -> 39508252 | W58: =U58-X58 -> 39309.597 | X58: =$J$19/$I$13*($S58-$S57)*V58 -> 175419.05 | Y58: =V58-W58 -> 39468942
B59: Total Rental Income | E59: =SUM(E55:E58) -> 4481070 | G59: Capital Reserves | I59: 150 | J59: =I59*$E$8 -> 45000 | P59: 45777 | Q59: 0.0131283 | S59: =EOMONTH(S58,1) -> 45716 | T59: =T58+1 -> 50 | U59: =IF(T59<=$J$21,$X59,$T$6) -> 214728.65 | V59: =Y58 -> 39468942 | W59: =U59-X59 -> 56443.28 | X59: =$J$19/$I$13*($S59-$S58)*V59 -> 158285.37 | Y59: =V59-W59 -> 39412499
B60: Utility Reimbursement | D60: 30 | E60: =D60*$E$8*12 -> 108000 | G60: Total | I60: =SUM(I58:I59) -> 5689.7737 | J60: =SUM(J58:J59) -> 1706932.1 | P60: 45808 | Q60: 0.0131903 | S60: =EOMONTH(S59,1) -> 45747 | T60: =T59+1 -> 51 | U60: =IF(T60<=$J$21,$X60,$T$6) -> 214728.65 | V60: =Y59 -> 39412499 | W60: =U60-X60 -> 39734.745 | X60: =$J$19/$I$13*($S60-$S59)*V60 -> 174993.9 | Y60: =V60-W60 -> 39372764
B61: Parking Revenue | D61: 100 | E61: =D61*$E$8*12 -> 360000 | P61: 45838 | Q61: 0.0132553 | S61: =EOMONTH(S60,1) -> 45777 | T61: =T60+1 -> 52 | U61: =IF(T61<=$J$21,$X61,$T$6) -> 214728.65 | V61: =Y60 -> 39372764 | W61: =U61-X61 -> 45550.443 | X61: =$J$19/$I$13*($S61-$S60)*V61 -> 169178.21 | Y61: =V61-W61 -> 39327214
B62: Other Revenue | D62: 25 | E62: =D62*$E$8*12 -> 90000 | P62: 45869 | Q62: 0.0133412 | S62: =EOMONTH(S61,1) -> 45808 | T62: =T61+1 -> 53 | U62: =IF(T62<=$J$21,$X62,$T$6) -> 214728.65 | V62: =Y61 -> 39327214 | W62: =U62-X62 -> 40113.417 | X62: =$J$19/$I$13*($S62-$S61)*V62 -> 174615.23 | Y62: =V62-W62 -> 39287100
B63: Total Income | E63: =SUM(E59:E62) -> 5039070 | P63: 45900 | Q63: 0.0134138 | S63: =EOMONTH(S62,1) -> 45838 | T63: =T62+1 -> 54 | U63: =IF(T63<=$J$21,$X63,$T$6) -> 214728.65 | V63: =Y62 -> 39287100 | W63: =U63-X63 -> 45918.527 | X63: =$J$19/$I$13*($S63-$S62)*V63 -> 168810.12 | Y63: =V63-W63 -> 39241182
P64: 45930 | Q64: 0.0134936 | S64: =EOMONTH(S63,1) -> 45869 | T64: =T63+1 -> 55 | U64: =IF(T64<=$J$21,$X64,$T$6) -> 214728.65 | V64: =Y63 -> 39241182 | W64: =U64-X64 -> 40495.404 | X64: =$J$19/$I$13*($S64-$S63)*V64 -> 174233.25 | Y64: =V64-W64 -> 39200686
B65: Revenue & Expense Assumptions | P65: 45961 | Q65: 0.0135849 | S65: =EOMONTH(S64,1) -> 45900 | T65: =T64+1 -> 56 | U65: =IF(T65<=$J$21,$X65,$T$6) -> 214728.65 | V65: =Y64 -> 39200686 | W65: =U65-X65 -> 40675.206 | X65: =$J$19/$I$13*($S65-$S64)*V65 -> 174053.44 | Y65: =V65-W65 -> 39160011
E66: Rent | G66: Other Revenue | I66: Expense | J66: RET | P66: 45991 | Q66: 0.0136573 | S66: =EOMONTH(S65,1) -> 45930 | T66: =T65+1 -> 57 | U66: =IF(T66<=$J$21,$X66,$T$6) -> 214728.65 | V66: =Y65 -> 39160011 | W66: =U66-X66 -> 46464.608 | X66: =$J$19/$I$13*($S66-$S65)*V66 -> 168264.04 | Y66: =V66-W66 -> 39113547
B67: Year | D67: Occupancy | E67: Growth | G67: Growth | I67: Growth | J67: Growth | P67: 46022 | Q67: 0.0137494 | S67: =EOMONTH(S66,1) -> 45961 | T67: =T66+1 -> 58 | U67: =IF(T67<=$J$21,$X67,$T$6) -> 214728.65 | V67: =Y66 -> 39113547 | W67: =U67-X67 -> 41062.112 | X67: =$J$19/$I$13*($S67-$S66)*V67 -> 173666.54 | Y67: =V67-W67 -> 39072485
B68: 1 | D68: 0.9 | E68: 0 | G68: 0 | I68: 0 | J68: 0 | P68: 46053 | Q68: 0.0138392 | S68: =EOMONTH(S67,1) -> 45991 | T68: =T67+1 -> 59 | U68: =IF(T68<=$J$21,$X68,$T$6) -> 214728.65 | V68: =Y67 -> 39072485 | W68: =U68-X68 -> 46840.695 | X68: =$J$19/$I$13*($S68-$S67)*V68 -> 167887.95 | Y68: =V68-W68 -> 39025644
B69: =++B68+1 -> 2 | D69: 0.91 | E69: 0.02 | G69: 0.02 | I69: 0.02 | J69: 0.02 | P69: 46081 | Q69: 0.0139057 | S69: =EOMONTH(S68,1) -> 46022 | T69: =T68+1 -> 60 | U69: =IF(T69<=$J$21,$X69,$T$6) -> 214728.65 | V69: =Y68 -> 39025644 | W69: =U69-X69 -> 41452.406 | X69: =$J$19/$I$13*($S69-$S68)*V69 -> 173276.24 | Y69: =V69-W69 -> 38984191
B70: =++B69+1 -> 3 | D70: 0.93 | E70: 0.03 | G70: 0.02 | I70: 0.03 | J70: 0.02 | P70: 46112 | Q70: 0.0139878 | S70: =EOMONTH(S69,1) -> 46053 | T70: =T69+1 -> 61 | U70: =IF(T70<=$J$21,$X70,$T$6) -> 214728.65 | V70: =Y69 -> 38984191 | W70: =U70-X70 -> 41636.457 | X70: =$J$19/$I$13*($S70-$S69)*V70 -> 173092.19 | Y70: =V70-W70 -> 38942555
B71: =++B70+1 -> 4 | D71: =D70 -> 0.93 | E71: =E70 -> 0.03 | G71: =G70 -> 0.02 | I71: =I70 -> 0.03 | J71: =J70 -> 0.02 | P71: 46142 | Q71: 0.0140706 | S71: =EOMONTH(S70,1) -> 46081 | T71: =T70+1 -> 62 | U71: =IF(T71<=$J$21,$X71,$T$6) -> 214728.65 | V71: =Y70 -> 38942555 | W71: =U71-X71 -> 58554.292 | X71: =$J$19/$I$13*($S71-$S70)*V71 -> 156174.36 | Y71: =V71-W71 -> 38884001
B72: =++B71+1 -> 5 | D72: =D71 -> 0.93 | E72: =E71 -> 0.03 | G72: =G71 -> 0.02 | I72: =I71 -> 0.03 | J72: =J71 -> 0.02 | P72: 46173 | Q72: 0.0141327 | S72: =EOMONTH(S71,1) -> 46112 | T72: =T71+1 -> 63 | U72: =IF(T72<=$J$21,$X72,$T$6) -> 214728.65 | V72: =Y71 -> 38884001 | W72: =U72-X72 -> 42081.31 | X72: =$J$19/$I$13*($S72-$S71)*V72 -> 172647.34 | Y72: =V72-W72 -> 38841919
B73: =++B72+1 -> 6 | D73: =D72 -> 0.93 | E73: =E72 -> 0.03 | G73: =G72 -> 0.02 | I73: =I72 -> 0.03 | J73: =J72 -> 0.02 | P73: 46203 | Q73: 0.0141966 | S73: =EOMONTH(S72,1) -> 46142 | T73: =T72+1 -> 64 | U73: =IF(T73<=$J$21,$X73,$T$6) -> 214728.65 | V73: =Y72 -> 38841919 | W73: =U73-X73 -> 47831.395 | X73: =$J$19/$I$13*($S73-$S72)*V73 -> 166897.25 | Y73: =V73-W73 -> 38794088
B74: =++B73+1 -> 7 | D74: =D73 -> 0.93 | E74: =E73 -> 0.03 | G74: =G73 -> 0.02 | I74: =I73 -> 0.03 | J74: =J73 -> 0.02 | P74: 46234 | Q74: 0.0142705 | S74: =EOMONTH(S73,1) -> 46173 | T74: =T73+1 -> 65 | U74: =IF(T74<=$J$21,$X74,$T$6) -> 214728.65 | V74: =Y73 -> 38794088 | W74: =U74-X74 -> 42480.528 | X74: =$J$19/$I$13*($S74-$S73)*V74 -> 172248.12 | Y74: =V74-W74 -> 38751607
B75: =++B74+1 -> 8 | D75: =D74 -> 0.93 | E75: =E74 -> 0.03 | G75: =G74 -> 0.02 | I75: =I74 -> 0.03 | J75: =J74 -> 0.02 | P75: 46265 | Q75: 0.0143158 | S75: =EOMONTH(S74,1) -> 46203 | T75: =T74+1 -> 66 | U75: =IF(T75<=$J$21,$X75,$T$6) -> 214728.65 | V75: =Y74 -> 38751607 | W75: =U75-X75 -> 48219.451 | X75: =$J$19/$I$13*($S75-$S74)*V75 -> 166509.2 | Y75: =V75-W75 -> 38703388
B76: =++B75+1 -> 9 | D76: =D75 -> 0.93 | E76: =E75 -> 0.03 | G76: =G75 -> 0.02 | I76: =I75 -> 0.03 | J76: =J75 -> 0.02 | P76: 46295 | Q76: 0.0143776 | S76: =EOMONTH(S75,1) -> 46234 | T76: =T75+1 -> 67 | U76: =IF(T76<=$J$21,$X76,$T$6) -> 214728.65 | V76: =Y75 -> 38703388 | W76: =U76-X76 -> 42883.241 | X76: =$J$19/$I$13*($S76-$S75)*V76 -> 171845.41 | Y76: =V76-W76 -> 38660505
B77: =++B76+1 -> 10 | D77: =D76 -> 0.93 | E77: =E76 -> 0.03 | G77: =G76 -> 0.02 | I77: =I76 -> 0.03 | J77: =J76 -> 0.02 | P77: 46326 | Q77: 0.0144425 | S77: =EOMONTH(S76,1) -> 46265 | T77: =T76+1 -> 68 | U77: =IF(T77<=$J$21,$X77,$T$6) -> 214728.65 | V77: =Y76 -> 38660505 | W77: =U77-X77 -> 43073.646 | X77: =$J$19/$I$13*($S77-$S76)*V77 -> 171655 | Y77: =V77-W77 -> 38617431
B78: =++B77+1 -> 11 | D78: =D77 -> 0.93 | E78: =E77 -> 0.03 | G78: =G77 -> 0.02 | I78: =I77 -> 0.03 | J78: =J77 -> 0.02 | P78: 46356 | Q78: 0.0144827 | S78: =EOMONTH(S77,1) -> 46295 | T78: =T77+1 -> 69 | U78: =IF(T78<=$J$21,$X78,$T$6) -> 214728.65 | V78: =Y77 -> 38617431 | W78: =U78-X78 -> 48795.984 | X78: =$J$19/$I$13*($S78-$S77)*V78 -> 165932.67 | Y78: =V78-W78 -> 38568635
P79: 46387 | Q79: 0.0145359 | S79: =EOMONTH(S78,1) -> 46326 | T79: =T78+1 -> 70 | U79: =IF(T79<=$J$21,$X79,$T$6) -> 214728.65 | V79: =Y78 -> 38568635 | W79: =U79-X79 -> 43481.552 | X79: =$J$19/$I$13*($S79-$S78)*V79 -> 171247.1 | Y79: =V79-W79 -> 38525154
P80: 46418 | Q80: 0.0145917 | S80: =EOMONTH(S79,1) -> 46356 | T80: =T79+1 -> 71 | U80: =IF(T80<=$J$21,$X80,$T$6) -> 214728.65 | V80: =Y79 -> 38525154 | W80: =U80-X80 -> 49192.485 | X80: =$J$19/$I$13*($S80-$S79)*V80 -> 165536.16 | Y80: =V80-W80 -> 38475961
P81: 46446 | Q81: 0.0146295 | S81: =EOMONTH(S80,1) -> 46387 | T81: =T80+1 -> 72 | U81: =IF(T81<=$J$21,$X81,$T$6) -> 214728.65 | V81: =Y80 -> 38475961 | W81: =U81-X81 -> 43893.031 | X81: =$J$19/$I$13*($S81-$S80)*V81 -> 170835.62 | Y81: =V81-W81 -> 38432068
P82: 46477 | Q82: 0.0146818 | S82: =EOMONTH(S81,1) -> 46418 | T82: =T81+1 -> 73 | U82: =IF(T82<=$J$21,$X82,$T$6) -> 214728.65 | V82: =Y81 -> 38432068 | W82: =U82-X82 -> 44087.918 | X82: =$J$19/$I$13*($S82-$S81)*V82 -> 170640.73 | Y82: =V82-W82 -> 38387980
P83: 46507 | Q83: 0.0147418 | S83: =EOMONTH(S82,1) -> 46446 | T83: =T82+1 -> 74 | U83: =IF(T83<=$J$21,$X83,$T$6) -> 214728.65 | V83: =Y82 -> 38387980 | W83: =U83-X83 -> 60778.347 | X83: =$J$19/$I$13*($S83-$S82)*V83 -> 153950.3 | Y83: =V83-W83 -> 38327202
P84: 46538 | Q84: 0.0147793 | S84: =EOMONTH(S83,1) -> 46477 | T84: =T83+1 -> 75 | U84: =IF(T84<=$J$21,$X84,$T$6) -> 214728.65 | V84: =Y83 -> 38327202 | W84: =U84-X84 -> 44553.531 | X84: =$J$19/$I$13*($S84-$S83)*V84 -> 170175.12 | Y84: =V84-W84 -> 38282648
P85: 46568 | Q85: 0.0148361 | S85: =EOMONTH(S84,1) -> 46507 | T85: =T84+1 -> 76 | U85: =IF(T85<=$J$21,$X85,$T$6) -> 214728.65 | V85: =Y84 -> 38282648 | W85: =U85-X85 -> 50234.49 | X85: =$J$19/$I$13*($S85-$S84)*V85 -> 164494.16 | Y85: =V85-W85 -> 38232414
P86: 46599 | Q86: 0.0148997 | S86: =EOMONTH(S85,1) -> 46538 | T86: =T85+1 -> 77 | U86: =IF(T86<=$J$21,$X86,$T$6) -> 214728.65 | V86: =Y85 -> 38232414 | W86: =U86-X86 -> 44974.396 | X86: =$J$19/$I$13*($S86-$S85)*V86 -> 169754.25 | Y86: =V86-W86 -> 38187439
P87: 46630 | Q87: 0.0149441 | S87: =EOMONTH(S86,1) -> 46568 | T87: =T86+1 -> 78 | U87: =IF(T87<=$J$21,$X87,$T$6) -> 214728.65 | V87: =Y86 -> 38187439 | W87: =U87-X87 -> 50643.587 | X87: =$J$19/$I$13*($S87-$S86)*V87 -> 164085.06 | Y87: =V87-W87 -> 38136796
P88: 46660 | Q88: 0.0150033 | S88: =EOMONTH(S87,1) -> 46599 | T88: =T87+1 -> 79 | U88: =IF(T88<=$J$21,$X88,$T$6) -> 214728.65 | V88: =Y87 -> 38136796 | W88: =U88-X88 -> 45398.945 | X88: =$J$19/$I$13*($S88-$S87)*V88 -> 169329.7 | Y88: =V88-W88 -> 38091397
P89: 46691 | Q89: 0.0150696 | S89: =EOMONTH(S88,1) -> 46630 | T89: =T88+1 -> 80 | U89: =IF(T89<=$J$21,$X89,$T$6) -> 214728.65 | V89: =Y88 -> 38091397 | W89: =U89-X89 -> 45600.519 | X89: =$J$19/$I$13*($S89-$S88)*V89 -> 169128.13 | Y89: =V89-W89 -> 38045796
P90: 46721 | Q90: 0.0151176 | S90: =EOMONTH(S89,1) -> 46660 | T90: =T89+1 -> 81 | U90: =IF(T90<=$J$21,$X90,$T$6) -> 214728.65 | V90: =Y89 -> 38045796 | W90: =U90-X90 -> 51252.203 | X90: =$J$19/$I$13*($S90-$S89)*V90 -> 163476.45 | Y90: =V90-W90 -> 37994544
... P127: 47848 | Q127: 0.0169351 | S127: =EOMONTH(S126,1) -> 47787 | T127: =T126+1 -> 118 | U127: =IF(T127<=$J$21,$X127,$T$6) -> 214728.65 | V127: =Y126 -> 36087343 | W127: =U127-X127 -> 54498.643 | X127: =$J$19/$I$13*($S127-$S126)*V127 -> 160230.01 | Y127: =V127-W127 -> 36032844
S128: =EOMONTH(S127,1) -> 47817 | T128: =T127+1 -> 119 | U128: =IF(T128<=$J$21,$X128,$T$6) -> 214728.65 | V128: =Y127 -> 36032844 | W128: =U128-X128 -> 59901.524 | X128: =$J$19/$I$13*($S128-$S127)*V128 -> 154827.12 | Y128: =V128-W128 -> 35972942
S129: =EOMONTH(S128,1) -> 47848 | T129: =T128+1 -> 120 | U129: =IF(T129<=$J$21,$X129,$T$6) -> 214728.65 | V129: =Y128 -> 35972942 | W129: =U129-X129 -> 55006.586 | X129: =$J$19/$I$13*($S129-$S128)*V129 -> 159722.06 | Y129: =V129-W129 -> 35917936

Sheet Model
B2: Model
B4: Acq Date | C4: ='Inputs & Drivers'!E12 -> 44196 | H4: 0 | I4: 1 | J4: 1 | K4: 1 | L4: 1 | M4: 1 | N4: 1 | O4: 1 | P4: 1 | Q4: 1 | R4: 1 | S4: 1 | T4: 1 | U4: =I4+1 -> 2 | V4: =J4+1 -> 2 | W4: =K4+1 -> 2 | X4: =L4+1 -> 2 | Y4: =M4+1 -> 2 | Z4: =N4+1 -> 2 | AA4: =O4+1 -> 2 | AB4: =P4+1 -> 2 | ... EJ4: =DX4+1 -> 11
B5: Exit Date | C5: ='Inputs & Drivers'!E14 -> 45291 | H5: 0 | I5: =++H5+1 -> 1 | J5: =++I5+1 -> 2 | K5: =++J5+1 -> 3 | L5: =++K5+1 -> 4 | M5: =++L5+1 -> 5 | N5: =++M5+1 -> 6 | O5: =++N5+1 -> 7 | P5: =++O5+1 -> 8 | ... EJ5: =++EI5+1 -> 132 | EL5: =H4 -> 0 | EM5: =EL5+1 -> 1 | EN5: =EM5+1 -> 2 | EO5: =EN5+1 -> 3 | EP5: =EO5+1 -> 4 | EQ5: =EP5+1 -> 5 | ER5: =EQ5+1 -> 6 | ES5: =ER5+1 -> 7 | ET5: =ES5+1 -> 8 | ... EW5: =EV5+1 -> 11
B6: Size | C6: ='Inputs & Drivers'!E8 -> 300 | F6: Total | H6: =C4 -> 44196 | I6: =EOMONTH(H6,1) -> 44227 | J6: =EOMONTH(I6,1) -> 44255 | K6: =EOMONTH(J6,1) -> 44286 | L6: =EOMONTH(K6,1) -> 44316 | M6: =EOMONTH(L6,1) -> 44347 | N6: =EOMONTH(M6,1) -> 44377 | O6: =EOMONTH(N6,1) -> 44408 | P6: =EOMONTH(O6,1) -> 44439 | ... EJ6: =EOMONTH(EI6,1) -> 48213 | EL6: =H6 -> 44196 | EM6: =EOMONTH(EL6,12) -> 44561 | EN6: =EOMONTH(EM6,12) -> 44926 | EO6: =EOMONTH(EN6,12) -> 45291 | EP6: =EOMONTH(EO6,12) -> 45657 | EQ6: =EOMONTH(EP6,12) -> 46022 | ER6: =EOMONTH(EQ6,12) -> 46387 | ES6: =EOMONTH(ER6,12) -> 46752 | ET6: =EOMONTH(ES6,12) -> 47118 | ... EW6: =EOMONTH(EV6,12) -> 48213
B8: Investment Month | H8: =H5 -> 0 | I8: =I5 -> 1 | J8: =J5 -> 2 | K8: =K5 -> 3 | L8: =L5 -> 4 | M8: =M5 -> 5 | N8: =N5 -> 6 | O8: =O5 -> 7 | ... EJ8: =EJ5 -> 132
B9: Construction Month | H9: =H5 -> 0 | I9: =IF(OR(Model!I$8<'Inputs & Drivers'!$F40,Model!I$8>'Inputs & Drivers'!$J40),0,IF(I$8='Inputs & Drivers'!$F40,1,Model!H9+1)) -> 0 | J9: =IF(OR(Model!J$8<'Inputs & Drivers'!$F40,Model!J$8>'Inputs & Drivers'!$J40),0,IF(J$8='Inputs & Drivers'!$F40,1,Model!I9+1)) -> 0 | K9: =IF(OR(Model!K$8<'Inputs & Drivers'!$F40,Model!K$8>'Inputs & Drivers'!$J40),0,IF(K$8='Inputs & Drivers'!$F40,1,Model!J9+1)) -> 0 | L9: =IF(OR(Model!L$8<'Inputs & Drivers'!$F40,Model!L$8>'Inputs & Drivers'!$J40),0,IF(L$8='Inputs & Drivers'!$F40,1,Model!K9+1)) -> 0 | M9: =IF(OR(Model!M$8<'Inputs & Drivers'!$F40,Model!M$8>'Inputs & Drivers'!$J40),0,IF(M$8='Inputs & Drivers'!$F40,1,Model!L9+1)) -> 0 | N9: =IF(OR(Model!N$8<'Inputs & Drivers'!$F40,Model!N$8>'Inputs & Drivers'!$J40),0,IF(N$8='Inputs & Drivers'!$F40,1,Model!M9+1)) -> 0 | O9: =IF(OR(Model!O$8<'Inputs & Drivers'!$F40,Model!O$8>'Inputs & Drivers'!$J40),0,IF(O$8='Inputs & Drivers'!$F40,1,Model!N9+1)) -> 1 | P9: =IF(OR(Model!P$8<'Inputs & Drivers'!$F40,Model!P$8>'Inputs & Drivers'!$J40),0,IF(P$8='Inputs & Drivers'!$F40,1,Model!O9+1)) -> 2 | ... DI9: =IF(OR(Model!DI$8<'Inputs & Drivers'!$F40,Model!DI$8>'Inputs & Drivers'!$J40),0,IF(DI$8='Inputs & Drivers'!$F40,1,Model!DH9+1)) -> 0
B10: Lease-up Month | I10: =IF(OR(Model!I$8<'Inputs & Drivers'!$F41,Model!I$8>'Inputs & Drivers'!$J41),0,IF(I$8='Inputs & Drivers'!$F41,1,Model!H10+1)) -> 0 | J10: =IF(OR(Model!J$8<'Inputs & Drivers'!$F41,Model!J$8>'Inputs & Drivers'!$J41),0,IF(J$8='Inputs & Drivers'!$F41,1,Model!I10+1)) -> 0 | K10: =IF(OR(Model!K$8<'Inputs & Drivers'!$F41,Model!K$8>'Inputs & Drivers'!$J41),0,IF(K$8='Inputs & Drivers'!$F41,1,Model!J10+1)) -> 0 | L10: =IF(OR(Model!L$8<'Inputs & Drivers'!$F41,Model!L$8>'Inputs & Drivers'!$J41),0,IF(L$8='Inputs & Drivers'!$F41,1,Model!K10+1)) -> 0 | M10: =IF(OR(Model!M$8<'Inputs & Drivers'!$F41,Model!M$8>'Inputs & Drivers'!$J41),0,IF(M$8='Inputs & Drivers'!$F41,1,Model!L10+1)) -> 0 | N10: =IF(OR(Model!N$8<'Inputs & Drivers'!$F41,Model!N$8>'Inputs & Drivers'!$J41),0,IF(N$8='Inputs & Drivers'!$F41,1,Model!M10+1)) -> 0 | O10: =IF(OR(Model!O$8<'Inputs & Drivers'!$F41,Model!O$8>'Inputs & Drivers'!$J41),0,IF(O$8='Inputs & Drivers'!$F41,1,Model!N10+1)) -> 0 | P10: =IF(OR(Model!P$8<'Inputs & Drivers'!$F41,Model!P$8>'Inputs & Drivers'!$J41),0,IF(P$8='Inputs & Drivers'!$F41,1,Model!O10+1)) -> 0 | ... DI10: =IF(OR(Model!DI$8<'Inputs & Drivers'!$F41,Model!DI$8>'Inputs & Drivers'!$J41),0,IF(DI$8='Inputs & Drivers'!$F41,1,Model!DH10+1)) -> 0
B11: Concession Month | I11: =IF(OR(Model!I$8<'Inputs & Drivers'!$F42,Model!I$8>'Inputs & Drivers'!$J42),0,IF(I$8='Inputs & Drivers'!$F42,1,Model!H11+1)) -> 0 | J11: =IF(OR(Model!J$8<'Inputs & Drivers'!$F42,Model!J$8>'Inputs & Drivers'!$J42),0,IF(J$8='Inputs & Drivers'!$F42,1,Model!I11+1)) -> 0 | K11: =IF(OR(Model!K$8<'Inputs & Drivers'!$F42,Model!K$8>'Inputs & Drivers'!$J42),0,IF(K$8='Inputs & Drivers'!$F42,1,Model!J11+1)) -> 0 | L11: =IF(OR(Model!L$8<'Inputs & Drivers'!$F42,Model!L$8>'Inputs & Drivers'!$J42),0,IF(L$8='Inputs & Drivers'!$F42,1,Model!K11+1)) -> 0 | M11: =IF(OR(Model!M$8<'Inputs & Drivers'!$F42,Model!M$8>'Inputs & Drivers'!$J42),0,IF(M$8='Inputs & Drivers'!$F42,1,Model!L11+1)) -> 0 | N11: =IF(OR(Model!N$8<'Inputs & Drivers'!$F42,Model!N$8>'Inputs & Drivers'!$J42),0,IF(N$8='Inputs & Drivers'!$F42,1,Model!M11+1)) -> 0 | O11: =IF(OR(Model!O$8<'Inputs & Drivers'!$F42,Model!O$8>'Inputs & Drivers'!$J42),0,IF(O$8='Inputs & Drivers'!$F42,1,Model!N11+1)) -> 0 | P11: =IF(OR(Model!P$8<'Inputs & Drivers'!$F42,Model!P$8>'Inputs & Drivers'!$J42),0,IF(P$8='Inputs & Drivers'!$F42,1,Model!O11+1)) -> 0 | ... DI11: =IF(OR(Model!DI$8<'Inputs & Drivers'!$F42,Model!DI$8>'Inputs & Drivers'!$J42),0,IF(DI$8='Inputs & Drivers'!$F42,1,Model!DH11+1)) -> 0
B13: Development Timeline
B14: Acquisition Costs | H14: =(1/'Inputs & Drivers'!$H38)*(Model!H$8>='Inputs & Drivers'!$F38)*(Model!H$8<='Inputs & Drivers'!$J38) -> 1 | I14: =(1/'Inputs & Drivers'!$H38)*(Model!I$8>='Inputs & Drivers'!$F38)*(Model!I$8<='Inputs & Drivers'!$J38) -> 0 | J14: =(1/'Inputs & Drivers'!$H38)*(Model!J$8>='Inputs & Drivers'!$F38)*(Model!J$8<='Inputs & Drivers'!$J38) -> 0 | K14: =(1/'Inputs & Drivers'!$H38)*(Model!K$8>='Inputs & Drivers'!$F38)*(Model!K$8<='Inputs & Drivers'!$J38) -> 0 | L14: =(1/'Inputs & Drivers'!$H38)*(Model!L$8>='Inputs & Drivers'!$F38)*(Model!L$8<='Inputs & Drivers'!$J38) -> 0 | M14: =(1/'Inputs & Drivers'!$H38)*(Model!M$8>='Inputs & Drivers'!$F38)*(Model!M$8<='Inputs & Drivers'!$J38) -> 0 | N14: =(1/'Inputs & Drivers'!$H38)*(Model!N$8>='Inputs & Drivers'!$F38)*(Model!N$8<='Inputs & Drivers'!$J38) -> 0 | O14: =(1/'Inputs & Drivers'!$H38)*(Model!O$8>='Inputs & Drivers'!$F38)*(Model!O$8<='Inputs & Drivers'!$J38) -> 0 | ... BJ14: =(1/'Inputs & Drivers'!$H38)*(Model!BJ$8>='Inputs & Drivers'!$F38)*(Model!BJ$8<='Inputs & Drivers'!$J38) -> 0 | EL14: =SUMIF($H$4:$EJ$4,EL$5,$H14:$EJ14) -> 1 | EM14: =SUMIF($H$4:$EJ$4,EM$5,$H14:$EJ14) -> 0 | EN14: =SUMIF($H$4:$EJ$4,EN$5,$H14:$EJ14) -> 0 | EO14: =SUMIF($H$4:$EJ$4,EO$5,$H14:$EJ14) -> 0 | EP14: =SUMIF($H$4:$EJ$4,EP$5,$H14:$EJ14) -> 0 | EQ14: =SUMIF($H$4:$EJ$4,EQ$5,$H14:$EJ14) -> 0 | ER14: =SUMIF($H$4:$EJ$4,ER$5,$H14:$EJ14) -> 0 | ES14: =SUMIF($H$4:$EJ$4,ES$5,$H14:$EJ14) -> 0 | ... EW14: =SUMIF($H$4:$EJ$4,EW$5,$H14:$EJ14) -> 0
B15: Soft Costs | H15: =(1/'Inputs & Drivers'!$H39)*(Model!H$8>='Inputs & Drivers'!$F39)*(Model!H$8<='Inputs & Drivers'!$J39) -> 0 | I15: =(1/'Inputs & Drivers'!$H39)*(Model!I$8>='Inputs & Drivers'!$F39)*(Model!I$8<='Inputs & Drivers'!$J39) -> 0 | J15: =(1/'Inputs & Drivers'!$H39)*(Model!J$8>='Inputs & Drivers'!$F39)*(Model!J$8<='Inputs & Drivers'!$J39) -> 0 | K15: =(1/'Inputs & Drivers'!$H39)*(Model!K$8>='Inputs & Drivers'!$F39)*(Model!K$8<='Inputs & Drivers'!$J39) -> 0.05 | L15: =(1/'Inputs & Drivers'!$H39)*(Model!L$8>='Inputs & Drivers'!$F39)*(Model!L$8<='Inputs & Drivers'!$J39) -> 0.05 | M15: =(1/'Inputs & Drivers'!$H39)*(Model!M$8>='Inputs & Drivers'!$F39)*(Model!M$8<='Inputs & Drivers'!$J39) -> 0.05 | N15: =(1/'Inputs & Drivers'!$H39)*(Model!N$8>='Inputs & Drivers'!$F39)*(Model!N$8<='Inputs & Drivers'!$J39) -> 0.05 | O15: =(1/'Inputs & Drivers'!$H39)*(Model!O$8>='Inputs & Drivers'!$F39)*(Model!O$8<='Inputs & Drivers'!$J39) -> 0.05 | ... AL15: =(1/'Inputs & Drivers'!$H39)*(Model!AL$8>='Inputs & Drivers'!$F39)*(Model!AL$8<='Inputs & Drivers'!$J39) -> 0 | EL15: =SUMIF($H$4:$EJ$4,EL$5,$H15:$EJ15) -> 0 | EM15: =SUMIF($H$4:$EJ$4,EM$5,$H15:$EJ15) -> 0.5 | EN15: =SUMIF($H$4:$EJ$4,EN$5,$H15:$EJ15) -> 0.5 | EO15: =SUMIF($H$4:$EJ$4,EO$5,$H15:$EJ15) -> 0 | EP15: =SUMIF($H$4:$EJ$4,EP$5,$H15:$EJ15) -> 0 | EQ15: =SUMIF($H$4:$EJ$4,EQ$5,$H15:$EJ15) -> 0 | ER15: =SUMIF($H$4:$EJ$4,ER$5,$H15:$EJ15) -> 0 | ES15: =SUMIF($H$4:$EJ$4,ES$5,$H15:$EJ15) -> 0 | ... EW15: =SUMIF($H$4:$EJ$4,EW$5,$H15:$EJ15) -> 0
B16: Hard Costs | H16: =(1/'Inputs & Drivers'!$H40)*(Model!H$8>='Inputs & Drivers'!$F40)*(Model!H$8<='Inputs & Drivers'!$J40) -> 0 | I16: =(1/'Inputs & Drivers'!$H40)*(Model!I$8>='Inputs & Drivers'!$F40)*(Model!I$8<='Inputs & Drivers'!$J40) -> 0 | J16: =(1/'Inputs & Drivers'!$H40)*(Model!J$8>='Inputs & Drivers'!$F40)*(Model!J$8<='Inputs & Drivers'!$J40) -> 0 | K16: =(1/'Inputs & Drivers'!$H40)*(Model!K$8>='Inputs & Drivers'!$F40)*(Model!K$8<='Inputs & Drivers'!$J40) -> 0 | L16: =(1/'Inputs & Drivers'!$H40)*(Model!L$8>='Inputs & Drivers'!$F40)*(Model!L$8<='Inputs & Drivers'!$J40) -> 0 | M16: =(1/'Inputs & Drivers'!$H40)*(Model!M$8>='Inputs & Drivers'!$F40)*(Model!M$8<='Inputs & Drivers'!$J40) -> 0 | N16: =(1/'Inputs & Drivers'!$H40)*(Model!N$8>='Inputs & Drivers'!$F40)*(Model!N$8<='Inputs & Drivers'!$J40) -> 0 | O16: =(1/'Inputs & Drivers'!$H40)*(Model!O$8>='Inputs & Drivers'!$F40)*(Model!O$8<='Inputs & Drivers'!$J40) -> 0.0625 | ... BQ16: =(1/'Inputs & Drivers'!$H40)*(Model!BQ$8>='Inputs & Drivers'!$F40)*(Model!BQ$8<='Inputs & Drivers'!$J40) -> 0 | EL16: =SUMIF($H$4:$EJ$4,EL$5,$H16:$EJ16) -> 0 | EM16: =SUMIF($H$4:$EJ$4,EM$5,$H16:$EJ16) -> 0.375 | EN16: =SUMIF($H$4:$EJ$4,EN$5,$H16:$EJ16) -> 0.625 | EO16: =SUMIF($H$4:$EJ$4,EO$5,$H16:$EJ16) -> 0 | EP16: =SUMIF($H$4:$EJ$4,EP$5,$H16:$EJ16) -> 0 | EQ16: =SUMIF($H$4:$EJ$4,EQ$5,$H16:$EJ16) -> 0 | ER16: =SUMIF($H$4:$EJ$4,ER$5,$H16:$EJ16) -> 0 | ES16: =SUMIF($H$4:$EJ$4,ES$5,$H16:$EJ16) -> 0 | ... EW16: =SUMIF($H$4:$EJ$4,EW$5,$H16:$EJ16) -> 0
B17: Other Development Costs | H17: =H15 -> 0 | I17: =I15 -> 0 | J17: =J15 -> 0 | K17: =K15 -> 0.05 | L17: =L15 -> 0.05 | M17: =M15 -> 0.05 | N17: =N15 -> 0.05 | O17: =O15 -> 0.05 | ... BF17: =BF15 -> 0 | EL17: =SUMIF($H$4:$EJ$4,EL$5,$H17:$EJ17) -> 0 | EM17: =SUMIF($H$4:$EJ$4,EM$5,$H17:$EJ17) -> 0.5 | EN17: =SUMIF($H$4:$EJ$4,EN$5,$H17:$EJ17) -> 0.5 | EO17: =SUMIF($H$4:$EJ$4,EO$5,$H17:$EJ17) -> 0 | EP17: =SUMIF($H$4:$EJ$4,EP$5,$H17:$EJ17) -> 0 | EQ17: =SUMIF($H$4:$EJ$4,EQ$5,$H17:$EJ17) -> 0 | ER17: =SUMIF($H$4:$EJ$4,ER$5,$H17:$EJ17) -> 0 | ES17: =SUMIF($H$4:$EJ$4,ES$5,$H17:$EJ17) -> 0 | ... EW17: =SUMIF($H$4:$EJ$4,EW$5,$H17:$EJ17) -> 0
B19: Lease-up Timeline
B20: Remaining Unleased Units | H20: =H22 -> 0 | I20: =$C$6-I22 -> 300 | J20: =$C$6-J22 -> 300 | K20: =$C$6-K22 -> 300 | L20: =$C$6-L22 -> 300 | M20: =$C$6-M22 -> 300 | N20: =$C$6-N22 -> 300 | O20: =$C$6-O22 -> 300 | P20: =$C$6-P22 -> 300 | ... EJ20: =$C$6-EJ22 -> 0
B22: BOP - Occupied Units | H22: 0 | I22: =H24 -> 0 | J22: =I24 -> 0 | K22: =J24 -> 0 | L22: =K24 -> 0 | M22: =L24 -> 0 | N22: =M24 -> 0 | O22: =N24 -> 0 | P22: =O24 -> 0 | ... EJ22: =EI24 -> 300 | EL22: 0 | EM22: =EL24 -> 0 | EN22: =EM24 -> 0 | EO22: =EN24 -> 270 | EP22: =EO24 -> 300 | EQ22: =EP24 -> 300 | ER22: =EQ24 -> 300 | ES22: =ER24 -> 300 | ET22: =ES24 -> 300 | ... EW22: =EV24 -> 300
B23: Units Leased | H23: =IF(H$8<'Inputs & Drivers'!$F$41,0,MIN('Inputs & Drivers'!$C$37,Model!H$20)) -> 0 | I23: =IF(I$8<'Inputs & Drivers'!$F$41,0,MIN('Inputs & Drivers'!$C$37,Model!I$20)) -> 0 | J23: =IF(J$8<'Inputs & Drivers'!$F$41,0,MIN('Inputs & Drivers'!$C$37,Model!J$20)) -> 0 | K23: =IF(K$8<'Inputs & Drivers'!$F$41,0,MIN('Inputs & Drivers'!$C$37,Model!K$20)) -> 0 | L23: =IF(L$8<'Inputs & Drivers'!$F$41,0,MIN('Inputs & Drivers'!$C$37,Model!L$20)) -> 0 | M23: =IF(M$8<'Inputs & Drivers'!$F$41,0,MIN('Inputs & Drivers'!$C$37,Model!M$20)) -> 0 | N23: =IF(N$8<'Inputs & Drivers'!$F$41,0,MIN('Inputs & Drivers'!$C$37,Model!N$20)) -> 0 | O23: =IF(O$8<'Inputs & Drivers'!$F$41,0,MIN('Inputs & Drivers'!$C$37,Model!O$20)) -> 0 | ... EJ23: =IF(EJ$8<'Inputs & Drivers'!$F$41,0,MIN('Inputs & Drivers'!$C$37,Model!EJ$20)) -> 0 | EL23: =SUMIF($H$4:$EJ$4,EL$5,$H23:$EJ23) -> 0 | EM23: =SUMIF($H$4:$EJ$4,EM$5,$H23:$EJ23) -> 0 | EN23: =SUMIF($H$4:$EJ$4,EN$5,$H23:$EJ23) -> 270 | EO23: =SUMIF($H$4:$EJ$4,EO$5,$H23:$EJ23) -> 30 | EP23: =SUMIF($H$4:$EJ$4,EP$5,$H23:$EJ23) -> 0 | EQ23: =SUMIF($H$4:$EJ$4,EQ$5,$H23:$EJ23) -> 0 | ER23: =SUMIF($H$4:$EJ$4,ER$5,$H23:$EJ23) -> 0 | ES23: =SUMIF($H$4:$EJ$4,ES$5,$H23:$EJ23) -> 0 | ... EW23: =SUMIF($H$4:$EJ$4,EW$5,$H23:$EJ23) -> 0
B24: EOP - Occupied Units | H24: =H23+H22 -> 0 | I24: =I23+I22 -> 0 | J24: =J23+J22 -> 0 | K24: =K23+K22 -> 0 | L24: =L23+L22 -> 0 | M24: =M23+M22 -> 0 | N24: =N23+N22 -> 0 | O24: =O23+O22 -> 0 | ... EJ24: =EJ23+EJ22 -> 300 | EL24: =SUM(EL22:EL23) -> 0 | EM24: =SUM(EM22:EM23) -> 0 | EN24: =SUM(EN22:EN23) -> 270 | EO24: =SUM(EO22:EO23) -> 300 | EP24: =SUM(EP22:EP23) -> 300 | EQ24: =SUM(EQ22:EQ23) -> 300 | ER24: =SUM(ER22:ER23) -> 300 | ES24: =SUM(ES22:ES23) -> 300 | ... EW24: =SUM(EW22:EW23) -> 300
B26: Other Revenue (per month)
B27: Utility Reimbursement | H27: 30 | I27: =H27*(1+(INDEX('Inputs & Drivers'!$G$68:$G$78,MATCH(Model!I$4,'Inputs & Drivers'!$B$68:$B$78))/12)) -> 30 | J27: =I27*(1+(INDEX('Inputs & Drivers'!$G$68:$G$78,MATCH(Model!J$4,'Inputs & Drivers'!$B$68:$B$78))/12)) -> 30 | K27: =J27*(1+(INDEX('Inputs & Drivers'!$G$68:$G$78,MATCH(Model!K$4,'Inputs & Drivers'!$B$68:$B$78))/12)) -> 30 | L27: =K27*(1+(INDEX('Inputs & Drivers'!$G$68:$G$78,MATCH(Model!L$4,'Inputs & Drivers'!$B$68:$B$78))/12)) -> 30 | M27: =L27*(1+(INDEX('Inputs & Drivers'!$G$68:$G$78,MATCH(Model!M$4,'Inputs & Drivers'!$B$68:$B$78))/12)) -> 30 | N27: =M27*(1+(INDEX('Inputs & Drivers'!$G$68:$G$78,MATCH(Model!N$4,'Inputs & Drivers'!$B$68:$B$78))/12)) -> 30 | O27: =N27*(1+(INDEX('Inputs & Drivers'!$G$68:$G$78,MATCH(Model!O$4,'Inputs & Drivers'!$B$68:$B$78))/12)) -> 30 | P27: =O27*(1+(INDEX('Inputs & Drivers'!$G$68:$G$78,MATCH(Model!P$4,'Inputs & Drivers'!$B$68:$B$78))/12)) -> 30 | ... EJ27: =EI27*(1+(INDEX('Inputs & Drivers'!$G$68:$G$78,MATCH(Model!EJ$4,'Inputs & Drivers'!$B$68:$B$78))/12)) -> 36.635983 | EL27: =SUMIF($H$6:$EJ$6,EL$6,$H27:$EJ27) -> 30 | EM27: =SUMIF($H$6:$EJ$6,EM$6,$H27:$EJ27) -> 30 | EN27: =SUMIF($H$6:$EJ$6,EN$6,$H27:$EJ27) -> 30.605531 | EO27: =SUMIF($H$6:$EJ$6,EO$6,$H27:$EJ27) -> 31.223284 | EP27: =SUMIF($H$6:$EJ$6,EP$6,$H27:$EJ27) -> 31.853505 | EQ27: =SUMIF($H$6:$EJ$6,EQ$6,$H27:$EJ27) -> 32.496448 | ER27: =SUMIF($H$6:$EJ$6,ER$6,$H27:$EJ27) -> 33.152368 | ES27: =SUMIF($H$6:$EJ$6,ES$6,$H27:$EJ27) -> 33.821527 | ... EW27: =SUMIF($H$6:$EJ$6,EW$6,$H27:$EJ27) -> 36.635983
B28: Parking Revenue | H28: 100 | I28: =H28*(1+(INDEX('Inputs & Drivers'!$G$68:$G$78,MATCH(Model!I$4,'Inputs & Drivers'!$B$68:$B$78))/12)) -> 100 | J28: =I28*(1+(INDEX('Inputs & Drivers'!$G$68:$G$78,MATCH(Model!J$4,'Inputs & Drivers'!$B$68:$B$78))/12)) -> 100 | K28: =J28*(1+(INDEX('Inputs & Drivers'!$G$68:$G$78,MATCH(Model!K$4,'Inputs & Drivers'!$B$68:$B$78))/12)) -> 100 | L28: =K28*(1+(INDEX('Inputs & Drivers'!$G$68:$G$78,MATCH(Model!L$4,'Inputs & Drivers'!$B$68:$B$78))/12)) -> 100 | M28: =L28*(1+(INDEX('Inputs & Drivers'!$G$68:$G$78,MATCH(Model!M$4,'Inputs & Drivers'!$B$68:$B$78))/12)) -> 100 | N28: =M28*(1+(INDEX('Inputs & Drivers'!$G$68:$G$78,MATCH(Model!N$4,'Inputs & Drivers'!$B$68:$B$78))/12)) -> 100 | O28: =N28*(1+(INDEX('Inputs & Drivers'!$G$68:$G$78,MATCH(Model!O$4,'Inputs & Drivers'!$B$68:$B$78))/12)) -> 100 | P28: =O28*(1+(INDEX('Inputs & Drivers'!$G$68:$G$78,MATCH(Model!P$4,'Inputs & Drivers'!$B$68:$B$78))/12)) -> 100 | ... EJ28: =EI28*(1+(INDEX('Inputs & Drivers'!$G$68:$G$78,MATCH(Model!EJ$4,'Inputs & Drivers'!$B$68:$B$78))/12)) -> 122.11994 | EL28: =SUMIF($H$6:$EJ$6,EL$6,$H28:$EJ28) -> 100 | EM28: =SUMIF($H$6:$EJ$6,EM$6,$H28:$EJ28) -> 100 | EN28: =SUMIF($H$6:$EJ$6,EN$6,$H28:$EJ28) -> 102.01844 | EO28: =SUMIF($H$6:$EJ$6,EO$6,$H28:$EJ28) -> 104.07761 | EP28: =SUMIF($H$6:$EJ$6,EP$6,$H28:$EJ28) -> 106.17835 | EQ28: =SUMIF($H$6:$EJ$6,EQ$6,$H28:$EJ28) -> 108.32149 | ER28: =SUMIF($H$6:$EJ$6,ER$6,$H28:$EJ28) -> 110.50789 | ES28: =SUMIF($H$6:$EJ$6,ES$6,$H28:$EJ28) -> 112.73842 | ... EW28: =SUMIF($H$6:$EJ$6,EW$6,$H28:$EJ28) -> 122.11994
B29: Other Revenue | H29: 25 | I29: =H29*(1+(INDEX('Inputs & Drivers'!$G$68:$G$78,MATCH(Model!I$4,'Inputs & Drivers'!$B$68:$B$78))/12)) -> 25 | J29: =I29*(1+(INDEX('Inputs & Drivers'!$G$68:$G$78,MATCH(Model!J$4,'Inputs & Drivers'!$B$68:$B$78))/12)) -> 25 | K29: =J29*(1+(INDEX('Inputs & Drivers'!$G$68:$G$78,MATCH(Model!K$4,'Inputs & Drivers'!$B$68:$B$78))/12)) -> 25 | L29: =K29*(1+(INDEX('Inputs & Drivers'!$G$68:$G$78,MATCH(Model!L$4,'Inputs & Drivers'!$B$68:$B$78))/12)) -> 25 | M29: =L29*(1+(INDEX('Inputs & Drivers'!$G$68:$G$78,MATCH(Model!M$4,'Inputs & Drivers'!$B$68:$B$78))/12)) -> 25 | N29: =M29*(1+(INDEX('Inputs & Drivers'!$G$68:$G$78,MATCH(Model!N$4,'Inputs & Drivers'!$B$68:$B$78))/12)) -> 25 | O29: =N29*(1+(INDEX('Inputs & Drivers'!$G$68:$G$78,MATCH(Model!O$4,'Inputs & Drivers'!$B$68:$B$78))/12)) -> 25 | P29: =O29*(1+(INDEX('Inputs & Drivers'!$G$68:$G$78,MATCH(Model!P$4,'Inputs & Drivers'!$B$68:$B$78))/12)) -> 25 | ... EJ29: =EI29*(1+(INDEX('Inputs & Drivers'!$G$68:$G$78,MATCH(Model!EJ$4,'Inputs & Drivers'!$B$68:$B$78))/12)) -> 30.529986 | EL29: =SUMIF($H$6:$EJ$6,EL$6,$H29:$EJ29) -> 25 | EM29: =SUMIF($H$6:$EJ$6,EM$6,$H29:$EJ29) -> 25 | EN29: =SUMIF($H$6:$EJ$6,EN$6,$H29:$EJ29) -> 25.504609 | EO29: =SUMIF($H$6:$EJ$6,EO$6,$H29:$EJ29) -> 26.019403 | EP29: =SUMIF($H$6:$EJ$6,EP$6,$H29:$EJ29) -> 26.544588 | EQ29: =SUMIF($H$6:$EJ$6,EQ$6,$H29:$EJ29) -> 27.080373 | ER29: =SUMIF($H$6:$EJ$6,ER$6,$H29:$EJ29) -> 27.626973 | ES29: =SUMIF($H$6:$EJ$6,ES$6,$H29:$EJ29) -> 28.184606 | ... EW29: =SUMIF($H$6:$EJ$6,EW$6,$H29:$EJ29) -> 30.529986
B31: Operating Expenses (per year)
B32: Repairs & Maintenance | H32: ='Inputs & Drivers'!I49 -> 600 | I32: =H32*(1+(INDEX('Inputs & Drivers'!$I$68:$I$78,MATCH(Model!I$4,'Inputs & Drivers'!$B$68:$B$78))/12)) -> 600 | J32: =I32*(1+(INDEX('Inputs & Drivers'!$I$68:$I$78,MATCH(Model!J$4,'Inputs & Drivers'!$B$68:$B$78))/12)) -> 600 | K32: =J32*(1+(INDEX('Inputs & Drivers'!$I$68:$I$78,MATCH(Model!K$4,'Inputs & Drivers'!$B$68:$B$78))/12)) -> 600 | L32: =K32*(1+(INDEX('Inputs & Drivers'!$I$68:$I$78,MATCH(Model!L$4,'Inputs & Drivers'!$B$68:$B$78))/12)) -> 600 | M32: =L32*(1+(INDEX('Inputs & Drivers'!$I$68:$I$78,MATCH(Model!M$4,'Inputs & Drivers'!$B$68:$B$78))/12)) -> 600 | N32: =M32*(1+(INDEX('Inputs & Drivers'!$I$68:$I$78,MATCH(Model!N$4,'Inputs & Drivers'!$B$68:$B$78))/12)) -> 600 | O32: =N32*(1+(INDEX('Inputs & Drivers'!$I$68:$I$78,MATCH(Model!O$4,'Inputs & Drivers'!$B$68:$B$78))/12)) -> 600 | P32: =O32*(1+(INDEX('Inputs & Drivers'!$I$68:$I$78,MATCH(Model!P$4,'Inputs & Drivers'!$B$68:$B$78))/12)) -> 600 | ... EJ32: =EI32*(1+(INDEX('Inputs & Drivers'!$I$68:$I$78,MATCH(Model!EJ$4,'Inputs & Drivers'!$B$68:$B$78))/12)) -> 801.57302 | EL32: =SUMIF($H$6:$EJ$6,EL$6,$H32:$EJ32) -> 600 | EM32: =SUMIF($H$6:$EJ$6,EM$6,$H32:$EJ32) -> 600 | EN32: =SUMIF($H$6:$EJ$6,EN$6,$H32:$EJ32) -> 612.11061 | EO32: =SUMIF($H$6:$EJ$6,EO$6,$H32:$EJ32) -> 630.72854 | EP32: =SUMIF($H$6:$EJ$6,EP$6,$H32:$EJ32) -> 649.91276 | EQ32: =SUMIF($H$6:$EJ$6,EQ$6,$H32:$EJ32) -> 669.68047 | ER32: =SUMIF($H$6:$EJ$6,ER$6,$H32:$EJ32) -> 690.04945 | ES32: =SUMIF($H$6:$EJ$6,ES$6,$H32:$EJ32) -> 711.03796 | ... EW32: =SUMIF($H$6:$EJ$6,EW$6,$H32:$EJ32) -> 801.57302
B33: Turnover | H33: ='Inputs & Drivers'!I50 -> 250 | I33: =H33*(1+(INDEX('Inputs & Drivers'!$I$68:$I$78,MATCH(Model!I$4,'Inputs & Drivers'!$B$68:$B$78))/12)) -> 250 | J33: =I33*(1+(INDEX('Inputs & Drivers'!$I$68:$I$78,MATCH(Model!J$4,'Inputs & Drivers'!$B$68:$B$78))/12)) -> 250 | K33: =J33*(1+(INDEX('Inputs & Drivers'!$I$68:$I$78,MATCH(Model!K$4,'Inputs & Drivers'!$B$68:$B$78))/12)) -> 250 | L33: =K33*(1+(INDEX('Inputs & Drivers'!$I$68:$I$78,MATCH(Model!L$4,'Inputs & Drivers'!$B$68:$B$78))/12)) -> 250 | M33: =L33*(1+(INDEX('Inputs & Drivers'!$I$68:$I$78,MATCH(Model!M$4,'Inputs & Drivers'!$B$68:$B$78))/12)) -> 250 | N33: =M33*(1+(INDEX('Inputs & Drivers'!$I$68:$I$78,MATCH(Model!N$4,'Inputs & Drivers'!$B$68:$B$78))/12)) -> 250 | O33: =N33*(1+(INDEX('Inputs & Drivers'!$I$68:$I$78,MATCH(Model!O$4,'Inputs & Drivers'!$B$68:$B$78))/12)) -> 250 | P33: =O33*(1+(INDEX('Inputs & Drivers'!$I$68:$I$78,MATCH(Model!P$4,'Inputs & Drivers'!$B$68:$B$78))/12)) -> 250 | ... EJ33: =EI33*(1+(INDEX('Inputs & Drivers'!$I$68:$I$78,MATCH(Model!EJ$4,'Inputs & Drivers'!$B$68:$B$78))/12)) -> 333.98876 | EL33: =SUMIF($H$6:$EJ$6,EL$6,$H33:$EJ33) -> 250 | EM33: =SUMIF($H$6:$EJ$6,EM$6,$H33:$EJ33) -> 250 | EN33: =SUMIF($H$6:$EJ$6,EN$6,$H33:$EJ33) -> 255.04609 | EO33: =SUMIF($H$6:$EJ$6,EO$6,$H33:$EJ33) -> 262.80356 | EP33: =SUMIF($H$6:$EJ$6,EP$6,$H33:$EJ33) -> 270.79698 | EQ33: =SUMIF($H$6:$EJ$6,EQ$6,$H33:$EJ33) -> 279.03353 | ER33: =SUMIF($H$6:$EJ$6,ER$6,$H33:$EJ33) -> 287.5206 | ES33: =SUMIF($H$6:$EJ$6,ES$6,$H33:$EJ33) -> 296.26582 | ... EW33: =SUMIF($H$6:$EJ$6,EW$6,$H33:$EJ33) -> 333.98876
B34: Marketing | H34: ='Inputs & Drivers'!I51 -> 150 | I34: =H34*(1+(INDEX('Inputs & Drivers'!$I$68:$I$78,MATCH(Model!I$4,'Inputs & Drivers'!$B$68:$B$78))/12)) -> 150 | J34: =I34*(1+(INDEX('Inputs & Drivers'!$I$68:$I$78,MATCH(Model!J$4,'Inputs & Drivers'!$B$68:$B$78))/12)) -> 150 | K34: =J34*(1+(INDEX('Inputs & Drivers'!$I$68:$I$78,MATCH(Model!K$4,'Inputs & Drivers'!$B$68:$B$78))/12)) -> 150 | L34: =K34*(1+(INDEX('Inputs & Drivers'!$I$68:$I$78,MATCH(Model!L$4,'Inputs & Drivers'!$B$68:$B$78))/12)) -> 150 | M34: =L34*(1+(INDEX('Inputs & Drivers'!$I$68:$I$78,MATCH(Model!M$4,'Inputs & Drivers'!$B$68:$B$78))/12)) -> 150 | N34: =M34*(1+(INDEX('Inputs & Drivers'!$I$68:$I$78,MATCH(Model!N$4,'Inputs & Drivers'!$B$68:$B$78))/12)) -> 150 | O34: =N34*(1+(INDEX('Inputs & Drivers'!$I$68:$I$78,MATCH(Model!O$4,'Inputs & Drivers'!$B$68:$B$78))/12)) -> 150 | P34: =O34*(1+(INDEX('Inputs & Drivers'!$I$68:$I$78,MATCH(Model!P$4,'Inputs & Drivers'!$B$68:$B$78))/12)) -> 150 | ... EJ34: =EI34*(1+(INDEX('Inputs & Drivers'!$I$68:$I$78,MATCH(Model!EJ$4,'Inputs & Drivers'!$B$68:$B$78))/12)) -> 200.39325 | EL34: =SUMIF($H$6:$EJ$6,EL$6,$H34:$EJ34) -> 150 | EM34: =SUMIF($H$6:$EJ$6,EM$6,$H34:$EJ34) -> 150 | EN34: =SUMIF($H$6:$EJ$6,EN$6,$H34:$EJ34) -> 153.02765 | EO34: =SUMIF($H$6:$EJ$6,EO$6,$H34:$EJ34) -> 157.68214 | EP34: =SUMIF($H$6:$EJ$6,EP$6,$H34:$EJ34) -> 162.47819 | EQ34: =SUMIF($H$6:$EJ$6,EQ$6,$H34:$EJ34) -> 167.42012 | ER34: =SUMIF($H$6:$EJ$6,ER$6,$H34:$EJ34) -> 172.51236 | ES34: =SUMIF($H$6:$EJ$6,ES$6,$H34:$EJ34) -> 177.75949 | ... EW34: =SUMIF($H$6:$EJ$6,EW$6,$H34:$EJ34) -> 200.39325
B35: General & Administrative | H35: ='Inputs & Drivers'!I52 -> 375 | I35: =H35*(1+(INDEX('Inputs & Drivers'!$I$68:$I$78,MATCH(Model!I$4,'Inputs & Drivers'!$B$68:$B$78))/12)) -> 375 | J35: =I35*(1+(INDEX('Inputs & Drivers'!$I$68:$I$78,MATCH(Model!J$4,'Inputs & Drivers'!$B$68:$B$78))/12)) -> 375 | K35: =J35*(1+(INDEX('Inputs & Drivers'!$I$68:$I$78,MATCH(Model!K$4,'Inputs & Drivers'!$B$68:$B$78))/12)) -> 375 | L35: =K35*(1+(INDEX('Inputs & Drivers'!$I$68:$I$78,MATCH(Model!L$4,'Inputs & Drivers'!$B$68:$B$78))/12)) -> 375 | M35: =L35*(1+(INDEX('Inputs & Drivers'!$I$68:$I$78,MATCH(Model!M$4,'Inputs & Drivers'!$B$68:$B$78))/12)) -> 375 | N35: =M35*(1+(INDEX('Inputs & Drivers'!$I$68:$I$78,MATCH(Model!N$4,'Inputs & Drivers'!$B$68:$B$78))/12)) -> 375 | O35: =N35*(1+(INDEX('Inputs & Drivers'!$I$68:$I$78,MATCH(Model!O$4,'Inputs & Drivers'!$B$68:$B$78))/12)) -> 375 | P35: =O35*(1+(INDEX('Inputs & Drivers'!$I$68:$I$78,MATCH(Model!P$4,'Inputs & Drivers'!$B$68:$B$78))/12)) -> 375 | ... EJ35: =EI35*(1+(INDEX('Inputs & Drivers'!$I$68:$I$78,MATCH(Model!EJ$4,'Inputs & Drivers'!$B$68:$B$78))/12)) -> 500.98314 | EL35: =SUMIF($H$6:$EJ$6,EL$6,$H35:$EJ35) -> 375 | EM35: =SUMIF($H$6:$EJ$6,EM$6,$H35:$EJ35) -> 375 | EN35: =SUMIF($H$6:$EJ$6,EN$6,$H35:$EJ35) -> 382.56913 | EO35: =SUMIF($H$6:$EJ$6,EO$6,$H35:$EJ35) -> 394.20534 | EP35: =SUMIF($H$6:$EJ$6,EP$6,$H35:$EJ35) -> 406.19547 | EQ35: =SUMIF($H$6:$EJ$6,EQ$6,$H35:$EJ35) -> 418.5503 | ER35: =SUMIF($H$6:$EJ$6,ER$6,$H35:$EJ35) -> 431.2809 | ES35: =SUMIF($H$6:$EJ$6,ES$6,$H35:$EJ35) -> 444.39873 | ... EW35: =SUMIF($H$6:$EJ$6,EW$6,$H35:$EJ35) -> 500.98314
B36: Payroll | H36: ='Inputs & Drivers'!I53 -> 1100 | I36: =H36*(1+(INDEX('Inputs & Drivers'!$I$68:$I$78,MATCH(Model!I$4,'Inputs & Drivers'!$B$68:$B$78))/12)) -> 1100 | J36: =I36*(1+(INDEX('Inputs & Drivers'!$I$68:$I$78,MATCH(Model!J$4,'Inputs & Drivers'!$B$68:$B$78))/12)) -> 1100 | K36: =J36*(1+(INDEX('Inputs & Drivers'!$I$68:$I$78,MATCH(Model!K$4,'Inputs & Drivers'!$B$68:$B$78))/12)) -> 1100 | L36: =K36*(1+(INDEX('Inputs & Drivers'!$I$68:$I$78,MATCH(Model!L$4,'Inputs & Drivers'!$B$68:$B$78))/12)) -> 1100 | M36: =L36*(1+(INDEX('Inputs & Drivers'!$I$68:$I$78,MATCH(Model!M$4,'Inputs & Drivers'!$B$68:$B$78))/12)) -> 1100 | N36: =M36*(1+(INDEX('Inputs & Drivers'!$I$68:$I$78,MATCH(Model!N$4,'Inputs & Drivers'!$B$68:$B$78))/12)) -> 1100 | O36: =N36*(1+(INDEX('Inputs & Drivers'!$I$68:$I$78,MATCH(Model!O$4,'Inputs & Drivers'!$B$68:$B$78))/12)) -> 1100 | P36: =O36*(1+(INDEX('Inputs & Drivers'!$I$68:$I$78,MATCH(Model!P$4,'Inputs & Drivers'!$B$68:$B$78))/12)) -> 1100 | ... EJ36: =EI36*(1+(INDEX('Inputs & Drivers'!$I$68:$I$78,MATCH(Model!EJ$4,'Inputs & Drivers'!$B$68:$B$78))/12)) -> 1469.5505 | EL36: =SUMIF($H$6:$EJ$6,EL$6,$H36:$EJ36) -> 1100 | EM36: =SUMIF($H$6:$EJ$6,EM$6,$H36:$EJ36) -> 1100 | EN36: =SUMIF($H$6:$EJ$6,EN$6,$H36:$EJ36) -> 1122.2028 | EO36: =SUMIF($H$6:$EJ$6,EO$6,$H36:$EJ36) -> 1156.3357 | EP36: =SUMIF($H$6:$EJ$6,EP$6,$H36:$EJ36) -> 1191.5067 | EQ36: =SUMIF($H$6:$EJ$6,EQ$6,$H36:$EJ36) -> 1227.7475 | ER36: =SUMIF($H$6:$EJ$6,ER$6,$H36:$EJ36) -> 1265.0907 | ES36: =SUMIF($H$6:$EJ$6,ES$6,$H36:$EJ36) -> 1303.5696 | ... EW36: =SUMIF($H$6:$EJ$6,EW$6,$H36:$EJ36) -> 1469.5505
B37: Management Fees | H37: ='Inputs & Drivers'!I54 -> 448.107 | I37: =H37*(1+(INDEX('Inputs & Drivers'!$I$68:$I$78,MATCH(Model!I$4,'Inputs & Drivers'!$B$68:$B$78))/12)) -> 448.107 | J37: =I37*(1+(INDEX('Inputs & Drivers'!$I$68:$I$78,MATCH(Model!J$4,'Inputs & Drivers'!$B$68:$B$78))/12)) -> 448.107 | K37: =J37*(1+(INDEX('Inputs & Drivers'!$I$68:$I$78,MATCH(Model!K$4,'Inputs & Drivers'!$B$68:$B$78))/12)) -> 448.107 | L37: =K37*(1+(INDEX('Inputs & Drivers'!$I$68:$I$78,MATCH(Model!L$4,'Inputs & Drivers'!$B$68:$B$78))/12)) -> 448.107 | M37: =L37*(1+(INDEX('Inputs & Drivers'!$I$68:$I$78,MATCH(Model!M$4,'Inputs & Drivers'!$B$68:$B$78))/12)) -> 448.107 | N37: =M37*(1+(INDEX('Inputs & Drivers'!$I$68:$I$78,MATCH(Model!N$4,'Inputs & Drivers'!$B$68:$B$78))/12)) -> 448.107 | O37: =N37*(1+(INDEX('Inputs & Drivers'!$I$68:$I$78,MATCH(Model!O$4,'Inputs & Drivers'!$B$68:$B$78))/12)) -> 448.107 | P37: =O37*(1+(INDEX('Inputs & Drivers'!$I$68:$I$78,MATCH(Model!P$4,'Inputs & Drivers'!$B$68:$B$78))/12)) -> 448.107 | ... EJ37: =EI37*(1+(INDEX('Inputs & Drivers'!$I$68:$I$78,MATCH(Model!EJ$4,'Inputs & Drivers'!$B$68:$B$78))/12)) -> 598.6508 | EL37: =SUMIF($H$6:$EJ$6,EL$6,$H37:$EJ37) -> 448.107 | EM37: =SUMIF($H$6:$EJ$6,EM$6,$H37:$EJ37) -> 448.107 | EN37: =SUMIF($H$6:$EJ$6,EN$6,$H37:$EJ37) -> 457.15175 | EO37: =SUMIF($H$6:$EJ$6,EO$6,$H37:$EJ37) -> 471.05646 | EP37: =SUMIF($H$6:$EJ$6,EP$6,$H37:$EJ37) -> 485.38409 | EQ37: =SUMIF($H$6:$EJ$6,EQ$6,$H37:$EJ37) -> 500.14751 | ER37: =SUMIF($H$6:$EJ$6,ER$6,$H37:$EJ37) -> 515.35998 | ES37: =SUMIF($H$6:$EJ$6,ES$6,$H37:$EJ37) -> 531.03515 | ... EW37: =SUMIF($H$6:$EJ$6,EW$6,$H37:$EJ37) -> 598.6508
B38: Utilities | H38: ='Inputs & Drivers'!I55 -> 175 | I38: =H38*(1+(INDEX('Inputs & Drivers'!$I$68:$I$78,MATCH(Model!I$4,'Inputs & Drivers'!$B$68:$B$78))/12)) -> 175 | J38: =I38*(1+(INDEX('Inputs & Drivers'!$I$68:$I$78,MATCH(Model!J$4,'Inputs & Drivers'!$B$68:$B$78))/12)) -> 175 | K38: =J38*(1+(INDEX('Inputs & Drivers'!$I$68:$I$78,MATCH(Model!K$4,'Inputs & Drivers'!$B$68:$B$78))/12)) -> 175 | L38: =K38*(1+(INDEX('Inputs & Drivers'!$I$68:$I$78,MATCH(Model!L$4,'Inputs & Drivers'!$B$68:$B$78))/12)) -> 175 | M38: =L38*(1+(INDEX('Inputs & Drivers'!$I$68:$I$78,MATCH(Model!M$4,'Inputs & Drivers'!$B$68:$B$78))/12)) -> 175 | N38: =M38*(1+(INDEX('Inputs & Drivers'!$I$68:$I$78,MATCH(Model!N$4,'Inputs & Drivers'!$B$68:$B$78))/12)) -> 175 | O38: =N38*(1+(INDEX('Inputs & Drivers'!$I$68:$I$78,MATCH(Model!O$4,'Inputs & Drivers'!$B$68:$B$78))/12)) -> 175 | P38: =O38*(1+(INDEX('Inputs & Drivers'!$I$68:$I$78,MATCH(Model!P$4,'Inputs & Drivers'!$B$68:$B$78))/12)) -> 175 | ... EJ38: =EI38*(1+(INDEX('Inputs & Drivers'!$I$68:$I$78,MATCH(Model!EJ$4,'Inputs & Drivers'!$B$68:$B$78))/12)) -> 233.79213 | EL38: =SUMIF($H$6:$EJ$6,EL$6,$H38:$EJ38) -> 175 | EM38: =SUMIF($H$6:$EJ$6,EM$6,$H38:$EJ38) -> 175 | EN38: =SUMIF($H$6:$EJ$6,EN$6,$H38:$EJ38) -> 178.53226 | EO38: =SUMIF($H$6:$EJ$6,EO$6,$H38:$EJ38) -> 183.96249 | EP38: =SUMIF($H$6:$EJ$6,EP$6,$H38:$EJ38) -> 189.55789 | EQ38: =SUMIF($H$6:$EJ$6,EQ$6,$H38:$EJ38) -> 195.32347 | ER38: =SUMIF($H$6:$EJ$6,ER$6,$H38:$EJ38) -> 201.26442 | ES38: =SUMIF($H$6:$EJ$6,ES$6,$H38:$EJ38) -> 207.38607 | ... EW38: =SUMIF($H$6:$EJ$6,EW$6,$H38:$EJ38) -> 233.79213
B39: Real Estate Taxes | H39: ='Inputs & Drivers'!I56 -> 2166.6667 | I39: =H39*(1+(INDEX('Inputs & Drivers'!$J$68:$J$78,MATCH(Model!I$4,'Inputs & Drivers'!$B$68:$B$78))/12)) -> 2166.6667 | J39: =I39*(1+(INDEX('Inputs & Drivers'!$J$68:$J$78,MATCH(Model!J$4,'Inputs & Drivers'!$B$68:$B$78))/12)) -> 2166.6667 | K39: =J39*(1+(INDEX('Inputs & Drivers'!$J$68:$J$78,MATCH(Model!K$4,'Inputs & Drivers'!$B$68:$B$78))/12)) -> 2166.6667 | L39: =K39*(1+(INDEX('Inputs & Drivers'!$J$68:$J$78,MATCH(Model!L$4,'Inputs & Drivers'!$B$68:$B$78))/12)) -> 2166.6667 | M39: =L39*(1+(INDEX('Inputs & Drivers'!$J$68:$J$78,MATCH(Model!M$4,'Inputs & Drivers'!$B$68:$B$78))/12)) -> 2166.6667 | N39: =M39*(1+(INDEX('Inputs & Drivers'!$J$68:$J$78,MATCH(Model!N$4,'Inputs & Drivers'!$B$68:$B$78))/12)) -> 2166.6667 | O39: =N39*(1+(INDEX('Inputs & Drivers'!$J$68:$J$78,MATCH(Model!O$4,'Inputs & Drivers'!$B$68:$B$78))/12)) -> 2166.6667 | P39: =O39*(1+(INDEX('Inputs & Drivers'!$J$68:$J$78,MATCH(Model!P$4,'Inputs & Drivers'!$B$68:$B$78))/12)) -> 2166.6667 | ... EJ39: =EI39*(1+(INDEX('Inputs & Drivers'!$J$68:$J$78,MATCH(Model!EJ$4,'Inputs & Drivers'!$B$68:$B$78))/12)) -> 2645.9321 | EL39: =SUMIF($H$6:$EJ$6,EL$6,$H39:$EJ39) -> 2166.6667 | EM39: =SUMIF($H$6:$EJ$6,EM$6,$H39:$EJ39) -> 2166.6667 | EN39: =SUMIF($H$6:$EJ$6,EN$6,$H39:$EJ39) -> 2210.3994 | EO39: =SUMIF($H$6:$EJ$6,EO$6,$H39:$EJ39) -> 2255.0149 | EP39: =SUMIF($H$6:$EJ$6,EP$6,$H39:$EJ39) -> 2300.5309 | EQ39: =SUMIF($H$6:$EJ$6,EQ$6,$H39:$EJ39) -> 2346.9657 | ER39: =SUMIF($H$6:$EJ$6,ER$6,$H39:$EJ39) -> 2394.3377 | ES39: =SUMIF($H$6:$EJ$6,ES$6,$H39:$EJ39) -> 2442.6658 | ... EW39: =SUMIF($H$6:$EJ$6,EW$6,$H39:$EJ39) -> 2645.9321
B40: Property Insurance | H40: ='Inputs & Drivers'!I57 -> 275 | I40: =H40*(1+(INDEX('Inputs & Drivers'!$I$68:$I$78,MATCH(Model!I$4,'Inputs & Drivers'!$B$68:$B$78))/12)) -> 275 | J40: =I40*(1+(INDEX('Inputs & Drivers'!$I$68:$I$78,MATCH(Model!J$4,'Inputs & Drivers'!$B$68:$B$78))/12)) -> 275 | K40: =J40*(1+(INDEX('Inputs & Drivers'!$I$68:$I$78,MATCH(Model!K$4,'Inputs & Drivers'!$B$68:$B$78))/12)) -> 275 | L40: =K40*(1+(INDEX('Inputs & Drivers'!$I$68:$I$78,MATCH(Model!L$4,'Inputs & Drivers'!$B$68:$B$78))/12)) -> 275 | M40: =L40*(1+(INDEX('Inputs & Drivers'!$I$68:$I$78,MATCH(Model!M$4,'Inputs & Drivers'!$B$68:$B$78))/12)) -> 275 | N40: =M40*(1+(INDEX('Inputs & Drivers'!$I$68:$I$78,MATCH(Model!N$4,'Inputs & Drivers'!$B$68:$B$78))/12)) -> 275 | O40: =N40*(1+(INDEX('Inputs & Drivers'!$I$68:$I$78,MATCH(Model!O$4,'Inputs & Drivers'!$B$68:$B$78))/12)) -> 275 | P40: =O40*(1+(INDEX('Inputs & Drivers'!$I$68:$I$78,MATCH(Model!P$4,'Inputs & Drivers'!$B$68:$B$78))/12)) -> 275 | ... EJ40: =EI40*(1+(INDEX('Inputs & Drivers'!$I$68:$I$78,MATCH(Model!EJ$4,'Inputs & Drivers'!$B$68:$B$78))/12)) -> 367.38763 | EL40: =SUMIF($H$6:$EJ$6,EL$6,$H40:$EJ40) -> 275 | EM40: =SUMIF($H$6:$EJ$6,EM$6,$H40:$EJ40) -> 275 | EN40: =SUMIF($H$6:$EJ$6,EN$6,$H40:$EJ40) -> 280.5507 | EO40: =SUMIF($H$6:$EJ$6,EO$6,$H40:$EJ40) -> 289.08392 | EP40: =SUMIF($H$6:$EJ$6,EP$6,$H40:$EJ40) -> 297.87668 | EQ40: =SUMIF($H$6:$EJ$6,EQ$6,$H40:$EJ40) -> 306.93688 | ER40: =SUMIF($H$6:$EJ$6,ER$6,$H40:$EJ40) -> 316.27266 | ES40: =SUMIF($H$6:$EJ$6,ES$6,$H40:$EJ40) -> 325.8924 | ... EW40: =SUMIF($H$6:$EJ$6,EW$6,$H40:$EJ40) -> 367.38763
B41: Capital Reserves | H41: ='Inputs & Drivers'!I59 -> 150 | I41: =H41 -> 150 | J41: =I41 -> 150 | K41: =J41 -> 150 | L41: =K41 -> 150 | M41: =L41 -> 150 | N41: =M41 -> 150 | O41: =N41 -> 150 | P41: =O41 -> 150 | ... EJ41: =EI41 -> 150 | EL41: =SUMIF($H$6:$EJ$6,EL$6,$H41:$EJ41) -> 150 | EM41: =SUMIF($H$6:$EJ$6,EM$6,$H41:$EJ41) -> 150 | EN41: =SUMIF($H$6:$EJ$6,EN$6,$H41:$EJ41) -> 150 | EO41: =SUMIF($H$6:$EJ$6,EO$6,$H41:$EJ41) -> 150 | EP41: =SUMIF($H$6:$EJ$6,EP$6,$H41:$EJ41) -> 150 | EQ41: =SUMIF($H$6:$EJ$6,EQ$6,$H41:$EJ41) -> 150 | ER41: =SUMIF($H$6:$EJ$6,ER$6,$H41:$EJ41) -> 150 | ES41: =SUMIF($H$6:$EJ$6,ES$6,$H41:$EJ41) -> 150 | ... EW41: =SUMIF($H$6:$EJ$6,EW$6,$H41:$EJ41) -> 150
B43: Rent Growth | I43: =INDEX('Inputs & Drivers'!$E$68:$E$78,MATCH(Model!I$4,'Inputs & Drivers'!$B$68:$B$78))/12 -> 0 | J43: =INDEX('Inputs & Drivers'!$E$68:$E$78,MATCH(Model!J$4,'Inputs & Drivers'!$B$68:$B$78))/12 -> 0 | K43: =INDEX('Inputs & Drivers'!$E$68:$E$78,MATCH(Model!K$4,'Inputs & Drivers'!$B$68:$B$78))/12 -> 0 | L43: =INDEX('Inputs & Drivers'!$E$68:$E$78,MATCH(Model!L$4,'Inputs & Drivers'!$B$68:$B$78))/12 -> 0 | M43: =INDEX('Inputs & Drivers'!$E$68:$E$78,MATCH(Model!M$4,'Inputs & Drivers'!$B$68:$B$78))/12 -> 0 | N43: =INDEX('Inputs & Drivers'!$E$68:$E$78,MATCH(Model!N$4,'Inputs & Drivers'!$B$68:$B$78))/12 -> 0 | O43: =INDEX('Inputs & Drivers'!$E$68:$E$78,MATCH(Model!O$4,'Inputs & Drivers'!$B$68:$B$78))/12 -> 0 | P43: =INDEX('Inputs & Drivers'!$E$68:$E$78,MATCH(Model!P$4,'Inputs & Drivers'!$B$68:$B$78))/12 -> 0 | ... EJ43: =INDEX('Inputs & Drivers'!$E$68:$E$78,MATCH(Model!EJ$4,'Inputs & Drivers'!$B$68:$B$78))/12 -> 0.0025 | EL43: =SUMIF($H$4:$EJ$4,EL$5,$H43:$EJ43) -> 0 | EM43: =SUMIF($H$4:$EJ$4,EM$5,$H43:$EJ43) -> 0 | EN43: =SUMIF($H$4:$EJ$4,EN$5,$H43:$EJ43) -> 0.02 | EO43: =SUMIF($H$4:$EJ$4,EO$5,$H43:$EJ43) -> 0.03 | EP43: =SUMIF($H$4:$EJ$4,EP$5,$H43:$EJ43) -> 0.03 | EQ43: =SUMIF($H$4:$EJ$4,EQ$5,$H43:$EJ43) -> 0.03 | ER43: =SUMIF($H$4:$EJ$4,ER$5,$H43:$EJ43) -> 0.03 | ES43: =SUMIF($H$4:$EJ$4,ES$5,$H43:$EJ43) -> 0.03 | ... EW43: =SUMIF($H$4:$EJ$4,EW$5,$H43:$EJ43) -> 0.03
B44: Potential Rent | H44: ='Inputs & Drivers'!E50 -> 1480 | I44: =H44*(1+I43) -> 1480 | J44: =I44*(1+J43) -> 1480 | K44: =J44*(1+K43) -> 1480 | L44: =K44*(1+L43) -> 1480 | M44: =L44*(1+M43) -> 1480 | N44: =M44*(1+N43) -> 1480 | O44: =N44*(1+O43) -> 1480 | P44: =O44*(1+P43) -> 1480 | ... EJ44: =EI44*(1+EJ43) -> 1977.2134 | EL44: =SUMIF($H$6:$EJ$6,EL$6,$H44:$EJ44) -> 1480 | EM44: =SUMIF($H$6:$EJ$6,EM$6,$H44:$EJ44) -> 1480 | EN44: =SUMIF($H$6:$EJ$6,EN$6,$H44:$EJ44) -> 1509.8728 | EO44: =SUMIF($H$6:$EJ$6,EO$6,$H44:$EJ44) -> 1555.7971 | EP44: =SUMIF($H$6:$EJ$6,EP$6,$H44:$EJ44) -> 1603.1181 | EQ44: =SUMIF($H$6:$EJ$6,EQ$6,$H44:$EJ44) -> 1651.8785 | ER44: =SUMIF($H$6:$EJ$6,ER$6,$H44:$EJ44) -> 1702.122 | ES44: =SUMIF($H$6:$EJ$6,ES$6,$H44:$EJ44) -> 1753.8936 | ... EW44: =SUMIF($H$6:$EJ$6,EW$6,$H44:$EJ44) -> 1977.2134
B45: Concessions | H45: =-H44/12*('Inputs & Drivers'!$C$38)*(H$5<='Inputs & Drivers'!$J$42) -> -123.33333 | I45: =-I44/12*('Inputs & Drivers'!$C$38)*(I$5<='Inputs & Drivers'!$J$42) -> -123.33333 | J45: =-J44/12*('Inputs & Drivers'!$C$38)*(J$5<='Inputs & Drivers'!$J$42) -> -123.33333 | K45: =-K44/12*('Inputs & Drivers'!$C$38)*(K$5<='Inputs & Drivers'!$J$42) -> -123.33333 | L45: =-L44/12*('Inputs & Drivers'!$C$38)*(L$5<='Inputs & Drivers'!$J$42) -> -123.33333 | M45: =-M44/12*('Inputs & Drivers'!$C$38)*(M$5<='Inputs & Drivers'!$J$42) -> -123.33333 | N45: =-N44/12*('Inputs & Drivers'!$C$38)*(N$5<='Inputs & Drivers'!$J$42) -> -123.33333 | O45: =-O44/12*('Inputs & Drivers'!$C$38)*(O$5<='Inputs & Drivers'!$J$42) -> -123.33333 | ... EJ45: =-EJ44/12*('Inputs & Drivers'!$C$38)*(EJ$5<='Inputs & Drivers'!$J$42) -> 0 | EL45: =SUMIF($H$6:$EJ$6,EL$6,$H45:$EJ45) -> -123.33333 | EM45: =SUMIF($H$6:$EJ$6,EM$6,$H45:$EJ45) -> -123.33333 | EN45: =SUMIF($H$6:$EJ$6,EN$6,$H45:$EJ45) -> -125.82274 | EO45: =SUMIF($H$6:$EJ$6,EO$6,$H45:$EJ45) -> 0 | EP45: =SUMIF($H$6:$EJ$6,EP$6,$H45:$EJ45) -> 0 | EQ45: =SUMIF($H$6:$EJ$6,EQ$6,$H45:$EJ45) -> 0 | ER45: =SUMIF($H$6:$EJ$6,ER$6,$H45:$EJ45) -> 0 | ES45: =SUMIF($H$6:$EJ$6,ES$6,$H45:$EJ45) -> 0 | ... EW45: =SUMIF($H$6:$EJ$6,EW$6,$H45:$EJ45) -> 0
B46: Effective Rent | H46: =SUM(H44+H45) -> 1356.6667 | I46: =SUM(I44+I45) -> 1356.6667 | J46: =SUM(J44+J45) -> 1356.6667 | K46: =SUM(K44+K45) -> 1356.6667 | L46: =SUM(L44+L45) -> 1356.6667 | M46: =SUM(M44+M45) -> 1356.6667 | N46: =SUM(N44+N45) -> 1356.6667 | O46: =SUM(O44+O45) -> 1356.6667 | ... EJ46: =SUM(EJ44+EJ45) -> 1977.2134 | EL46: =SUM(EL44:EL45) -> 1356.6667 | EM46: =SUM(EM44:EM45) -> 1356.6667 | EN46: =SUM(EN44:EN45) -> 1384.0501 | EO46: =SUM(EO44:EO45) -> 1555.7971 | EP46: =SUM(EP44:EP45) -> 1603.1181 | EQ46: =SUM(EQ44:EQ45) -> 1651.8785 | ER46: =SUM(ER44:ER45) -> 1702.122 | ES46: =SUM(ES44:ES45) -> 1753.8936 | ... EW46: =SUM(EW44:EW45) -> 1977.2134
B48: INCOME
B49: Net Potential Rent | F49: {=SUMPRODUCT(($H49:$EJ49)*($H$6:$EJ$6<=$C$5))} -> 7103622.7 | I49: =I44*I22 -> 0 | J49: =J44*J22 -> 0 | K49: =K44*K22 -> 0 | L49: =L44*L22 -> 0 | M49: =M44*M22 -> 0 | N49: =N44*N22 -> 0 | O49: =O44*O22 -> 0 | P49: =P44*P22 -> 0 | ... EJ49: =EJ44*EJ22 -> 593164.03 | EL49: =SUMIF($H$4:$EJ$4,EL$5,$H49:$EJ49) -> 0 | EM49: =SUMIF($H$4:$EJ$4,EM$5,$H49:$EJ49) -> 0 | EN49: =SUMIF($H$4:$EJ$4,EN$5,$H49:$EJ49) -> 1624347.5 | EO49: =SUMIF($H$4:$EJ$4,EO$5,$H49:$EJ49) -> 5479275.1 | EP49: =SUMIF($H$4:$EJ$4,EP$5,$H49:$EJ49) -> 5692723.1 | EQ49: =SUMIF($H$4:$EJ$4,EQ$5,$H49:$EJ49) -> 5865872.8 | ER49: =SUMIF($H$4:$EJ$4,ER$5,$H49:$EJ49) -> 6044288.9 | ES49: =SUMIF($H$4:$EJ$4,ES$5,$H49:$EJ49) -> 6228131.7 | ... EW49: =SUMIF($H$4:$EJ$4,EW$5,$H49:$EJ49) -> 7021147.4
B50: Concessions | F50: {=SUMPRODUCT(($H50:$EJ50)*($H$6:$EJ$6<=$C$5))} -> -398461.45 | I50: =I45*I22 -> 0 | J50: =J45*J22 -> 0 | K50: =K45*K22 -> 0 | L50: =L45*L22 -> 0 | M50: =M45*M22 -> 0 | N50: =N45*N22 -> 0 | O50: =O45*O22 -> 0 | P50: =P45*P22 -> 0 | ... EJ50: =EJ45*EJ22 -> 0 | EL50: =SUMIF($H$4:$EJ$4,EL$5,$H50:$EJ50) -> 0 | EM50: =SUMIF($H$4:$EJ$4,EM$5,$H50:$EJ50) -> 0 | EN50: =SUMIF($H$4:$EJ$4,EN$5,$H50:$EJ50) -> -135362.29 | EO50: =SUMIF($H$4:$EJ$4,EO$5,$H50:$EJ50) -> -263099.16 | EP50: =SUMIF($H$4:$EJ$4,EP$5,$H50:$EJ50) -> 0 | EQ50: =SUMIF($H$4:$EJ$4,EQ$5,$H50:$EJ50) -> 0 | ER50: =SUMIF($H$4:$EJ$4,ER$5,$H50:$EJ50) -> 0 | ES50: =SUMIF($H$4:$EJ$4,ES$5,$H50:$EJ50) -> 0 | ... EW50: =SUMIF($H$4:$EJ$4,EW$5,$H50:$EJ50) -> 0
B51: Net Effective Rent | F51: =SUM(F49:F50) -> 6705161.2 | I51: =SUM(I49:I50) -> 0 | J51: =SUM(J49:J50) -> 0 | K51: =SUM(K49:K50) -> 0 | L51: =SUM(L49:L50) -> 0 | M51: =SUM(M49:M50) -> 0 | N51: =SUM(N49:N50) -> 0 | O51: =SUM(O49:O50) -> 0 | P51: =SUM(P49:P50) -> 0 | ... EJ51: =SUM(EJ49:EJ50) -> 593164.03 | EL51: =SUM(EL49:EL50) -> 0 | EM51: =SUM(EM49:EM50) -> 0 | EN51: =SUM(EN49:EN50) -> 1488985.2 | EO51: =SUM(EO49:EO50) -> 5216176 | EP51: =SUM(EP49:EP50) -> 5692723.1 | EQ51: =SUM(EQ49:EQ50) -> 5865872.8 | ER51: =SUM(ER49:ER50) -> 6044288.9 | ES51: =SUM(ES49:ES50) -> 6228131.7 | ... EW51: =SUM(EW49:EW50) -> 7021147.4
B52: Vacancy Loss | F52: {=SUMPRODUCT(($H52:$EJ52)*($H$6:$EJ$6<=$C$5))} -> -499140.99 | I52: =-(1-INDEX('Inputs & Drivers'!$D$68:$D$78,MATCH(Model!I$4,'Inputs & Drivers'!$B$68:$B$78,0)))*I51 -> 0 | J52: =-(1-INDEX('Inputs & Drivers'!$D$68:$D$78,MATCH(Model!J$4,'Inputs & Drivers'!$B$68:$B$78,0)))*J51 -> 0 | K52: =-(1-INDEX('Inputs & Drivers'!$D$68:$D$78,MATCH(Model!K$4,'Inputs & Drivers'!$B$68:$B$78,0)))*K51 -> 0 | L52: =-(1-INDEX('Inputs & Drivers'!$D$68:$D$78,MATCH(Model!L$4,'Inputs & Drivers'!$B$68:$B$78,0)))*L51 -> 0 | M52: =-(1-INDEX('Inputs & Drivers'!$D$68:$D$78,MATCH(Model!M$4,'Inputs & Drivers'!$B$68:$B$78,0)))*M51 -> 0 | N52: =-(1-INDEX('Inputs & Drivers'!$D$68:$D$78,MATCH(Model!N$4,'Inputs & Drivers'!$B$68:$B$78,0)))*N51 -> 0 | O52: =-(1-INDEX('Inputs & Drivers'!$D$68:$D$78,MATCH(Model!O$4,'Inputs & Drivers'!$B$68:$B$78,0)))*O51 -> 0 | P52: =-(1-INDEX('Inputs & Drivers'!$D$68:$D$78,MATCH(Model!P$4,'Inputs & Drivers'!$B$68:$B$78,0)))*P51 -> 0 | ... EJ52: =-(1-INDEX('Inputs & Drivers'!$D$68:$D$78,MATCH(Model!EJ$4,'Inputs & Drivers'!$B$68:$B$78,0)))*EJ51 -> -41521.482 | EL52: =SUMIF($H$4:$EJ$4,EL$5,$H52:$EJ52) -> 0 | EM52: =SUMIF($H$4:$EJ$4,EM$5,$H52:$EJ52) -> 0 | EN52: =SUMIF($H$4:$EJ$4,EN$5,$H52:$EJ52) -> -134008.67 | EO52: =SUMIF($H$4:$EJ$4,EO$5,$H52:$EJ52) -> -365132.32 | EP52: =SUMIF($H$4:$EJ$4,EP$5,$H52:$EJ52) -> -398490.62 | EQ52: =SUMIF($H$4:$EJ$4,EQ$5,$H52:$EJ52) -> -410611.09 | ER52: =SUMIF($H$4:$EJ$4,ER$5,$H52:$EJ52) -> -423100.22 | ES52: =SUMIF($H$4:$EJ$4,ES$5,$H52:$EJ52) -> -435969.22 | ... EW52: =SUMIF($H$4:$EJ$4,EW$5,$H52:$EJ52) -> -491480.32
B53: Non-Revenue Units | F53: {=SUMPRODUCT(($H53:$EJ53)*($H$6:$EJ$6<=$C$5))} -> -33525.806 | I53: =-'Inputs & Drivers'!$D57*Model!I$51 -> 0 | J53: =-'Inputs & Drivers'!$D57*Model!J$51 -> 0 | K53: =-'Inputs & Drivers'!$D57*Model!K$51 -> 0 | L53: =-'Inputs & Drivers'!$D57*Model!L$51 -> 0 | M53: =-'Inputs & Drivers'!$D57*Model!M$51 -> 0 | N53: =-'Inputs & Drivers'!$D57*Model!N$51 -> 0 | O53: =-'Inputs & Drivers'!$D57*Model!O$51 -> 0 | P53: =-'Inputs & Drivers'!$D57*Model!P$51 -> 0 | ... EJ53: =-'Inputs & Drivers'!$D57*Model!EJ$51 -> -2965.8202 | EL53: =SUMIF($H$4:$EJ$4,EL$5,$H53:$EJ53) -> 0 | EM53: =SUMIF($H$4:$EJ$4,EM$5,$H53:$EJ53) -> 0 | EN53: =SUMIF($H$4:$EJ$4,EN$5,$H53:$EJ53) -> -7444.9262 | EO53: =SUMIF($H$4:$EJ$4,EO$5,$H53:$EJ53) -> -26080.88 | EP53: =SUMIF($H$4:$EJ$4,EP$5,$H53:$EJ53) -> -28463.616 | EQ53: =SUMIF($H$4:$EJ$4,EQ$5,$H53:$EJ53) -> -29329.364 | ER53: =SUMIF($H$4:$EJ$4,ER$5,$H53:$EJ53) -> -30221.444 | ES53: =SUMIF($H$4:$EJ$4,ES$5,$H53:$EJ53) -> -31140.659 | ... EW53: =SUMIF($H$4:$EJ$4,EW$5,$H53:$EJ53) -> -35105.737
B54: Bad Debt | F54: {=SUMPRODUCT(($H54:$EJ54)*($H$6:$EJ$6<=$C$5))} -> -50288.709 | I54: =-'Inputs & Drivers'!$D58*Model!I$51 -> 0 | J54: =-'Inputs & Drivers'!$D58*Model!J$51 -> 0 | K54: =-'Inputs & Drivers'!$D58*Model!K$51 -> 0 | L54: =-'Inputs & Drivers'!$D58*Model!L$51 -> 0 | M54: =-'Inputs & Drivers'!$D58*Model!M$51 -> 0 | N54: =-'Inputs & Drivers'!$D58*Model!N$51 -> 0 | O54: =-'Inputs & Drivers'!$D58*Model!O$51 -> 0 | P54: =-'Inputs & Drivers'!$D58*Model!P$51 -> 0 | ... EJ54: =-'Inputs & Drivers'!$D58*Model!EJ$51 -> -4448.7302 | EL54: =SUMIF($H$4:$EJ$4,EL$5,$H54:$EJ54) -> 0 | EM54: =SUMIF($H$4:$EJ$4,EM$5,$H54:$EJ54) -> 0 | EN54: =SUMIF($H$4:$EJ$4,EN$5,$H54:$EJ54) -> -11167.389 | EO54: =SUMIF($H$4:$EJ$4,EO$5,$H54:$EJ54) -> -39121.32 | EP54: =SUMIF($H$4:$EJ$4,EP$5,$H54:$EJ54) -> -42695.423 | EQ54: =SUMIF($H$4:$EJ$4,EQ$5,$H54:$EJ54) -> -43994.046 | ER54: =SUMIF($H$4:$EJ$4,ER$5,$H54:$EJ54) -> -45332.167 | ES54: =SUMIF($H$4:$EJ$4,ES$5,$H54:$EJ54) -> -46710.988 | ... EW54: =SUMIF($H$4:$EJ$4,EW$5,$H54:$EJ54) -> -52658.605
B55: Total Rental Income | F55: =SUM(F51:F54) -> 6122205.7 | I55: =SUM(I51:I54) -> 0 | J55: =SUM(J51:J54) -> 0 | K55: =SUM(K51:K54) -> 0 | L55: =SUM(L51:L54) -> 0 | M55: =SUM(M51:M54) -> 0 | N55: =SUM(N51:N54) -> 0 | O55: =SUM(O51:O54) -> 0 | P55: =SUM(P51:P54) -> 0 | ... EJ55: =SUM(EJ51:EJ54) -> 544228 | EL55: =SUM(EL51:EL54) -> 0 | EM55: =SUM(EM51:EM54) -> 0 | EN55: =SUM(EN51:EN54) -> 1336364.3 | EO55: =SUM(EO51:EO54) -> 4785841.5 | EP55: =SUM(EP51:EP54) -> 5223073.5 | EQ55: =SUM(EQ51:EQ54) -> 5381938.2 | ER55: =SUM(ER51:ER54) -> 5545635.1 | ES55: =SUM(ES51:ES54) -> 5714310.8 | ... EW55: =SUM(EW51:EW54) -> 6441902.7
B56: Effective Rent / Month | I56: =IFERROR(I51/I22,0) -> 0 | J56: =IFERROR(J51/J22,0) -> 0 | K56: =IFERROR(K51/K22,0) -> 0 | L56: =IFERROR(L51/L22,0) -> 0 | M56: =IFERROR(M51/M22,0) -> 0 | N56: =IFERROR(N51/N22,0) -> 0 | O56: =IFERROR(O51/O22,0) -> 0 | P56: =IFERROR(P51/P22,0) -> 0 | ... EJ56: =IFERROR(EJ51/EJ22,0) -> 1977.2134 | EM56: =EM46 -> 1356.6667 | EN56: =EN46 -> 1384.0501 | EO56: =EO46 -> 1555.7971 | EP56: =EP46 -> 1603.1181 | EQ56: =EQ46 -> 1651.8785 | ER56: =ER46 -> 1702.122 | ES56: =ES46 -> 1753.8936 | ET56: =ET46 -> 1807.24 | ... EW56: =EW46 -> 1977.2134
B57: Effective Rent PSF / Month | I57: =I56/'Inputs & Drivers'!$F$34 -> 0 | J57: =J56/'Inputs & Drivers'!$F$34 -> 0 | K57: =K56/'Inputs & Drivers'!$F$34 -> 0 | L57: =L56/'Inputs & Drivers'!$F$34 -> 0 | M57: =M56/'Inputs & Drivers'!$F$34 -> 0 | N57: =N56/'Inputs & Drivers'!$F$34 -> 0 | O57: =O56/'Inputs & Drivers'!$F$34 -> 0 | P57: =P56/'Inputs & Drivers'!$F$34 -> 0 | ... EJ57: =EJ56/'Inputs & Drivers'!$F$34 -> 2.0524707 | EM57: =EM56/'Inputs & Drivers'!$F$34 -> 1.4083045 | EN57: =EN56/'Inputs & Drivers'!$F$34 -> 1.4367302 | EO57: =EO56/'Inputs & Drivers'!$F$34 -> 1.6150143 | EP57: =EP56/'Inputs & Drivers'!$F$34 -> 1.6641365 | EQ57: =EQ56/'Inputs & Drivers'!$F$34 -> 1.7147528 | ER57: =ER56/'Inputs & Drivers'!$F$34 -> 1.7669086 | ES57: =ES56/'Inputs & Drivers'!$F$34 -> 1.8206508 | ET57: =ET56/'Inputs & Drivers'!$F$34 -> 1.8760277 | ... EW57: =EW56/'Inputs & Drivers'!$F$34 -> 2.0524707
B58: Physical Occupancy | I58: =IF(I22<$C$6,I22/$C$6,I52/I51+1) -> 0 | J58: =IF(J22<$C$6,J22/$C$6,J52/J51+1) -> 0 | K58: =IF(K22<$C$6,K22/$C$6,K52/K51+1) -> 0 | L58: =IF(L22<$C$6,L22/$C$6,L52/L51+1) -> 0 | M58: =IF(M22<$C$6,M22/$C$6,M52/M51+1) -> 0 | N58: =IF(N22<$C$6,N22/$C$6,N52/N51+1) -> 0 | O58: =IF(O22<$C$6,O22/$C$6,O52/O51+1) -> 0 | P58: =IF(P22<$C$6,P22/$C$6,P52/P51+1) -> 0 | ... EJ58: =IF(EJ22<$C$6,EJ22/$C$6,EJ52/EJ51+1) -> 0.93 | EM58: =IFERROR(EM52/EM51+1,0) -> 0 | EN58: =IFERROR(EN52/EN51+1,0) -> 0.91 | EO58: =IFERROR(EO52/EO51+1,0) -> 0.93 | EP58: =IFERROR(EP52/EP51+1,0) -> 0.93 | EQ58: =IFERROR(EQ52/EQ51+1,0) -> 0.93 | ER58: =IFERROR(ER52/ER51+1,0) -> 0.93 | ES58: =IFERROR(ES52/ES51+1,0) -> 0.93 | ET58: =IFERROR(ET52/ET51+1,0) -> 0.93 | ... EW58: =IFERROR(EW52/EW51+1,0) -> 0.93
B59: Economic Occupancy | I59: =IF(I22<$C$6,I22/$C$6,I55/I51) -> 0 | J59: =IF(J22<$C$6,J22/$C$6,J55/J51) -> 0 | K59: =IF(K22<$C$6,K22/$C$6,K55/K51) -> 0 | L59: =IF(L22<$C$6,L22/$C$6,L55/L51) -> 0 | M59: =IF(M22<$C$6,M22/$C$6,M55/M51) -> 0 | N59: =IF(N22<$C$6,N22/$C$6,N55/N51) -> 0 | O59: =IF(O22<$C$6,O22/$C$6,O55/O51) -> 0 | P59: =IF(P22<$C$6,P22/$C$6,P55/P51) -> 0 | ... EJ59: =IF(EJ22<$C$6,EJ22/$C$6,EJ55/EJ51) -> 0.9175 | EM59: =IFERROR(EM55/EM51,0) -> 0 | EN59: =IFERROR(EN55/EN51,0) -> 0.8975 | EO59: =IFERROR(EO55/EO51,0) -> 0.9175 | EP59: =IFERROR(EP55/EP51,0) -> 0.9175 | EQ59: =IFERROR(EQ55/EQ51,0) -> 0.9175 | ER59: =IFERROR(ER55/ER51,0) -> 0.9175 | ES59: =IFERROR(ES55/ES51,0) -> 0.9175 | ET59: =IFERROR(ET55/ET51,0) -> 0.9175 | ... EW59: =IFERROR(EW55/EW51,0) -> 0.9175
B61: Utility Reimbursement | F61: {=SUMPRODUCT(($H61:$EJ61)*($H$6:$EJ$6<=$C$5))} -> 143387.12 | I61: =I27*I$22 -> 0 | J61: =J27*J$22 -> 0 | K61: =K27*K$22 -> 0 | L61: =L27*L$22 -> 0 | M61: =M27*M$22 -> 0 | N61: =N27*N$22 -> 0 | O61: =O27*O$22 -> 0 | P61: =P27*P$22 -> 0 | ... EJ61: =EJ27*EJ$22 -> 10990.795 | EL61: =SUMIF($H$4:$EJ$4,EL$5,$H61:$EJ61) -> 0 | EM61: =SUMIF($H$4:$EJ$4,EM$5,$H61:$EJ61) -> 0 | EN61: =SUMIF($H$4:$EJ$4,EN$5,$H61:$EJ61) -> 32925.964 | EO61: =SUMIF($H$4:$EJ$4,EO$5,$H61:$EJ61) -> 110461.15 | EP61: =SUMIF($H$4:$EJ$4,EP$5,$H61:$EJ61) -> 113629 | EQ61: =SUMIF($H$4:$EJ$4,EQ$5,$H61:$EJ61) -> 115922.53 | ER61: =SUMIF($H$4:$EJ$4,ER$5,$H61:$EJ61) -> 118262.35 | ES61: =SUMIF($H$4:$EJ$4,ES$5,$H61:$EJ61) -> 120649.4 | ... EW61: =SUMIF($H$4:$EJ$4,EW$5,$H61:$EJ61) -> 130689.23
B62: Parking Revenue | F62: {=SUMPRODUCT(($H62:$EJ62)*($H$6:$EJ$6<=$C$5))} -> 477957.06 | I62: =I28*I$22 -> 0 | J62: =J28*J$22 -> 0 | K62: =K28*K$22 -> 0 | L62: =L28*L$22 -> 0 | M62: =M28*M$22 -> 0 | N62: =N28*N$22 -> 0 | O62: =O28*O$22 -> 0 | P62: =P28*P$22 -> 0 | ... EJ62: =EJ28*EJ$22 -> 36635.983 | EL62: =SUMIF($H$4:$EJ$4,EL$5,$H62:$EJ62) -> 0 | EM62: =SUMIF($H$4:$EJ$4,EM$5,$H62:$EJ62) -> 0 | EN62: =SUMIF($H$4:$EJ$4,EN$5,$H62:$EJ62) -> 109753.21 | EO62: =SUMIF($H$4:$EJ$4,EO$5,$H62:$EJ62) -> 368203.85 | EP62: =SUMIF($H$4:$EJ$4,EP$5,$H62:$EJ62) -> 378763.34 | EQ62: =SUMIF($H$4:$EJ$4,EQ$5,$H62:$EJ62) -> 386408.43 | ER62: =SUMIF($H$4:$EJ$4,ER$5,$H62:$EJ62) -> 394207.84 | ES62: =SUMIF($H$4:$EJ$4,ES$5,$H62:$EJ62) -> 402164.67 | ... EW62: =SUMIF($H$4:$EJ$4,EW$5,$H62:$EJ62) -> 435630.77
B63: Other Revenue | F63: {=SUMPRODUCT(($H63:$EJ63)*($H$6:$EJ$6<=$C$5))} -> 119489.27 | I63: =I29*I$22 -> 0 | J63: =J29*J$22 -> 0 | K63: =K29*K$22 -> 0 | L63: =L29*L$22 -> 0 | M63: =M29*M$22 -> 0 | N63: =N29*N$22 -> 0 | O63: =O29*O$22 -> 0 | P63: =P29*P$22 -> 0 | ... EJ63: =EJ29*EJ$22 -> 9158.9958 | EL63: =SUMIF($H$4:$EJ$4,EL$5,$H63:$EJ63) -> 0 | EM63: =SUMIF($H$4:$EJ$4,EM$5,$H63:$EJ63) -> 0 | EN63: =SUMIF($H$4:$EJ$4,EN$5,$H63:$EJ63) -> 27438.303 | EO63: =SUMIF($H$4:$EJ$4,EO$5,$H63:$EJ63) -> 92050.962 | EP63: =SUMIF($H$4:$EJ$4,EP$5,$H63:$EJ63) -> 94690.835 | EQ63: =SUMIF($H$4:$EJ$4,EQ$5,$H63:$EJ63) -> 96602.108 | ER63: =SUMIF($H$4:$EJ$4,ER$5,$H63:$EJ63) -> 98551.959 | ES63: =SUMIF($H$4:$EJ$4,ES$5,$H63:$EJ63) -> 100541.17 | ... EW63: =SUMIF($H$4:$EJ$4,EW$5,$H63:$EJ63) -> 108907.69
B64: Total Other Revenue | F64: =SUM(F61:F63) -> 740833.44 | I64: =SUM(I61:I63) -> 0 | J64: =SUM(J61:J63) -> 0 | K64: =SUM(K61:K63) -> 0 | L64: =SUM(L61:L63) -> 0 | M64: =SUM(M61:M63) -> 0 | N64: =SUM(N61:N63) -> 0 | O64: =SUM(O61:O63) -> 0 | P64: =SUM(P61:P63) -> 0 | ... EJ64: =SUM(EJ61:EJ63) -> 56785.774 | EL64: =SUM(EL61:EL63) -> 0 | EM64: =SUM(EM61:EM63) -> 0 | EN64: =SUM(EN61:EN63) -> 170117.48 | EO64: =SUM(EO61:EO63) -> 570715.97 | EP64: =SUM(EP61:EP63) -> 587083.18 | EQ64: =SUM(EQ61:EQ63) -> 598933.07 | ER64: =SUM(ER61:ER63) -> 611022.15 | ES64: =SUM(ES61:ES63) -> 623355.24 | ... EW64: =SUM(EW61:EW63) -> 675227.7
B66: TOTAL INCOME | F66: =F55+F64 -> 6863039.2 | I66: =I55+I64 -> 0 | J66: =J55+J64 -> 0 | K66: =K55+K64 -> 0 | L66: =L55+L64 -> 0 | M66: =M55+M64 -> 0 | N66: =N55+N64 -> 0 | O66: =O55+O64 -> 0 | P66: =P55+P64 -> 0 | ... EJ66: =EJ55+EJ64 -> 601013.77 | EL66: =EL55+EL64 -> 0 | EM66: =EM55+EM64 -> 0 | EN66: =EN55+EN64 -> 1506481.7 | EO66: =EO55+EO64 -> 5356557.4 | EP66: =EP55+EP64 -> 5810156.6 | EQ66: =EQ55+EQ64 -> 5980871.3 | ER66: =ER55+ER64 -> 6156657.2 | ES66: =ES55+ES64 -> 6337666.1 | ... EW66: =EW55+EW64 -> 7117130.4
B68: OPERATING EXPENSES
B69: Repairs & Maintenance | F69: {=SUMPRODUCT(($H69:$EJ69)*($H$6:$EJ$6<=$C$5))} -> -239987.25 | I69: =-I32/12*I$22 -> 0 | J69: =-J32/12*J$22 -> 0 | K69: =-K32/12*K$22 -> 0 | L69: =-L32/12*L$22 -> 0 | M69: =-M32/12*M$22 -> 0 | N69: =-N32/12*N$22 -> 0 | O69: =-O32/12*O$22 -> 0 | P69: =-P32/12*P$22 -> 0 | ... EJ69: =-EJ32/12*EJ$22 -> -20039.325 | EL69: =SUMIF($H$4:$EJ$4,EL$5,$H69:$EJ69) -> 0 | EM69: =SUMIF($H$4:$EJ$4,EM$5,$H69:$EJ69) -> 0 | EN69: =SUMIF($H$4:$EJ$4,EN$5,$H69:$EJ69) -> -54876.606 | EO69: =SUMIF($H$4:$EJ$4,EO$5,$H69:$EJ69) -> -185110.65 | EP69: =SUMIF($H$4:$EJ$4,EP$5,$H69:$EJ69) -> -192321.73 | EQ69: =SUMIF($H$4:$EJ$4,EQ$5,$H69:$EJ69) -> -198171.38 | ER69: =SUMIF($H$4:$EJ$4,ER$5,$H69:$EJ69) -> -204198.95 | ES69: =SUMIF($H$4:$EJ$4,ES$5,$H69:$EJ69) -> -210409.86 | ... EW69: =SUMIF($H$4:$EJ$4,EW$5,$H69:$EJ69) -> -237200.93
B70: Turnover | F70: {=SUMPRODUCT(($H70:$EJ70)*($H$6:$EJ$6<=$C$5))} -> -99994.688 | I70: =-I33/12*I$22 -> 0 | J70: =-J33/12*J$22 -> 0 | K70: =-K33/12*K$22 -> 0 | L70: =-L33/12*L$22 -> 0 | M70: =-M33/12*M$22 -> 0 | N70: =-N33/12*N$22 -> 0 | O70: =-O33/12*O$22 -> 0 | P70: =-P33/12*P$22 -> 0 | ... EJ70: =-EJ33/12*EJ$22 -> -8349.7189 | EL70: =SUMIF($H$4:$EJ$4,EL$5,$H70:$EJ70) -> 0 | EM70: =SUMIF($H$4:$EJ$4,EM$5,$H70:$EJ70) -> 0 | EN70: =SUMIF($H$4:$EJ$4,EN$5,$H70:$EJ70) -> -22865.252 | EO70: =SUMIF($H$4:$EJ$4,EO$5,$H70:$EJ70) -> -77129.436 | EP70: =SUMIF($H$4:$EJ$4,EP$5,$H70:$EJ70) -> -80134.053 | EQ70: =SUMIF($H$4:$EJ$4,EQ$5,$H70:$EJ70) -> -82571.407 | ER70: =SUMIF($H$4:$EJ$4,ER$5,$H70:$EJ70) -> -85082.895 | ES70: =SUMIF($H$4:$EJ$4,ES$5,$H70:$EJ70) -> -87670.773 | ... EW70: =SUMIF($H$4:$EJ$4,EW$5,$H70:$EJ70) -> -98833.719
B71: Marketing | F71: {=SUMPRODUCT(($H71:$EJ71)*($H$6:$EJ$6<=$C$5))} -> -59996.813 | I71: =-I34/12*I$22 -> 0 | J71: =-J34/12*J$22 -> 0 | K71: =-K34/12*K$22 -> 0 | L71: =-L34/12*L$22 -> 0 | M71: =-M34/12*M$22 -> 0 | N71: =-N34/12*N$22 -> 0 | O71: =-O34/12*O$22 -> 0 | P71: =-P34/12*P$22 -> 0 | ... EJ71: =-EJ34/12*EJ$22 -> -5009.8314 | EL71: =SUMIF($H$4:$EJ$4,EL$5,$H71:$EJ71) -> 0 | EM71: =SUMIF($H$4:$EJ$4,EM$5,$H71:$EJ71) -> 0 | EN71: =SUMIF($H$4:$EJ$4,EN$5,$H71:$EJ71) -> -13719.151 | EO71: =SUMIF($H$4:$EJ$4,EO$5,$H71:$EJ71) -> -46277.662 | EP71: =SUMIF($H$4:$EJ$4,EP$5,$H71:$EJ71) -> -48080.432 | EQ71: =SUMIF($H$4:$EJ$4,EQ$5,$H71:$EJ71) -> -49542.844 | ER71: =SUMIF($H$4:$EJ$4,ER$5,$H71:$EJ71) -> -51049.737 | ES71: =SUMIF($H$4:$EJ$4,ES$5,$H71:$EJ71) -> -52602.464 | ... EW71: =SUMIF($H$4:$EJ$4,EW$5,$H71:$EJ71) -> -59300.231
B72: General & Administrative | F72: {=SUMPRODUCT(($H72:$EJ72)*($H$6:$EJ$6<=$C$5))} -> -149992.03 | I72: =-I35/12*I$22 -> 0 | J72: =-J35/12*J$22 -> 0 | K72: =-K35/12*K$22 -> 0 | L72: =-L35/12*L$22 -> 0 | M72: =-M35/12*M$22 -> 0 | N72: =-N35/12*N$22 -> 0 | O72: =-O35/12*O$22 -> 0 | P72: =-P35/12*P$22 -> 0 | ... EJ72: =-EJ35/12*EJ$22 -> -12524.578 | EL72: =SUMIF($H$4:$EJ$4,EL$5,$H72:$EJ72) -> 0 | EM72: =SUMIF($H$4:$EJ$4,EM$5,$H72:$EJ72) -> 0 | EN72: =SUMIF($H$4:$EJ$4,EN$5,$H72:$EJ72) -> -34297.879 | EO72: =SUMIF($H$4:$EJ$4,EO$5,$H72:$EJ72) -> -115694.15 | EP72: =SUMIF($H$4:$EJ$4,EP$5,$H72:$EJ72) -> -120201.08 | EQ72: =SUMIF($H$4:$EJ$4,EQ$5,$H72:$EJ72) -> -123857.11 | ER72: =SUMIF($H$4:$EJ$4,ER$5,$H72:$EJ72) -> -127624.34 | ES72: =SUMIF($H$4:$EJ$4,ES$5,$H72:$EJ72) -> -131506.16 | ... EW72: =SUMIF($H$4:$EJ$4,EW$5,$H72:$EJ72) -> -148250.58
B73: Payroll | F73: {=SUMPRODUCT(($H73:$EJ73)*($H$6:$EJ$6<=$C$5))} -> -439976.63 | I73: =-I36/12*I$22 -> 0 | J73: =-J36/12*J$22 -> 0 | K73: =-K36/12*K$22 -> 0 | L73: =-L36/12*L$22 -> 0 | M73: =-M36/12*M$22 -> 0 | N73: =-N36/12*N$22 -> 0 | O73: =-O36/12*O$22 -> 0 | P73: =-P36/12*P$22 -> 0 | ... EJ73: =-EJ36/12*EJ$22 -> -36738.763 | EL73: =SUMIF($H$4:$EJ$4,EL$5,$H73:$EJ73) -> 0 | EM73: =SUMIF($H$4:$EJ$4,EM$5,$H73:$EJ73) -> 0 | EN73: =SUMIF($H$4:$EJ$4,EN$5,$H73:$EJ73) -> -100607.11 | EO73: =SUMIF($H$4:$EJ$4,EO$5,$H73:$EJ73) -> -339369.52 | EP73: =SUMIF($H$4:$EJ$4,EP$5,$H73:$EJ73) -> -352589.83 | EQ73: =SUMIF($H$4:$EJ$4,EQ$5,$H73:$EJ73) -> -363314.19 | ER73: =SUMIF($H$4:$EJ$4,ER$5,$H73:$EJ73) -> -374364.74 | ES73: =SUMIF($H$4:$EJ$4,ES$5,$H73:$EJ73) -> -385751.4 | ... EW73: =SUMIF($H$4:$EJ$4,EW$5,$H73:$EJ73) -> -434868.36
B74: Management Fees | F74: {=SUMPRODUCT(($H74:$EJ74)*($H$6:$EJ$6<=$C$5))} -> -183666.17 | I74: =-'Inputs & Drivers'!$H$54*Model!I55 -> 0 | J74: =-'Inputs & Drivers'!$H$54*Model!J55 -> 0 | K74: =-'Inputs & Drivers'!$H$54*Model!K55 -> 0 | L74: =-'Inputs & Drivers'!$H$54*Model!L55 -> 0 | M74: =-'Inputs & Drivers'!$H$54*Model!M55 -> 0 | N74: =-'Inputs & Drivers'!$H$54*Model!N55 -> 0 | O74: =-'Inputs & Drivers'!$H$54*Model!O55 -> 0 | P74: =-'Inputs & Drivers'!$H$54*Model!P55 -> 0 | ... EJ74: =-'Inputs & Drivers'!$H$54*Model!EJ55 -> -16326.84 | EL74: =SUMIF($H$4:$EJ$4,EL$5,$H74:$EJ74) -> 0 | EM74: =SUMIF($H$4:$EJ$4,EM$5,$H74:$EJ74) -> 0 | EN74: =SUMIF($H$4:$EJ$4,EN$5,$H74:$EJ74) -> -40090.928 | EO74: =SUMIF($H$4:$EJ$4,EO$5,$H74:$EJ74) -> -143575.24 | EP74: =SUMIF($H$4:$EJ$4,EP$5,$H74:$EJ74) -> -156692.2 | EQ74: =SUMIF($H$4:$EJ$4,EQ$5,$H74:$EJ74) -> -161458.15 | ER74: =SUMIF($H$4:$EJ$4,ER$5,$H74:$EJ74) -> -166369.05 | ES74: =SUMIF($H$4:$EJ$4,ES$5,$H74:$EJ74) -> -171429.33 | ... EW74: =SUMIF($H$4:$EJ$4,EW$5,$H74:$EJ74) -> -193257.08
B75: Utilities | F75: {=SUMPRODUCT(($H75:$EJ75)*($H$6:$EJ$6<=$C$5))} -> -69996.282 | I75: =-I38/12*I$22 -> 0 | J75: =-J38/12*J$22 -> 0 | K75: =-K38/12*K$22 -> 0 | L75: =-L38/12*L$22 -> 0 | M75: =-M38/12*M$22 -> 0 | N75: =-N38/12*N$22 -> 0 | O75: =-O38/12*O$22 -> 0 | P75: =-P38/12*P$22 -> 0 | ... EJ75: =-EJ38/12*EJ$22 -> -5844.8032 | EL75: =SUMIF($H$4:$EJ$4,EL$5,$H75:$EJ75) -> 0 | EM75: =SUMIF($H$4:$EJ$4,EM$5,$H75:$EJ75) -> 0 | EN75: =SUMIF($H$4:$EJ$4,EN$5,$H75:$EJ75) -> -16005.677 | EO75: =SUMIF($H$4:$EJ$4,EO$5,$H75:$EJ75) -> -53990.605 | EP75: =SUMIF($H$4:$EJ$4,EP$5,$H75:$EJ75) -> -56093.837 | EQ75: =SUMIF($H$4:$EJ$4,EQ$5,$H75:$EJ75) -> -57799.985 | ER75: =SUMIF($H$4:$EJ$4,ER$5,$H75:$EJ75) -> -59558.027 | ES75: =SUMIF($H$4:$EJ$4,ES$5,$H75:$EJ75) -> -61369.541 | ... EW75: =SUMIF($H$4:$EJ$4,EW$5,$H75:$EJ75) -> -69183.603
B76: Real Estate Taxes | F76: {=SUMPRODUCT(($H76:$EJ76)*($H$6:$EJ$6<=$C$5))} -> -1109861.6 | I76: =-I39/12*$C$6*(I$5>'Inputs & Drivers'!$F$41) -> 0 | J76: =-J39/12*$C$6*(J$5>'Inputs & Drivers'!$F$41) -> 0 | K76: =-K39/12*$C$6*(K$5>'Inputs & Drivers'!$F$41) -> 0 | L76: =-L39/12*$C$6*(L$5>'Inputs & Drivers'!$F$41) -> 0 | M76: =-M39/12*$C$6*(M$5>'Inputs & Drivers'!$F$41) -> 0 | N76: =-N39/12*$C$6*(N$5>'Inputs & Drivers'!$F$41) -> 0 | O76: =-O39/12*$C$6*(O$5>'Inputs & Drivers'!$F$41) -> 0 | P76: =-P39/12*$C$6*(P$5>'Inputs & Drivers'!$F$41) -> 0 | ... EJ76: =-EJ39/12*$C$6*(EJ$5>'Inputs & Drivers'!$F$41) -> -66148.303 | EL76: =SUMIF($H$4:$EJ$4,EL$5,$H76:$EJ76) -> 0 | EM76: =SUMIF($H$4:$EJ$4,EM$5,$H76:$EJ76) -> 0 | EN76: =SUMIF($H$4:$EJ$4,EN$5,$H76:$EJ76) -> -439513.93 | EO76: =SUMIF($H$4:$EJ$4,EO$5,$H76:$EJ76) -> -670347.71 | EP76: =SUMIF($H$4:$EJ$4,EP$5,$H76:$EJ76) -> -683878.25 | EQ76: =SUMIF($H$4:$EJ$4,EQ$5,$H76:$EJ76) -> -697681.89 | ER76: =SUMIF($H$4:$EJ$4,ER$5,$H76:$EJ76) -> -711764.15 | ES76: =SUMIF($H$4:$EJ$4,ES$5,$H76:$EJ76) -> -726130.65 | ... EW76: =SUMIF($H$4:$EJ$4,EW$5,$H76:$EJ76) -> -786555.56
B77: Property Insurance | F77: {=SUMPRODUCT(($H77:$EJ77)*($H$6:$EJ$6<=$C$5))} -> -141329.97 | I77: =-I40/12*$C$6*(I$5>'Inputs & Drivers'!$F$41) -> 0 | J77: =-J40/12*$C$6*(J$5>'Inputs & Drivers'!$F$41) -> 0 | K77: =-K40/12*$C$6*(K$5>'Inputs & Drivers'!$F$41) -> 0 | L77: =-L40/12*$C$6*(L$5>'Inputs & Drivers'!$F$41) -> 0 | M77: =-M40/12*$C$6*(M$5>'Inputs & Drivers'!$F$41) -> 0 | N77: =-N40/12*$C$6*(N$5>'Inputs & Drivers'!$F$41) -> 0 | O77: =-O40/12*$C$6*(O$5>'Inputs & Drivers'!$F$41) -> 0 | P77: =-P40/12*$C$6*(P$5>'Inputs & Drivers'!$F$41) -> 0 | ... EJ77: =-EJ40/12*$C$6*(EJ$5>'Inputs & Drivers'!$F$41) -> -9184.6908 | EL77: =SUMIF($H$4:$EJ$4,EL$5,$H77:$EJ77) -> 0 | EM77: =SUMIF($H$4:$EJ$4,EM$5,$H77:$EJ77) -> 0 | EN77: =SUMIF($H$4:$EJ$4,EN$5,$H77:$EJ77) -> -55784.46 | EO77: =SUMIF($H$4:$EJ$4,EO$5,$H77:$EJ77) -> -85545.51 | EP77: =SUMIF($H$4:$EJ$4,EP$5,$H77:$EJ77) -> -88147.458 | EQ77: =SUMIF($H$4:$EJ$4,EQ$5,$H77:$EJ77) -> -90828.548 | ER77: =SUMIF($H$4:$EJ$4,ER$5,$H77:$EJ77) -> -93591.185 | ES77: =SUMIF($H$4:$EJ$4,ES$5,$H77:$EJ77) -> -96437.85 | ... EW77: =SUMIF($H$4:$EJ$4,EW$5,$H77:$EJ77) -> -108717.09
B78: TOTAL OPERATING EXPENSES | F78: =SUM(F69:F77) -> -2494801.5 | I78: =SUM(I69:I77) -> 0 | J78: =SUM(J69:J77) -> 0 | K78: =SUM(K69:K77) -> 0 | L78: =SUM(L69:L77) -> 0 | M78: =SUM(M69:M77) -> 0 | N78: =SUM(N69:N77) -> 0 | O78: =SUM(O69:O77) -> 0 | P78: =SUM(P69:P77) -> 0 | ... EJ78: =SUM(EJ69:EJ77) -> -180166.85 | EL78: =SUM(EL69:EL77) -> 0 | EM78: =SUM(EM69:EM77) -> 0 | EN78: =SUM(EN69:EN77) -> -777760.99 | EO78: =SUM(EO69:EO77) -> -1717040.5 | EP78: =SUM(EP69:EP77) -> -1778138.9 | EQ78: =SUM(EQ69:EQ77) -> -1825225.5 | ER78: =SUM(ER69:ER77) -> -1873603.1 | ES78: =SUM(ES69:ES77) -> -1923308 | ... EW78: =SUM(EW69:EW77) -> -2136167.2
B80: NET OPERATING INCOME | F80: =F66+F78 -> 4368237.7 | I80: =I66+I78 -> 0 | J80: =J66+J78 -> 0 | K80: =K66+K78 -> 0 | L80: =L66+L78 -> 0 | M80: =M66+M78 -> 0 | N80: =N66+N78 -> 0 | O80: =O66+O78 -> 0 | P80: =P66+P78 -> 0 | ... EJ80: =EJ66+EJ78 -> 420846.92 | EL80: =EL66+EL78 -> 0 | EM80: =EM66+EM78 -> 0 | EN80: =EN66+EN78 -> 728720.74 | EO80: =EO66+EO78 -> 3639516.9 | EP80: =EP66+EP78 -> 4032017.8 | EQ80: =EQ66+EQ78 -> 4155645.8 | ER80: =ER66+ER78 -> 4283054.1 | ES80: =ES66+ES78 -> 4414358.1 | ... EW80: =EW66+EW78 -> 4980963.3
B81: Forward 12 Month NOI | I81: =SUM(J80:U80) -> 0 | J81: =SUM(K80:V80) -> 0 | K81: =SUM(L80:W80) -> 0 | L81: =SUM(M80:X80) -> 0 | M81: =SUM(N80:Y80) -> -27814.901 | N81: =SUM(O80:Z80) -> -21882.786 | O81: =SUM(P80:AA80) -> 17908.912 | P81: =SUM(Q80:AB80) -> 91673.042 | ... DX81: =SUM(DY80:EJ80) -> 4980963.3
B82: Margin | I82: =IFERROR(I80/I66,0) -> 0 | J82: =IFERROR(J80/J66,0) -> 0 | K82: =IFERROR(K80/K66,0) -> 0 | L82: =IFERROR(L80/L66,0) -> 0 | M82: =IFERROR(M80/M66,0) -> 0 | N82: =IFERROR(N80/N66,0) -> 0 | O82: =IFERROR(O80/O66,0) -> 0 | P82: =IFERROR(P80/P66,0) -> 0 | ... EJ82: =IFERROR(EJ80/EJ66,0) -> 0.70022841 | EM82: =IFERROR(EM80/EM66,0) -> 0 | EN82: =IFERROR(EN80/EN66,0) -> 0.48372358 | EO82: =IFERROR(EO80/EO66,0) -> 0.67945075 | EP82: =IFERROR(EP80/EP66,0) -> 0.69396025 | EQ82: =IFERROR(EQ80/EQ66,0) -> 0.69482281 | ER82: =IFERROR(ER80/ER66,0) -> 0.69567851 | ES82: =IFERROR(ES80/ES66,0) -> 0.6965274 | ET82: =IFERROR(ET80/ET66,0) -> 0.6973695 | ... EW82: =IFERROR(EW80/EW66,0) -> 0.69985556
B83: Yield-on-Cost | I83: =I80*12/I175 -> 0 | J83: =J80*12/J175 -> 0 | K83: =K80*12/K175 -> 0 | L83: =L80*12/L175 -> 0 | M83: =M80*12/M175 -> 0 | N83: =N80*12/N175 -> 0 | O83: =O80*12/O175 -> 0 | P83: =P80*12/P175 -> 0 | ... EJ83: =EJ80*12/EJ175 -> 0.085856901 | EM83: =EM80/EM175 -> 0 | EN83: =EN80/EN175 -> 0.012398334 | EO83: =EO80/EO175 -> 0.061874764 | EP83: =EP80/EP175 -> 0.068547599 | EQ83: =EQ80/EQ175 -> 0.070649377 | ER83: =ER80/ER175 -> 0.072815422 | ES83: =ES80/ES175 -> 0.075047697 | ET83: =ET80/ET175 -> 0.077348222 | ... EW83: =EW80/EW175 -> 0.084680449
B85: CAPITAL EXPENDITURES
B86: Capital Reserves | F86: {=SUMPRODUCT(($H86:$EJ86)*($H$6:$EJ$6<=$C$5))} -> -75000 | I86: =-I41/12*$C$6*(Model!I$5>'Inputs & Drivers'!$F$41)*(I$6<=Model!$C$5) -> 0 | J86: =-J41/12*$C$6*(Model!J$5>'Inputs & Drivers'!$F$41)*(J$6<=Model!$C$5) -> 0 | K86: =-K41/12*$C$6*(Model!K$5>'Inputs & Drivers'!$F$41)*(K$6<=Model!$C$5) -> 0 | L86: =-L41/12*$C$6*(Model!L$5>'Inputs & Drivers'!$F$41)*(L$6<=Model!$C$5) -> 0 | M86: =-M41/12*$C$6*(Model!M$5>'Inputs & Drivers'!$F$41)*(M$6<=Model!$C$5) -> 0 | N86: =-N41/12*$C$6*(Model!N$5>'Inputs & Drivers'!$F$41)*(N$6<=Model!$C$5) -> 0 | O86: =-O41/12*$C$6*(Model!O$5>'Inputs & Drivers'!$F$41)*(O$6<=Model!$C$5) -> 0 | P86: =-P41/12*$C$6*(Model!P$5>'Inputs & Drivers'!$F$41)*(P$6<=Model!$C$5) -> 0 | ... EJ86: =-EJ41/12*$C$6*(Model!EJ$5>'Inputs & Drivers'!$F$41)*(EJ$6<=Model!$C$5) -> 0 | EL86: =SUMIF($H$4:$EJ$4,EL$5,$H86:$EJ86) -> 0 | EM86: =SUMIF($H$4:$EJ$4,EM$5,$H86:$EJ86) -> 0 | EN86: =SUMIF($H$4:$EJ$4,EN$5,$H86:$EJ86) -> -30000 | EO86: =SUMIF($H$4:$EJ$4,EO$5,$H86:$EJ86) -> -45000 | EP86: =SUMIF($H$4:$EJ$4,EP$5,$H86:$EJ86) -> 0 | EQ86: =SUMIF($H$4:$EJ$4,EQ$5,$H86:$EJ86) -> 0 | ER86: =SUMIF($H$4:$EJ$4,ER$5,$H86:$EJ86) -> 0 | ES86: =SUMIF($H$4:$EJ$4,ES$5,$H86:$EJ86) -> 0 | ... EW86: =SUMIF($H$4:$EJ$4,EW$5,$H86:$EJ86) -> 0
B87: TOTAL CAPITAL EXPENDITURES | F87: =SUM(F86:F86) -> -75000 | I87: =SUM(I86:I86) -> 0 | J87: =SUM(J86:J86) -> 0 | K87: =SUM(K86:K86) -> 0 | L87: =SUM(L86:L86) -> 0 | M87: =SUM(M86:M86) -> 0 | N87: =SUM(N86:N86) -> 0 | O87: =SUM(O86:O86) -> 0 | P87: =SUM(P86:P86) -> 0 | ... EJ87: =SUM(EJ86:EJ86) -> 0 | EL87: =SUM(EL86:EL86) -> 0 | EM87: =SUM(EM86:EM86) -> 0 | EN87: =SUM(EN86:EN86) -> -30000 | EO87: =SUM(EO86:EO86) -> -45000 | EP87: =SUM(EP86:EP86) -> 0 | EQ87: =SUM(EQ86:EQ86) -> 0 | ER87: =SUM(ER86:ER86) -> 0 | ES87: =SUM(ES86:ES86) -> 0 | ... EW87: =SUM(EW86:EW86) -> 0
B89: DEVELOPMENT & SALE
B90: Acquisition Costs | F90: {=SUMPRODUCT(($H90:$EJ90)*($H$6:$EJ$6<=$C$5))} -> -5700000 | H90: =-'Development Budget'!$E$9*H14 -> -5700000 | I90: =-'Development Budget'!$E$9*I14 -> 0 | J90: =-'Development Budget'!$E$9*J14 -> 0 | K90: =-'Development Budget'!$E$9*K14 -> 0 | L90: =-'Development Budget'!$E$9*L14 -> 0 | M90: =-'Development Budget'!$E$9*M14 -> 0 | N90: =-'Development Budget'!$E$9*N14 -> 0 | O90: =-'Development Budget'!$E$9*O14 -> 0 | ... EJ90: =-'Development Budget'!$E$9*EJ14 -> 0 | EL90: =SUMIF($H$4:$EJ$4,EL$5,$H90:$EJ90) -> -5700000 | EM90: =SUMIF($H$4:$EJ$4,EM$5,$H90:$EJ90) -> 0 | EN90: =SUMIF($H$4:$EJ$4,EN$5,$H90:$EJ90) -> 0 | EO90: =SUMIF($H$4:$EJ$4,EO$5,$H90:$EJ90) -> 0 | EP90: =SUMIF($H$4:$EJ$4,EP$5,$H90:$EJ90) -> 0 | EQ90: =SUMIF($H$4:$EJ$4,EQ$5,$H90:$EJ90) -> 0 | ER90: =SUMIF($H$4:$EJ$4,ER$5,$H90:$EJ90) -> 0 | ES90: =SUMIF($H$4:$EJ$4,ES$5,$H90:$EJ90) -> 0 | ... EW90: =SUMIF($H$4:$EJ$4,EW$5,$H90:$EJ90) -> 0
B91: Soft Costs | F91: {=SUMPRODUCT(($H91:$EJ91)*($H$6:$EJ$6<=$C$5))} -> -5460000 | H91: =-'Development Budget'!$E$15*H15 -> 0 | I91: =-'Development Budget'!$E$15*I15 -> 0 | J91: =-'Development Budget'!$E$15*J15 -> 0 | K91: =-'Development Budget'!$E$15*K15 -> -273000 | L91: =-'Development Budget'!$E$15*L15 -> -273000 | M91: =-'Development Budget'!$E$15*M15 -> -273000 | N91: =-'Development Budget'!$E$15*N15 -> -273000 | O91: =-'Development Budget'!$E$15*O15 -> -273000 | ... EJ91: =-'Development Budget'!$E$15*EJ15 -> 0 | EL91: =SUMIF($H$4:$EJ$4,EL$5,$H91:$EJ91) -> 0 | EM91: =SUMIF($H$4:$EJ$4,EM$5,$H91:$EJ91) -> -2730000 | EN91: =SUMIF($H$4:$EJ$4,EN$5,$H91:$EJ91) -> -2730000 | EO91: =SUMIF($H$4:$EJ$4,EO$5,$H91:$EJ91) -> 0 | EP91: =SUMIF($H$4:$EJ$4,EP$5,$H91:$EJ91) -> 0 | EQ91: =SUMIF($H$4:$EJ$4,EQ$5,$H91:$EJ91) -> 0 | ER91: =SUMIF($H$4:$EJ$4,ER$5,$H91:$EJ91) -> 0 | ES91: =SUMIF($H$4:$EJ$4,ES$5,$H91:$EJ91) -> 0 | ... EW91: =SUMIF($H$4:$EJ$4,EW$5,$H91:$EJ91) -> 0
B92: Hard Costs | F92: {=SUMPRODUCT(($H92:$EJ92)*($H$6:$EJ$6<=$C$5))} -> -44500000 | H92: =-'Development Budget'!$E$21*H16 -> 0 | I92: =-'Development Budget'!$E$21*I16 -> 0 | J92: =-'Development Budget'!$E$21*J16 -> 0 | K92: =-'Development Budget'!$E$21*K16 -> 0 | L92: =-'Development Budget'!$E$21*L16 -> 0 | M92: =-'Development Budget'!$E$21*M16 -> 0 | N92: =-'Development Budget'!$E$21*N16 -> 0 | O92: =-'Development Budget'!$E$21*O16 -> -2781250 | ... EJ92: =-'Development Budget'!$E$21*EJ16 -> 0 | EL92: =SUMIF($H$4:$EJ$4,EL$5,$H92:$EJ92) -> 0 | EM92: =SUMIF($H$4:$EJ$4,EM$5,$H92:$EJ92) -> -16687500 | EN92: =SUMIF($H$4:$EJ$4,EN$5,$H92:$EJ92) -> -27812500 | EO92: =SUMIF($H$4:$EJ$4,EO$5,$H92:$EJ92) -> 0 | EP92: =SUMIF($H$4:$EJ$4,EP$5,$H92:$EJ92) -> 0 | EQ92: =SUMIF($H$4:$EJ$4,EQ$5,$H92:$EJ92) -> 0 | ER92: =SUMIF($H$4:$EJ$4,ER$5,$H92:$EJ92) -> 0 | ES92: =SUMIF($H$4:$EJ$4,ES$5,$H92:$EJ92) -> 0 | ... EW92: =SUMIF($H$4:$EJ$4,EW$5,$H92:$EJ92) -> 0
B93: Other Development Costs | F93: {=SUMPRODUCT(($H93:$EJ93)*($H$6:$EJ$6<=$C$5))} -> -1750000 | H93: =-'Development Budget'!$E$25*H17 -> 0 | I93: =-'Development Budget'!$E$25*I17 -> 0 | J93: =-'Development Budget'!$E$25*J17 -> 0 | K93: =-'Development Budget'!$E$25*K17 -> -87500 | L93: =-'Development Budget'!$E$25*L17 -> -87500 | M93: =-'Development Budget'!$E$25*M17 -> -87500 | N93: =-'Development Budget'!$E$25*N17 -> -87500 | O93: =-'Development Budget'!$E$25*O17 -> -87500 | ... EJ93: =-'Development Budget'!$E$25*EJ17 -> 0 | EL93: =SUMIF($H$4:$EJ$4,EL$5,$H93:$EJ93) -> 0 | EM93: =SUMIF($H$4:$EJ$4,EM$5,$H93:$EJ93) -> -875000 | EN93: =SUMIF($H$4:$EJ$4,EN$5,$H93:$EJ93) -> -875000 | EO93: =SUMIF($H$4:$EJ$4,EO$5,$H93:$EJ93) -> 0 | EP93: =SUMIF($H$4:$EJ$4,EP$5,$H93:$EJ93) -> 0 | EQ93: =SUMIF($H$4:$EJ$4,EQ$5,$H93:$EJ93) -> 0 | ER93: =SUMIF($H$4:$EJ$4,ER$5,$H93:$EJ93) -> 0 | ES93: =SUMIF($H$4:$EJ$4,ES$5,$H93:$EJ93) -> 0 | ... EW93: =SUMIF($H$4:$EJ$4,EW$5,$H93:$EJ93) -> 0
B94: Sale Proceeds | F94: {=SUMPRODUCT(($H94:$EJ94)*($H$6:$EJ$6<=$C$5))} -> 73309414 | H94: =H$81/'Inputs & Drivers'!$E$16*(H$6=$C$5) -> 0 | I94: =I$81/'Inputs & Drivers'!$E$16*(I$6=$C$5) -> 0 | J94: =J$81/'Inputs & Drivers'!$E$16*(J$6=$C$5) -> 0 | K94: =K$81/'Inputs & Drivers'!$E$16*(K$6=$C$5) -> 0 | L94: =L$81/'Inputs & Drivers'!$E$16*(L$6=$C$5) -> 0 | M94: =M$81/'Inputs & Drivers'!$E$16*(M$6=$C$5) -> 0 | N94: =N$81/'Inputs & Drivers'!$E$16*(N$6=$C$5) -> 0 | O94: =O$81/'Inputs & Drivers'!$E$16*(O$6=$C$5) -> 0 | ... EJ94: =EJ$81/'Inputs & Drivers'!$E$16*(EJ$6=$C$5) -> 0 | EL94: =SUMIF($H$4:$EJ$4,EL$5,$H94:$EJ94) -> 0 | EM94: =SUMIF($H$4:$EJ$4,EM$5,$H94:$EJ94) -> 0 | EN94: =SUMIF($H$4:$EJ$4,EN$5,$H94:$EJ94) -> 0 | EO94: =SUMIF($H$4:$EJ$4,EO$5,$H94:$EJ94) -> 73309414 | EP94: =SUMIF($H$4:$EJ$4,EP$5,$H94:$EJ94) -> 0 | EQ94: =SUMIF($H$4:$EJ$4,EQ$5,$H94:$EJ94) -> 0 | ER94: =SUMIF($H$4:$EJ$4,ER$5,$H94:$EJ94) -> 0 | ES94: =SUMIF($H$4:$EJ$4,ES$5,$H94:$EJ94) -> 0 | ... EW94: =SUMIF($H$4:$EJ$4,EW$5,$H94:$EJ94) -> 0
B95: Exit Closing Costs | F95: {=SUMPRODUCT(($H95:$EJ95)*($H$6:$EJ$6<=$C$5))} -> -733094.14 | H95: =-'Inputs & Drivers'!$E$15*Model!H94 -> 0 | I95: =-'Inputs & Drivers'!$E$15*Model!I94 -> 0 | J95: =-'Inputs & Drivers'!$E$15*Model!J94 -> 0 | K95: =-'Inputs & Drivers'!$E$15*Model!K94 -> 0 | L95: =-'Inputs & Drivers'!$E$15*Model!L94 -> 0 | M95: =-'Inputs & Drivers'!$E$15*Model!M94 -> 0 | N95: =-'Inputs & Drivers'!$E$15*Model!N94 -> 0 | O95: =-'Inputs & Drivers'!$E$15*Model!O94 -> 0 | ... EJ95: =-'Inputs & Drivers'!$E$15*Model!EJ94 -> 0 | EL95: =SUMIF($H$4:$EJ$4,EL$5,$H95:$EJ95) -> 0 | EM95: =SUMIF($H$4:$EJ$4,EM$5,$H95:$EJ95) -> 0 | EN95: =SUMIF($H$4:$EJ$4,EN$5,$H95:$EJ95) -> 0 | EO95: =SUMIF($H$4:$EJ$4,EO$5,$H95:$EJ95) -> -733094.14 | EP95: =SUMIF($H$4:$EJ$4,EP$5,$H95:$EJ95) -> 0 | EQ95: =SUMIF($H$4:$EJ$4,EQ$5,$H95:$EJ95) -> 0 | ER95: =SUMIF($H$4:$EJ$4,ER$5,$H95:$EJ95) -> 0 | ES95: =SUMIF($H$4:$EJ$4,ES$5,$H95:$EJ95) -> 0 | ... EW95: =SUMIF($H$4:$EJ$4,EW$5,$H95:$EJ95) -> 0
B96: TOTAL DEVELOPMENT & SALE | F96: =SUM(F90:F95) -> 15166320 | H96: =SUM(H90:H95) -> -5700000 | I96: =SUM(I90:I95) -> 0 | J96: =SUM(J90:J95) -> 0 | K96: =SUM(K90:K95) -> -360500 | L96: =SUM(L90:L95) -> -360500 | M96: =SUM(M90:M95) -> -360500 | N96: =SUM(N90:N95) -> -360500 | O96: =SUM(O90:O95) -> -3141750 | ... EJ96: =SUM(EJ90:EJ95) -> 0 | EL96: =SUM(EL90:EL95) -> -5700000 | EM96: =SUM(EM90:EM95) -> -20292500 | EN96: =SUM(EN90:EN95) -> -31417500 | EO96: =SUM(EO90:EO95) -> 72576320 | EP96: =SUM(EP90:EP95) -> 0 | EQ96: =SUM(EQ90:EQ95) -> 0 | ER96: =SUM(ER90:ER95) -> 0 | ES96: =SUM(ES90:ES95) -> 0 | ... EW96: =SUM(EW90:EW95) -> 0
B98: UNLEVERED CASH FLOW | F98: =F80+F87+F96 -> 19459558 | H98: =(H80+H87+H96)*(H$6<=$C$5) -> -5700000 | I98: =(I80+I87+I96)*(I$6<=$C$5) -> 0 | J98: =(J80+J87+J96)*(J$6<=$C$5) -> 0 | K98: =(K80+K87+K96)*(K$6<=$C$5) -> -360500 | L98: =(L80+L87+L96)*(L$6<=$C$5) -> -360500 | M98: =(M80+M87+M96)*(M$6<=$C$5) -> -360500 | N98: =(N80+N87+N96)*(N$6<=$C$5) -> -360500 | O98: =(O80+O87+O96)*(O$6<=$C$5) -> -3141750 | ... EJ98: =(EJ80+EJ87+EJ96)*(EJ$6<=$C$5) -> 0 | EL98: =(EL80+EL87+EL96)*(EL$6<=$C$5) -> -5700000 | EM98: =(EM80+EM87+EM96)*(EM$6<=$C$5) -> -20292500 | EN98: =(EN80+EN87+EN96)*(EN$6<=$C$5) -> -30718779 | EO98: =(EO80+EO87+EO96)*(EO$6<=$C$5) -> 76170837 | EP98: =(EP80+EP87+EP96)*(EP$6<=$C$5) -> 0 | EQ98: =(EQ80+EQ87+EQ96)*(EQ$6<=$C$5) -> 0 | ER98: =(ER80+ER87+ER96)*(ER$6<=$C$5) -> 0 | ES98: =(ES80+ES87+ES96)*(ES$6<=$C$5) -> 0 | ... EW98: =(EW80+EW87+EW96)*(EW$6<=$C$5) -> 0
B100: Peak Equity | C100: =-SUMIF(H98:EJ98,"<0") -> 57090929
B101: IRR | C101: =XIRR(H98:EJ98,$H$6:$EJ$6) -> 0.16394511
B102: Profit | C102: =SUM(H98:EJ98) -> 19459558
B103: Multiple | C103: =SUMIF(H98:EJ98,">"&0)/C100 -> 1.340852
B106: FUNDING TIMELINE
B108: Unlevered Development Costs | H108: =SUM(H90:H93) -> -5700000 | I108: =SUM(I90:I93) -> 0 | J108: =SUM(J90:J93) -> 0 | K108: =SUM(K90:K93) -> -360500 | L108: =SUM(L90:L93) -> -360500 | M108: =SUM(M90:M93) -> -360500 | N108: =SUM(N90:N93) -> -360500 | O108: =SUM(O90:O93) -> -3141750 | ... EJ108: =SUM(EJ90:EJ93) -> 0
B109: Financing Fees | H109: =H150 -> -400000 | I109: =I150 -> 0 | J109: =J150 -> 0 | K109: =K150 -> 0 | L109: =L150 -> 0 | M109: =M150 -> 0 | N109: =N150 -> 0 | O109: =O150 -> 0 | ... EJ109: =EJ150 -> 0
B110: Interest Reserve Draw | H110: =H131 -> 0 | I110: =I131 -> 0 | J110: =J131 -> 0 | K110: =K131 -> 0 | L110: =L131 -> 0 | M110: =M131 -> 0 | N110: =N131 -> 0 | O110: =O131 -> 0 | ... EJ110: =EJ131 -> 0
B111: Operating Reserve Draw | H111: =H139 -> 0 | I111: =I139 -> 0 | J111: =J139 -> 0 | K111: =K139 -> 0 | L111: =L139 -> 0 | M111: =M139 -> 0 | N111: =N139 -> 0 | O111: =O139 -> 0 | ... EJ111: =EJ139 -> 0
B112: Total Development Costs | H112: =SUM(H108:H111) -> -6100000 | I112: =SUM(I108:I111) -> 0 | J112: =SUM(J108:J111) -> 0 | K112: =SUM(K108:K111) -> -360500 | L112: =SUM(L108:L111) -> -360500 | M112: =SUM(M108:M111) -> -360500 | N112: =SUM(N108:N111) -> -360500 | O112: =SUM(O108:O111) -> -3141750 | ... EJ112: =SUM(EJ108:EJ111) -> 0
B114: Equity
B115: Beginning Blance | H115: ='Development Budget'!F46 -> 18745700 | I115: =H117 -> 12645700 | J115: =I117 -> 12645700 | K115: =J117 -> 12645700 | L115: =K117 -> 12285200 | M115: =L117 -> 11924700 | N115: =M117 -> 11564200 | O115: =N117 -> 11203700 | P115: =O117 -> 8061950 | ... EJ115: =EI117 -> 0
B116: Draw | H116: =-MIN(H115,-H112) -> -6100000 | I116: =-MIN(I115,-I112) -> 0 | J116: =-MIN(J115,-J112) -> 0 | K116: =-MIN(K115,-K112) -> -360500 | L116: =-MIN(L115,-L112) -> -360500 | M116: =-MIN(M115,-M112) -> -360500 | N116: =-MIN(N115,-N112) -> -360500 | O116: =-MIN(O115,-O112) -> -3141750 | ... EJ116: =-MIN(EJ115,-EJ112) -> 0
B117: Ending Balance | H117: =SUM(H115:H116) -> 12645700 | I117: =SUM(I115:I116) -> 12645700 | J117: =SUM(J115:J116) -> 12645700 | K117: =SUM(K115:K116) -> 12285200 | L117: =SUM(L115:L116) -> 11924700 | M117: =SUM(M115:M116) -> 11564200 | N117: =SUM(N115:N116) -> 11203700 | O117: =SUM(O115:O116) -> 8061950 | ... EJ117: =SUM(EJ115:EJ116) -> 0
B119: Debt
B120: Beginning Blance | H120: ='Development Budget'!F47 -> 40000000 | I120: =H122 -> 40000000 | J120: =I122 -> 40000000 | K120: =J122 -> 40000000 | L120: =K122 -> 40000000 | M120: =L122 -> 40000000 | N120: =M122 -> 40000000 | O120: =N122 -> 40000000 | P120: =O122 -> 40000000 | ... EJ120: =EI122 -> 0
B121: Draw | H121: =-MIN(H120,-(H112-H116)) -> 0 | I121: =-MIN(I120,-(I112-I116)) -> 0 | J121: =-MIN(J120,-(J112-J116)) -> 0 | K121: =-MIN(K120,-(K112-K116)) -> 0 | L121: =-MIN(L120,-(L112-L116)) -> 0 | M121: =-MIN(M120,-(M112-M116)) -> 0 | N121: =-MIN(N120,-(N112-N116)) -> 0 | O121: =-MIN(O120,-(O112-O116)) -> 0 | ... EJ121: =-MIN(EJ120,-(EJ112-EJ116)) -> 0
B122: Ending Balance | H122: =SUM(H120:H121) -> 40000000 | I122: =SUM(I120:I121) -> 40000000 | J122: =SUM(J120:J121) -> 40000000 | K122: =SUM(K120:K121) -> 40000000 | L122: =SUM(L120:L121) -> 40000000 | M122: =SUM(M120:M121) -> 40000000 | N122: =SUM(N120:N121) -> 40000000 | O122: =SUM(O120:O121) -> 40000000 | ... EJ122: =SUM(EJ120:EJ121) -> 0
B124: RESERVES
...

Sheet Development Budget
B2: Development Budget
D4: % Total | E4: Total Cost | F4: $ / Unit
B6: Land Purchase Price | D6: =E6/$E$34 -> 0.085112612 | E6: 5000000 | F6: =E6/'Inputs & Drivers'!$E$8 -> 16666.667
B7: Land Mark-up | D7: =E7/$E$34 -> 0 | E7: 0 | F7: =E7/'Inputs & Drivers'!$E$8 -> 0
B8: Closing Costs | D8: =E8/$E$34 -> 0.011915766 | E8: 700000 | F8: =E8/'Inputs & Drivers'!$E$8 -> 2333.3333
B9: Acquisition Costs | D9: =SUM(D6:D8) -> 0.097028378 | E9: =SUM(E6:E8) -> 5700000 | F9: =SUM(F6:F8) -> 19000
B11: Permitting Fees | D11: =E11/$E$34 -> 0.053365608 | E11: 3135000 | F11: =E11/'Inputs & Drivers'!$E$8 -> 10450
B12: A&E | D12: =E12/$E$34 -> 0.035321734 | E12: 2075000 | F12: =E12/'Inputs & Drivers'!$E$8 -> 6916.6667
B13: Legal | D13: =E13/$E$34 -> 0.0042556306 | E13: 250000 | F13: =E13/'Inputs & Drivers'!$E$8 -> 833.33333
B14: Contingency | D14: =E14/$E$34 -> 0 | E14: 0 | F14: =E14/'Inputs & Drivers'!$E$8 -> 0
B15: Soft Costs | D15: =SUM(D11:D14) -> 0.092942973 | E15: =SUM(E11:E14) -> 5460000 | F15: =SUM(F11:F14) -> 18200
B17: Site Development | D17: =E17/$E$34 -> 0.0025533784 | E17: 150000 | F17: =E17/'Inputs & Drivers'!$E$8 -> 500
B18: Shell Construction | D18: =E18/$E$34 -> 0.71494594 | E18: 42000000 | F18: =E18/'Inputs & Drivers'!$E$8 -> 140000
B19: FF&E | D19: =E19/$E$34 -> 0.011915766 | E19: 700000 | F19: =E19/'Inputs & Drivers'!$E$8 -> 2333.3333
B20: Contingency | D20: =E20/$E$34 -> 0.028087162 | E20: 1650000 | F20: =E20/'Inputs & Drivers'!$E$8 -> 5500
B21: Hard Costs | D21: =SUM(D17:D20) -> 0.75750225 | E21: =SUM(E17:E20) -> 44500000 | F21: =SUM(F17:F20) -> 148333.33
B23: Development Fee | D23: =E23/$E$34 -> 0.029789414 | E23: 1750000 | F23: =E23/'Inputs & Drivers'!$E$8 -> 5833.3333
B24: Additional Contingency | D24: =E24/$E$34 -> 0 | E24: 0 | F24: =E24/'Inputs & Drivers'!$E$8 -> 0
B25: Other Development Costs | D25: =SUM(D23:D24) -> 0.029789414 | E25: =SUM(E23:E24) -> 1750000 | F25: =SUM(F23:F24) -> 5833.3333
B27: Total Unlevered Costs | D27: =D25+D21+D15+D9 -> 0.97726302 | E27: =E25+E21+E15+E9 -> 57410000 | F27: =F25+F21+F15+F9 -> 191366.67
B29: Financing Fees | D29: =E29/$E$34 -> 0.006809009 | E29: =-Model!H150 -> 400000 | F29: =E29/'Inputs & Drivers'!$E$8 -> 1333.3333
B30: Interest Reserve | D30: =E30/$E$34 -> 0.015454495 | E30: ='Inputs & Drivers'!J25 -> 907885.1 | F30: =E30/'Inputs & Drivers'!$E$8 -> 3026.2837
B31: Operating Reserve | D31: =E31/$E$34 -> 0.00047347977 | E31: ='Inputs & Drivers'!J26 -> 27814.901 | F31: =E31/'Inputs & Drivers'!$E$8 -> 92.716335
B32: Financing Costs | D32: =SUM(D29:D31) -> 0.022736983 | E32: =SUM(E29:E31) -> 1335700 | F32: =SUM(F29:F31) -> 4452.3333
B34: Total Development Costs | D34: =D27+D32 -> 1 | E34: =E27+E32 -> 58745700 | F34: =F27+F32 -> 195819
B36: Contingencies
B37: Soft Cost Contingency | D37: % of Soft Costs | E37: =E14 -> 0 | F37: =E37/$E$34 -> 0
B38: Hard Cost Contingency | D38: % of Hard Costs | E38: =E20 -> 1650000 | F38: =E38/$E$34 -> 0.028087162
B39: Additional Contingency | E39: =E24 -> 0 | F39: =E39/$E$34 -> 0
B40: Total | D40: % of Total Development Costs | E40: =SUM(E37:E39) -> 1650000 | F40: =E40/$E$34 -> 0.028087162
B42: Fees
B43: Development Fee | E43: % of Land + Hard + Soft Costs (excl. contingency) | F43: {=E23/SUM(E6:E8+E11:E13+E17:E19)} -> 0.032401407
B45: Sources of Financing
B46: Equity | F46: =F48-F47 -> 18745700
B47: Debt | F47: ='Inputs & Drivers'!J16 -> 40000000
B48: Total | F48: =E34 -> 58745700
